Workbook
Name Academic_Date: Form_Setup!$B$8:$C$8
Name Academic_End_Date: Form_Setup!$C$8
Name Academic_End_Date: Form_Setup!$C$8
Name Academic_End_Date: Form_Setup!$C$8
Name Academic_End_Date: Form_Setup!$C$8
Name Academic_End_Year: constants!$E$2
Name Academic_End_Year: constants!$E$2
Name Academic_End_Year: constants!$E$2
Name Academic_End_Year: constants!$E$2
Name Academic_Start_Date: Form_Setup!$B$8
Name Academic_Start_Date: Form_Setup!$B$8
Name Academic_Start_Date: Form_Setup!$B$8
Name Academic_Start_Date: Form_Setup!$B$8
Name Academic_Start_Year: constants!$D$2
Name Academic_Start_Year: constants!$D$2
Name Academic_Start_Year: constants!$D$2
Name Academic_Start_Year: constants!$D$2
Name AcademicYear_ID: constants!$B$2
Name AcademicYear_ID: constants!$B$2
Name AcademicYear_ID: constants!$B$2
Name AcademicYear_ID: constants!$B$2
Name AcademicYear_List: constants!$A$2:$B$2
Name AcademicYear_Name: constants!$A$2
Name AcademicYear_Name: constants!$A$2
Name AcademicYear_Name: constants!$A$2
Name AcademicYear_Name: constants!$A$2
Name Age_ID: constants!$A$91:$A$111
Name Age_List: constants!$A$91:$B$111
Name Age_List: constants!$A$91:$B$111
Name Age_List: constants!$A$91:$B$111
Name Age_List: constants!$A$91:$B$111
Name Age_Name: constants!$B$91:$B$111
Name Age_Name: constants!$B$91:$B$111
Name Age_Name: constants!$B$91:$B$111
Name Age_Name: constants!$B$91:$B$111
Name Attrition_ID: constants!$A$16:$A$22
Name Attrition_List: constants!$A$16:$B$22
Name Attrition_Name: constants!$B$16:$B$22
Name District_Name_EN: Form_Setup!$K$4
Name District_PCode: Form_Setup!$J$4
Name Document_Code: constants!$F$79:$F$96
Name Electricity_Availability: 'SA-2'!$D$85
Name Electricity_Availability: 'SA-2'!$D$85
Name Electricity_Availability: 'SA-2'!$D$85
Name Electricity_Availability: 'SA-2'!$D$85
Name ElectricityAvailability_ID: constants!$E$65:$E$72
Name ElectricityAvailability_List: constants!$E$65:$F$72
Name ElectricityAvailability_Name: constants!$F$65:$F$72
Name ExpenditureType_ID: Form_Setup!$I$8:$I$9
Name ExpenditureType_List: Form_Setup!$I$8:$J$9
Name ExpenditureType_Name: Form_Setup!$J$8:$J$9
Name Facility_ID: constants!$A$120:$A$149
Name Facility_List: constants!$A$120:$B$149
Name Facility_List: constants!$A$120:$B$149
Name Facility_List: constants!$A$120:$B$149
Name Facility_List: constants!$A$120:$B$149
Name Facility_Name: constants!$B$120:$B$149
Name Facility_Name: constants!$B$120:$B$149
Name Facility_Name: constants!$B$120:$B$149
Name Facility_Name: constants!$B$120:$B$149

Sheet Sheet1
B1: 41273 | C1: =UPPER(LEFT(TEXT(B1,D$1&D$1&D$1),1)) -> S | D1: =DL -> d | E1: =" " & C1 & " " & C2 & " " & C3 & " " & C4 & " " & C5 & " " & C6 & " " & C7 -> S M T W T F S
B2: 41274 | C2: =UPPER(LEFT(TEXT(B2,D$1&D$1&D$1),1)) -> M | E2: =" " & C2 & " " & C3 & " " & C4 & " " & C5 & " " & C6 & " " & C7 & " " & C8 -> M T W T F S S
B3: 41275 | C3: =UPPER(LEFT(TEXT(B3,D$1&D$1&D$1),1)) -> T
B4: 41276 | C4: =UPPER(LEFT(TEXT(B4,D$1&D$1&D$1),1)) -> W
B5: 41277 | C5: =UPPER(LEFT(TEXT(B5,D$1&D$1&D$1),1)) -> T
B6: 41278 | C6: =UPPER(LEFT(TEXT(B6,D$1&D$1&D$1),1)) -> F
B7: 41279 | C7: =UPPER(LEFT(TEXT(B7,D$1&D$1&D$1),1)) -> S
B8: 41280 | C8: =UPPER(LEFT(TEXT(B8,D$1&D$1&D$1),1)) -> S

Sheet constants
B1: Academic Year ID | D1: Academic Start Year | E1: Academic End Year | G1: Not Applicable Sign | AH1: Academic_Date | AN1: MyanmarLetter_ID | AO1: MyanmarLetter_MM | AP1: MyanmarLetter_EN | AQ1: MyanmarLetter_EnglishSymbol
A2: =Academic_Start_Year & "-" & Academic_End_Year -> 2013-2014 | B2: =Academic_End_Year -> 2014 | D2: =TEXT(Academic_Start_Date,"yyyy") -> 2013 | E2: =TEXT(Academic_End_Date,"yyyy") -> 2014 | G2: N/A | AH2: Academic_End_Date | AN2: 01 | AO2: က | AP2: KA | AQ2: A
AH3: Academic_End_Year | AN3: 02 | AO3: ခ | AP3: KHA | AQ3: B
AH4: Academic_Start_Date | AN4: 03 | AO4: ဂ | AP4: GA | AQ4: C | AW4: Academic_Date | AX4: =Form_Setup!$B$7:$C$7
AH5: Academic_Start_Year | AN5: 04 | AO5: ဃ | AP5: GHA | AQ5: D | AS5: NRCState_ID | AT5: NRCState_Name | AW5: Academic_End_Date | AX5: =Form_Setup!$C$7
AH6: AcademicYear_ID | AN6: 05 | AO6: င | AP6: NGA | AQ6: E | AS6: 1 | AT6: Kachin | AW6: Academic_End_Year | AX6: =constants!$E$2
P7: =IF(LEN(I26)=1,"0"& I26,""&I26) -> 01 | AH7: AcademicYear_List | AN7: 06 | AO7: စ | AP7: CA | AQ7: F | AS7: 2 | AT7: Kayah | AW7: Academic_Start_Date | AX7: =Form_Setup!$B$7
A8: Identity Type ID | B8: Identity Type_Code | C8: IdentityType_EN | D8: IdentityType_MM | E8: SchoolPost ID | F8: SchoolPost Name | G8: SchoolPost_SortCode | I8: LeaveType_ID | J8: LeaveType_Name | P8: 1 | T8: 1 | AB8: 1 | AH8: AcademicYear_Name | AJ8: 1 | AN8: 07 | AO8: ဆ | AP8: CHA | AQ8: G | AS8: 3 | AT8: Kayin | AW8: Academic_Start_Year | AX8: =constants!$D$2
A9: 1 | B9: n | C9: Naing | D9: နိုင် | E9: 1 | F9: School Principals | G9: 1 | I9: 1 | J9: Other Duty | N9: 1 | P9: 1 | T9: 1 | AH9: Age_ID | AN9: 08 | AO9: ဇ | AP9: JA | AQ9: H | AS9: 4 | AT9: Chin | AW9: AcademicYear_ID | AX9: =constants!$B$2
A10: 2 | B10: e | C10: Eaet | D10: ဧည့် | E10: 2 | F10: SAT | G10: 2 | I10: 2 | J10: Certified Leave | AH10: Age_List | AN10: 09 | AO10: ဈ | AP10: JHA | AQ10: I | AS10: 5 | AT10: Sagaing | AW10: AcademicYear_List | AX10: =constants!$A$2:$B$2
A11: 3 | B11: p | C11: Pu | D11: ပြု | E11: 3 | F11: SAT (Physical Training) | G11: 2 | I11: 3 | J11: Uncertified Leave | AH11: Age_Name | AN11: 10 | AO11: ဉ | AP11: NYA | AS11: 6 | AT11: Taninthayi | AW11: AcademicYear_Name | AX11: =constants!$A$2
A12: 4 | B12: y | C12: Yaryee | D12: ယာယီ | E12: 4 | F12: JAT | G12: 3 | AA12: Module_ID | AB12: Grade_ID | AC12: TextBook_ID | AD12: Subject_ID | AE12: TextBook_Name | AH12: Attrition_ID | AN12: 11 | AO12: ည | AP12: NNYA | AQ12: J | AS12: 7 | AT12: Bago | AW12: Age_ID | AX12: =constants!$A$91:$A$111
E13: 5 | F13: JAT (Physical Training) | G13: 3 | AA13: 0101 | AB13: 01 | AC13: 01 | AD13: 2 | AE13: မြန်မာစာ | AH13: Attrition_List | AN13: 12 | AO13: ဋ | AP13: TTA | AQ13: K | AS13: 8 | AT13: Magway | AW13: Age_List | AX13: =constants!$A$91:$B$111
E14: 6 | F14: JAT 2 | G14: 4 | AA14: 0116 | AB14: 01 | AC14: 16 | AD14: 3 | AE14: အင်္ဂလိပ်စာ | AH14: Attrition_Name | AN14: 13 | AO14: ဌ | AP14: TTHA | AQ14: L | AS14: 9 | AT14: Mandalay | AW14: Age_Name | AX14: =constants!$B$91:$B$111
A15: Attrition ID | B15: Type of Attrition | E15: 7 | F15: PAT | G15: 5 | AA15: 0117 | AB15: 01 | AC15: 17 | AD15: 4 | AE15: သင်္ချာ | AH15: District_Name_EN | AN15: 14 | AO15: ဍ | AP15: DDA | AQ15: M | AS15: 10 | AT15: Mon | AW15: Attrition_ID | AX15: =constants!$A$16:$A$22
A16: 1 | B16: Super Annulations | E16: 8 | F16: Office Clerk | G16: 6 | AA16: 0120 | AB16: 01 | AC16: 20 | AD16: 6 | AE16: သဘာဝသိပ္ပံ | AH16: District_PCode | AN16: 15 | AO16: ဎ | AP16: DDHA | AQ16: N | AS16: 11 | AT16: Rakine | AW16: Attrition_List | AX16: =constants!$A$16:$B$22
A17: 2 | B17: Service pension | E17: 9 | F17: JAT 3 | G17: 7 | AA17: 0123 | AB17: 01 | AC17: 23 | AD17: 14 | AE17: ဘဝတွက်တာကျွမ်းကျင်စရာ | AH17: DL | AN17: 16 | AO17: ဏ | AP17: NNA | AQ17: O | AS17: 12 | AT17: Yangon | AW17: Attrition_Name | AX17: =constants!$B$16:$B$22
A18: 3 | B18: Other pension | E18: 10 | F18: Cleaner/ Guard | G18: 8 | AA18: 0201 | AB18: 02 | AC18: 01 | AD18: 2 | AE18: မြန်မာစာ | AH18: Document_Code | AN18: 17 | AO18: တ | AP18: TA | AQ18: P | AS18: 13 | AT18: Shan | AW18: District_Name_EN | AX18: =Form_Setup!$K$3
A19: 4 | B19: Transfer to other dept | AA19: 0216 | AB19: 02 | AC19: 16 | AD19: 3 | AE19: အင်္ဂလိပ်စာ | AH19: Electricity_Availability | AN19: 18 | AO19: ထ | AP19: THA | AQ19: Q | AS19: 14 | AT19: Ayeyarwady | AW19: District_PCode | AX19: =Form_Setup!$J$3
A20: 5 | B20: Resign | AA20: 0217 | AB20: 02 | AC20: 17 | AD20: 4 | AE20: သင်္ချာ | AH20: ElectricityAvailability_ID | AN20: 19 | AO20: ဒ | AP20: DA | AQ20: R | AS20: 15 | AT20: Naypyitaw | AW20: DL | AX20: =INDEX(GET.WORKSPACE(37+NOW()*0),21)
A21: 6 | B21: Dismiss | AA21: 0220 | AB21: 02 | AC21: 20 | AD21: 6 | AE21: သဘာဝသိပ္ပံ | AH21: ElectricityAvailability_List | AN21: 20 | AO21: ဓ | AP21: DHA | AQ21: S | AW21: Document_Code | AX21: =constants!$F$79:$F$96
A22: 7 | B22: Deceased | AA22: 0223 | AB22: 02 | AC22: 23 | AD22: 14 | AE22: ဘဝတွက်တာကျွမ်းကျင်စရာ | AH22: ElectricityAvailability_Name | AN22: 21 | AO22: န | AP22: NA | AQ22: T | AW22: Electricity_Availability | AX22: ='SA-2'!$D$85
AA23: 0301 | AB23: 03 | AC23: 01 | AD23: 2 | AE23: မြန်မာစာ | AH23: ExpenditureType_ID | AN23: 22 | AO23: ပ | AP23: PA | AQ23: U | AW23: ElectricityAvailability_ID | AX23: =constants!$E$65:$E$72
A24: School Level ID | B24: School Level Short Name | C24: SchoolLevel_SortCode | AA24: 0316 | AB24: 03 | AC24: 16 | AD24: 3 | AE24: အင်္ဂလိပ်စာ | AH24: ExpenditureType_List | AN24: 23 | AO24: ဖ | AP24: PHA | AQ24: V | AW24: ElectricityAvailability_List | AX24: =constants!$E$65:$F$72
A25: 1 | B25: SHS | C25: 1 | I25: Grade_ID | J25: Grade_Name | K25: GradeSort_Code | AA25: 0317 | AB25: 03 | AC25: 17 | AD25: 4 | AE25: သင်္ချာ | AH25: ExpenditureType_Name | AN25: 24 | AO25: ဗ | AP25: BA | AQ25: W | AW25: ElectricityAvailability_Name | AX25: =constants!$F$65:$F$72
A26: 2 | B26: SMS | C26: 2 | I26: 01 | J26: Grade 1 | K26: 2 | AA26: 0320 | AB26: 03 | AC26: 20 | AD26: 6 | AE26: သဘာဝသိပ္ပံ | AH26: Form_ID | AN26: 25 | AO26: ဘ | AP26: BHA | AQ26: X | AW26: ExpenditureType_ID | AX26: =Form_Setup!$I$7:$I$8
A27: 3 | B27: SPS | C27: 3 | I27: 02 | J27: Grade 2 | K27: 3 | Q27: SectionID | R27: SectionName | S27: SectionSort_Code | U27: =IF(LEN(V28)=1,"0"& V28,""&V28) -> 01 | V27: TextBook_ID | W27: TextBook_EN | X27: TextBook_MM | Y27: Subject_ID | AA27: 0323 | AB27: 03 | AC27: 23 | AD27: 14 | AE27: ဘဝတွက်တာကျွမ်းကျင်စရာ | AH27: Form_List | AN27: 26 | AO27: မ | AP27: MA | AQ27: Y | AW27: ExpenditureType_List | AX27: =Form_Setup!$I$7:$J$8
A28: 4 | B28: Br- High | C28: 5 | I28: 03 | J28: Grade 3 | K28: 4 | Q28: 01 | R28: Special | S28: 1 | V28: 01 | W28: Myanmar | X28: မြန်မာစာ | Y28: 2 | AA28: 391 | AB28: 04 | AC28: 01 | AD28: 2 | AE28: မြန်မာစာ | AH28: Form_Name | AN28: 27 | AO28: ယ | AP28: YA | AQ28: Z | AW28: ExpenditureType_Name | AX28: =Form_Setup!$J$7:$J$8
A29: 5 | B29: Br-Mid | C29: 6 | I29: 04 | J29: Grade 4 | K29: 5 | Q29: 02 | R29: A | S29: 2 | V29: 02 | W29: Myanmar Reader | X29: မြန်မာဖတ်စာ | Y29: 2 | AA29: 0416 | AB29: 04 | AC29: 16 | AD29: 3 | AE29: အင်္ဂလိပ်စာ | AH29: FormPost_31 | AN29: 28 | AO29: ရ | AP29: RA | AQ29: AA | AW29: Facility_ID | AX29: =constants!$A$120:$A$149
A30: 6 | B30: Br-Pri | C30: 7 | I30: 05 | J30: Grade 5 | K30: 6 | Q30: 03 | R30: B | S30: 3 | V30: 03 | W30: Myanmar Grammar | X30: မြန်မာသဒ္ဒါ | Y30: 2 | AA30: 0417 | AB30: 04 | AC30: 17 | AD30: 4 | AE30: သင်္ချာ | AH30: FormPost_312_First | AN30: 29 | AO30: လ | AP30: LA | AQ30: BB | AW30: Facility_List | AX30: =constants!$A$120:$B$149
A31: 7 | B31: Af-High | C31: 8 | I31: 06 | J31: Grade 6 | K31: 7 | Q31: 04 | R31: C | S31: 4 | V31: 04 | W31: Myanmar Zartaka stories | X31: မြန်မာဇာတကဝတ္ထုတိုပျား | Y31: 2 | AA31: 0425 | AB31: 04 | AC31: 25 | AD31: 5 | AE31: ပထဝီဝင်သမိုင်း | AH31: FormPost_312_Second | AN31: 30 | AO31: ဝ | AP31: WA | AQ31: CC | AW31: Facility_Name | AX31: =constants!$B$120:$B$149
A32: 8 | B32: Af-Mid | C32: 9 | E32: 1 | I32: 07 | J32: Grade 7 | K32: 8 | Q32: 05 | R32: D | S32: 5 | V32: 05 | W32: Mahawtada | X32: မဟော်သဓာ | Y32: 2 | AA32: 0421 | AB32: 04 | AC32: 21 | AD32: 6 | AE32: အခြေခံသိပ္ပံ | AH32: FormPost_32 | AN32: 31 | AO32: သ | AP32: SA | AQ32: DD | AW32: Form_ID | AX32: =constants!$E$79:$E$96
A33: 9 | B33: Af-Pri | C33: 10 | I33: 08 | J33: Grade 8 | K33: 9 | Q33: 06 | R33: E | S33: 6 | V33: 06 | W33: Myanmar poems | X33: မြန်မာကဗျာ | Y33: 2 | AA33: 0423 | AB33: 04 | AC33: 23 | AD33: 14 | AE33: ဘဝတွက်တာကျွမ်းကျင်စရာ | AH33: FormPost_33 | AN33: 32 | AO33: ဟ | AP33: HA | AQ33: EE | AW33: Form_List | AX33: =constants!$E$78:$G$96
A34: 10 | B34: Post- Pri | C34: 4 | I34: 09 | J34: Grade 9 | K34: 10 | Q34: 07 | R34: F | S34: 7 | V34: 07 | W34: Myanmar selected poems | X34: မြန်မာကဗျာလက်ရွေးစဉ် | Y34: 2 | AA34: 0424 | AB34: 04 | AC34: 24 | AD34: 14 | AE34: ပြည်ထောင်စုစိတ်ဓာတ် | AH34: FormPost_34_Aug | AN34: 33 | AO34: ဠ | AP34: LLA | AQ34: FF | AW34: Form_Name | AX34: =constants!$G$79:$G$96
A35: 11 | B35: Monastic | C35: 11 | I35: 10 | J35: Grade 10 | K35: 11 | Q35: 08 | R35: G | S35: 8 | V35: 08 | W35: Compulsory Myanmar Prose | X35: ပင်ရင်းစကားပြေ | Y35: 2 | AA35: 0428 | AB35: 04 | AC35: 28 | AD35: 8 | AE35: မြန်မာ့သမိုင်း အတွဲ၂ | AH35: FormPost_34_Feb | AN35: 34 | AO35: အ | AP35: A | AQ35: GG | AW35: FormDate_31 | AX35: ='SA-1'!$P$114
A36: 12 | B36: Community | C36: 12 | I36: 11 | J36: Grade 11 | K36: 12 | Q36: 09 | R36: H | S36: 9 | V36: 09 | W36: Writing Myanmar Poetry | X36: မြန်မာကဗျာဖွဲ့နည်း | Y36: 2 | AA36: 0501 | AB36: 05 | AC36: 01 | AD36: 2 | AE36: မြန်မာစာ | AH36: FormPost_34_Nov | AN36: 35 | AO36: ဧ | AP36: E | AW36: FormPost_31 | AX36: ='SA-1'!$P$113
I37: 101 | J37: ECD | K37: 1 | Q37: 10 | R37: I | S37: 10 | V37: 10 | W37: Myanmar short stories | X37: မြန်မာဝတ္ထုတိုများ | Y37: 2 | AA37: 0516 | AB37: 05 | AC37: 16 | AD37: 3 | AE37: အင်္ဂလိပ်စာ | AH37: FormPost_37 | AN37: 36 | AO37: ဥ | AP37: U | AQ37: HH | AW37: FormPost_312_First | AX37: =PCET2_First!$AJ$8
Q38: 11 | R38: J | S38: 11 | V38: 11 | W38: Potetawwarda Pjou | X38: ပုတ္တောဝါဒပျို့ | Y38: 2 | AA38: 0517 | AB38: 05 | AC38: 17 | AD38: 4 | AE38: သင်္ချာ | AH38: FormPost_38 | AN38: 37 | AO38: A | AW38: FormPost_312_Second | AX38: =PCET2_Second!$AJ$8
A39: SchoolLevelExist _ID | B39: School Level Exist Name | Q39: 12 | R39: K | S39: 12 | V39: 12 | W39: Yaethe Play | X39: ရေသည်ပြဇာတ် | Y39: 2 | AA39: 0525 | AB39: 05 | AC39: 25 | AD39: 5 | AE39: ပထဝီဝင်သမိုင်း | AH39: FormPost_39 | AN39: 38 | AO39: B | AW39: FormPost_32 | AX39: ='SA-2'!$V$98
A40: 1 | B40: Pri | E40: LandOwnershipType_ID | F40: LandOwnershipType_Name | Q40: 13 | R40: L | S40: 13 | V40: 13 | W40: Mg Yin Mg, Ma Mae Ma | X40: မောင်ရင်မောင်မမယ်မ | Y40: 2 | AA40: 0521 | AB40: 05 | AC40: 21 | AD40: 6 | AE40: အခြေခံသိပ္ပံ | AH40: FormSignPost_List | AN40: 39 | AO40: C | AW40: FormPost_33 | AX40: ='SA-3'!$W$9
A41: 2 | B41: Mid | E41: 1 | F41: Govt | Q41: 14 | R41: M | S41: 14 | V41: 14 | W41: History of Myanmar literature | X41: မြန်မာစာပေသမိုင်း | Y41: 2 | AA41: 0523 | AB41: 05 | AC41: 23 | AD41: 14 | AE41: ဘဝတွက်တာကျွမ်းကျင်စရာ | AH41: FormSignPost_Name | AN41: 40 | AO41: D | AW41: FormPost_34_Aug | AX41: ='SA-4_Aug'!$K$83
A42: 3 | B42: Mid & Pri | E42: 2 | F42: Monastery | Q42: 15 | R42: N | S42: 15 | V42: 15 | W42: Thanwara Pjou | X42: သံဝရပျို့ | Y42: 2 | AA42: 0524 | AB42: 05 | AC42: 24 | AD42: 14 | AE42: ပြည်ထောင်စုစိတ်ဓာတ် | AH42: Grade_Code | AN42: 41 | AO42: E | AW42: FormPost_34_Feb | AX42: ='SA-4_Feb'!$K$83
A43: 4 | B43: High | E43: 3 | F43: Private | Q43: 16 | R43: O | S43: 16 | V43: 16 | W43: English | X43: အင်္ဂလိပ်စာ | Y43: 3 | AA43: 0528 | AB43: 05 | AC43: 28 | AD43: 8 | AE43: မြန်မာ့သမိုင်း အတွဲ၂ | AH43: Grade_ID | AN43: 42 | AO43: F | AW43: FormPost_34_Nov | AX43: ='SA-4_Nov'!$K$78
A44: 5 | B44: High & Pri | E44: 4 | F44: Faith | Q44: 17 | R44: P | S44: 17 | V44: 17 | W44: Maths | X44: သင်္ချာ | Y44: 4 | AA44: 0602 | AB44: 06 | AC44: 02 | AD44: 2 | AE44: မြန်မာဖတ်စာ | AH44: Grade_List | AN44: 43 | AO44: G | AW44: FormPost_37 | AX44: ='PA-1'!$T$9
A45: 6 | B45: High & Mid | E45: 5 | F45: Other | Q45: 18 | R45: Q | S45: 18 | V45: 18 | W45: Maths 1 | X45: သင်္ချာ ၁ | Y45: 4 | AA45: 0603 | AB45: 06 | AC45: 03 | AD45: 2 | AE45: မြန်မာသဒ္ဒါ | AH45: Grade_Name | AN45: 44 | AO45: H | AW45: FormPost_38 | AX45: ='PA-2'!$AI$49
A46: 7 | B46: High, Mid & Pri | Q46: 19 | R46: R | S46: 19 | V46: 19 | W46: Maths 2 | X46: သင်္ချာ ၂ | Y46: 4 | AA46: 0616 | AB46: 06 | AC46: 16 | AD46: 3 | AE46: အင်္ဂလိပ်စာ | AH46: 1 | AN46: 45 | AO46: I | AW46: FormPost_39 | AX46: ='PA-3'!$P$9
E47: OfficeStaff ID | F47: OfficeStaff Name | G47: OfficePost_SortCode | Q47: 20 | R47: S | S47: 20 | V47: 20 | W47: Natural Science | X47: သဘာဝသိပ္ပံ | Y47: 6 | AA47: 0618 | AB47: 06 | AC47: 18 | AD47: 4 | AE47: သင်္ချာ ၁ | AH47: Grade1_Code | AN47: 46 | AO47: J | AW47: FormSignedName_31 | AX47: ='SA-1'!$P$112
A48: FormSignPost_ID | B48: FormSignPost_Name | E48: 1 | F48: TEO | G48: 1 | Q48: 21 | R48: T | S48: 21 | V48: 21 | W48: Basic Science | X48: အခြေခံသိပ္ပံ | Y48: 6 | AA48: 0619 | AB48: 06 | AC48: 19 | AD48: 4 | AE48: သင်္ချာ ၂ | AH48: Grade1_Name | AN48: 47 | AO48: K | AW48: FormSignPost_List | AX48: =constants!$A$49:$B$61
A49: 1 | B49: TEO | E49: 2 | F49: DTEO | G49: 2 | Q49: 22 | R49: U | S49: 22 | V49: 22 | W49: General Science | X49: အထွေထွေသိပ္ပံ | Y49: 6 | AA49: 0631 | AB49: 06 | AC49: 31 | AD49: 7 | AE49: ပထဝီဝင် | AH49: Grade11RowEnd | AI49: 1 | AN49: 48 | AO49: L | AW49: FormSignPost_Name | AX49: =constants!$B$49:$B$61
A50: 2 | B50: DTEO | E50: 3 | F50: ATEO | G50: 3 | Q50: 23 | R50: V | S50: 23 | V50: 23 | W50: Life Skills | X50: ဘဝတွက်တာကျွမ်းကျင်စရာ | Y50: 14 | AA50: 0626 | AB50: 06 | AC50: 26 | AD50: 8 | AE50: သမိုင်း | AH50: Grade3To8_List | AN50: 49 | AO50: M | AW50: Grade_Code | AX50: =constants!$I$26:$I$37
A51: 3 | B51: ATEO | E51: 4 | F51: Clerical staff Grade 2 | G51: 4 | Q51: 24 | R51: W | S51: 24 | V51: 24 | W51: Union Spirit | X51: ပြည်ထောင်စုစိတ်ဓာတ် | Y51: 14 | AA51: 0622 | AB51: 06 | AC51: 22 | AD51: 6 | AE51: အထွေထွေသိပ္ပံ | AH51: Grade8RowEnd | AN51: 50 | AO51: N | AW51: Grade_ID | AX51: =constants!$I$26:$I$37
A52: 4 | B52: Clerical staff Grade 2 | E52: 5 | F52: Lab technician 3 | G52: 5 | Q52: 25 | R52: X | S52: 25 | V52: 25 | W52: Geography/History | X52: ပထဝီဝင်သမိုင်း | Y52: 5 | AA52: 0628 | AB52: 06 | AC52: 28 | AD52: 8 | AE52: မြန်မာ့သမိုင်း အတွဲ၂ | AH52: Grade9To11_List | AN52: 51 | AO52: O | AW52: Grade_List | AX52: =constants!$I$26:$K$37
A53: 5 | B53: Lab technician 3 | E53: 6 | F53: Clerical staff Grade 1 | G53: 6 | Q53: 26 | R53: Y | S53: 26 | V53: 26 | W53: History | X53: သမိုင်း | Y53: 8 | AA53: 0702 | AB53: 07 | AC53: 02 | AD53: 2 | AE53: မြန်မာဖတ်စာ | AH53: GradeAll_List | AN53: 52 | AO53: P | AW53: Grade_Name | AX53: =constants!$J$26:$J$37
A54: 6 | B54: Clerical staff Grade 1 | E54: 7 | F54: Driver | G54: 7 | Q54: 27 | R54: Z | S54: 27 | V54: 27 | W54: Myanmar History | X54: မြန်မာ့သမိုင်း | Y54: 8 | AA54: 0703 | AB54: 07 | AC54: 03 | AD54: 2 | AE54: မြန်မာသဒ္ဒါ | AH54: GradeSection | AN54: 53 | AO54: Q | AW54: Grade_SortCode | AX54: =constants!$K$26:$K$37
A55: 7 | B55: School Principals | E55: 8 | F55: Copier Machine Helper | G55: 8 | V55: 28 | W55: Myanmar History 2 | X55: မြန်မာ့သမိုင်း အတွဲ၂ | Y55: 8 | AA55: 0716 | AB55: 07 | AC55: 16 | AD55: 3 | AE55: အင်္ဂလိပ်စာ | AH55: LandOwnershipType_Name | AN55: 54 | AO55: R | AW55: Grade1_Code | AX55: =constants!$I$26
A56: 8 | B56: SAT | E56: 9 | F56: Office helper | G56: 9 | V56: 29 | W56: World History | X56: ကမ္ဘာ့ သမိုင်း | Y56: 8 | AA56: 0718 | AB56: 07 | AC56: 18 | AD56: 4 | AE56: သင်္ချာ ၁ | AH56: LandType_ID | AN56: 55 | AO56: S | AW56: Grade1_Name | AX56: =constants!$J$26
A57: 9 | B57: SAT (Physical Training) | E57: 10 | F57: Sweeper | G57: 10 | V57: 30 | W57: Myanmar Yodaya History | X57: မြန်မာယိုးဒယားသမိုင်း | Y57: 8 | AA57: 0719 | AB57: 07 | AC57: 19 | AD57: 4 | AE57: သင်္ချာ ၂ | AH57: LandType_List | AN57: 56 | AO57: T | AW57: Grade11RowEnd | AX57: =SUM('PA-1'!Grade09Count,'PA-1'!Grade10Count,'PA-1'!Grade11Count)
A58: 10 | B58: JAT | E58: 11 | F58: Worker (Garden) | G58: 11 | V58: 31 | W58: Geography | X58: ပထဝီဝင် | Y58: 7 | AA58: 0731 | AB58: 07 | AC58: 31 | AD58: 7 | AE58: ပထဝီဝင် | AH58: LandType_Name | AN58: 57 | AO58: U | AW58: Grade3To8_List | AX58: =OFFSET('PA-1'!$C$21,'PA-1'!Grade3RowStart-0,1,Grade8RowEnd,5)
A59: 11 | B59: JAT (Physical Training) | E59: 12 | F59: Watchman (School) | G59: 12 | V59: 32 | W59: Economics | X59: ဘောဂဗေဒ | Y59: 12 | AA59: 0726 | AB59: 07 | AC59: 26 | AD59: 8 | AE59: သမိုင်း | AH59: Language_ID | AN59: 58 | AO59: V | AW59: Grade8RowEnd | AX59: =SUM('PA-1'!Grade03Count,'PA-1'!Grade04Count,'PA-1'!Grade05Count,'PA-1'!Grade06Count,'PA-1'!Grade07Count,'PA-1'!Grade08Count)
A60: 12 | B60: JAT 2 | E60: 13 | F60: Lab helper | G60: 13 | V60: 33 | W60: Physics | X60: ရူပဗေဒ | Y60: 9 | AA60: 0722 | AB60: 07 | AC60: 22 | AD60: 6 | AE60: အထွေထွေသိပ္ပံ | AH60: Language_Name | AN60: 59 | AO60: W | AW60: Grade9To11_List | AX60: =OFFSET('PA-1'!$C$21,'PA-1'!Grade9RowStart-0,1,Grade11RowEnd,5)
A61: 13 | B61: PAT | E61: 14 | F61: General worker | G61: 14 | V61: 34 | W61: Chemistry | X61: ဓာတုဗေဒ | Y61: 10 | AA61: 0728 | AB61: 07 | AC61: 28 | AD61: 8 | AE61: မြန်မာ့သမိုင်း အတွဲ၂ | AH61: Module_ID | AN61: 60 | AO61: X | AW61: GradeAll_List | AX61: =OFFSET('PA-1'!$C$21,1,0,RowCount_GradeSection,6)
V62: 35 | W62: Biology | X62: ဇီဝဗေဒ | Y62: 11 | AA62: 0804 | AB62: 08 | AC62: 04 | AD62: 2 | AE62: မြန်မာဇာတကဝတ္ထုတိုပျား | AH62: Module_List | AN62: 61 | AO62: Y | AW62: GradeSection | AX62: ='PA-1'!$D$22:$D$41
A63: WaterSource_ID | B63: WaterSource_Name | J63: 1 | V63: 36 | W63: General Arts | Y63: 5 | AA63: 0805 | AB63: 08 | AC63: 05 | AD63: 2 | AE63: မဟော်သဓာ | AH63: Month_ID | AN63: 62 | AO63: Z | AW63: LandOwnershipType_Name | AX63: =constants!$F$41:$F$45
A64: 1 | B64: In school compound | E64: ElectricityAvailability_ID | F64: ElectricityAvailability_Name | AA64: 0803 | AB64: 08 | AC64: 03 | AD64: 2 | AE64: မြန်မာသဒ္ဒါ | AH64: Month_List | AW64: LandType_ID | AX64: =constants!$A$70:$A$72
A65: 2 | B65: <100 ft | E65: 1 | F65: No electricity | AA65: 0806 | AB65: 08 | AC65: 06 | AD65: 2 | AE65: မြန်မာကဗျာ | AH65: Month_Name | AW65: LandType_List | AX65: =constants!$A$70:$B$72
A66: 3 | B66: 100-200 ft | E66: 2 | F66: <2 hours | AA66: 0816 | AB66: 08 | AC66: 16 | AD66: 3 | AE66: အင်္ဂလိပ်စာ | AH66: MYA_INFO_TS_ID | AW66: LandType_Name | AX66: =constants!$B$70:$B$72
A67: 4 | B67: > 200 ft | E67: 3 | F67: 2-4 hours | AA67: 0818 | AB67: 08 | AC67: 18 | AD67: 4 | AE67: သင်္ချာ ၁ | AH67: NA_Sign | AW67: Language_ID | AX67: =constants!$E$116:$E$123
E68: 4 | F68: 4-6 hours | AA68: 0819 | AB68: 08 | AC68: 19 | AD68: 4 | AE68: သင်္ချာ ၂ | AH68: NRCType_Code | AW68: Language_Name | AX68: =constants!$F$116:$F$123
A69: LandType_ID | B69: LandType_Name | E69: 5 | F69: 6-8 hours | AA69: 0831 | AB69: 08 | AC69: 31 | AD69: 7 | AE69: ပထဝီဝင် | AH69: NRCType_ID | AW69: Module_ID | AX69: =constants!$AA$13:$AA$118
A70: 1 | B70: Garan | E70: 6 | F70: 8-10 hours | AA70: 0826 | AB70: 08 | AC70: 26 | AD70: 8 | AE70: သမိုင်း | AH70: NRCType_List | AW70: Module_List | AX70: =constants!$AA$13:$AC$118
A71: 2 | B71: Lana39 | E71: 7 | F71: 10-12 hours | K71: 1 | AA71: 0822 | AB71: 08 | AC71: 22 | AD71: 6 | AE71: အထွေထွေသိပ္ပံ | AH71: NRCType_Name | AW71: Month_ID | AX71: =constants!$E$100:$E$111
A72: 3 | B72: F-105 | E72: 8 | F72: 12-14 hours | AA72: 0828 | AB72: 08 | AC72: 28 | AD72: 8 | AE72: မြန်မာ့သမိုင်း အတွဲ၂ | AH72: OfficeStaff_ID | AW72: Month_List | AX72: =constants!$E$100:$F$111
V73: 9 | AA73: 0904 | AB73: 09 | AC73: 04 | AD73: 2 | AE73: မြန်မာဇာတကဝတ္ထုတိုပျား | AH73: PA_1_ID | AW73: Month_Name | AX73: =constants!$F$100:$F$111
AA74: 0905 | AB74: 09 | AC74: 05 | AD74: 2 | AE74: မဟော်သဓာ | AH74: PA_2_ID | AW74: MYA_INFO_TS_ID | AX74: =Form_Setup!$L$3
AA75: 0903 | AB75: 09 | AC75: 03 | AD75: 2 | AE75: မြန်မာသဒ္ဒါ | AH75: PA_3_ID | AW75: MyanmarLetter_EN | AX75: =constants!$AP$2:$AP$37
AA76: 0906 | AB76: 09 | AC76: 06 | AD76: 2 | AE76: မြန်မာကဗျာ | AH76: PCET1_01_ID | AW76: MyanmarLetter_EnglishSymbol | AX76: =constants!$AQ$2:$AQ$37
A77: SchoolShiftType_ID | B77: SchooShiftType_Name | AA77: 0916 | AB77: 09 | AC77: 16 | AD77: 3 | AE77: အင်္ဂလိပ်စာ | AH77: PCET1_02_ID | AW77: MyanmarLetter_ID | AX77: =constants!$AN$2:$AN$37
A78: 1 | B78: One | E78: FormID | F78: Document Code | G78: FormName | K78: 1 | AA78: 0918 | AB78: 09 | AC78: 18 | AD78: 4 | AE78: သင်္ချာ ၁ | AH78: PCET1_06_ID | AW78: MyanmarLetter_List | AX78: =constants!$AN$2:$AQ$37
A79: 2 | B79: Two | E79: 31 | F79: Annex 3.1 | G79: SCHOOL INFORMATION SA-1 | AA79: 0919 | AB79: 09 | AC79: 19 | AD79: 4 | AE79: သင်္ချာ ၂ | AH79: PCET1_07_ID | AW79: MyanmarLetter_MM | AX79: =constants!$AO$2:$AO$37
E80: 32 | F80: Annex 3.2 | G80: SCHOOL INFRASTRUCTURE SA-2 | AA80: 0931 | AB80: 09 | AC80: 31 | AD80: 7 | AE80: ပထဝီဝင် | AH80: PCET1_08_ID | AW80: NA_Sign | AX80: =constants!$G$2
E81: 33 | F81: Annex 3.3 | G81: SCHOOL CATCHMENT AREA SA-3 | AA81: 0926 | AB81: 09 | AC81: 26 | AD81: 8 | AE81: သမိုင်း | AH81: PCET1_09_ID | AW81: NRCState_ID | AX81: =constants!$AN$41:$AN$54
A82: SchoolMediaPlatform_ID | B82: SchoolMediaPlatform_Name | E82: 34 | F82: Annex 3.4 | G82: BUDGET PLAN SA-4 | AA82: 0922 | AB82: 09 | AC82: 22 | AD82: 6 | AE82: အထွေထွေသိပ္ပံ | AH82: PCET1_10_ID | AW82: NRCState_List | AX82: =constants!$AN$41:$AO$54
A83: 1 | B83: Multimedia | E83: 36 | F83: Annex 3.6 | G83: TEARCHER ATTENDANCE | K83: 1 | AA83: 0928 | AB83: 09 | AC83: 28 | AD83: 8 | AE83: မြန်မာ့သမိုင်း အတွဲ၂ | AH83: PCET1_11_ID | AW83: NRCState_Name | AX83: =constants!$AO$41:$AO$54
A84: 2 | B84: 3 Platform | E84: 37 | F84: Annex 3.7 | G84: STUDENT STATUS PA-1 | AA84: 1007 | AB84: 10 | AC84: 07 | AD84: 2 | AE84: မြန်မာကဗျာလက်ရွေးစဉ် | AH84: PCET1_12_ID | AW84: NRCType_Code | AX84: =constants!$B$9:$B$12
A85: 3 | B85: 2 Platform | E85: 38 | F85: Annex 3.8 | G85: STUDENT ENTROLMENT BY AGE PA-2 | AA85: 1008 | AB85: 10 | AC85: 08 | AD85: 2 | AE85: ပင်ရင်းစကားပြေ | AH85: PCET2_01_ID | AW85: NRCType_EN | AX85: =constants!$C$9:$C$12
A86: 4 | B86: 1 Platform | E86: 39 | F86: Annex 3.9 | G86: TEXTBOOKS PA-3 | AA86: 1003 | AB86: 10 | AC86: 03 | AD86: 2 | AE86: မြန်မာသဒ္ဒါ | AH86: PCET2_02_ID | AW86: NRCType_ID | AX86: =constants!$A$9:$A$12
E87: 311 | F87: Annex 3.11 | G87: MONITORING LEARNING ACHIEVEMENT (GRADE 3 TO 8) PCET-1 | AA87: 1009 | AB87: 10 | AC87: 09 | AD87: 2 | AE87: မြန်မာကဗျာဖွဲ့နည်း | AH87: PM01_ID | AW87: NRCType_List | AX87: =constants!$A$9:$D$12
E88: 312 | F88: Annex 3.12 | G88: MONITORING LEARNING ACHIEVEMENT (GRADE 9, 10, 11) PCET-2 | AA88: 1010 | AB88: 10 | AC88: 10 | AD88: 2 | AE88: မြန်မာဝတ္ထုတိုများ | AH88: PM02_ID | AW88: NRCType_MM | AX88: =constants!$D$9:$D$12
E89: 313 | F89: Annex 3.13 | G89: STUDENT STATUS PM | AA89: 1011 | AB89: 10 | AC89: 11 | AD89: 2 | AE89: ပုတ္တောဝါဒပျို့ | AH89: PM03_ID | AW89: OfficeStaff_ID | AX89: =constants!$E$48:$E$61
A90: Age_ID | B90: Age_Name | E90: 41 | F90: Annex 4.1 | G90: TOWNSHIP POPULATION | AA90: 1016 | AB90: 10 | AC90: 16 | AD90: 3 | AE90: အင်္ဂလိပ်စာ | AH90: PM06_ID | AW90: PA_1_ID | AX90: ='Clean_PA_1 _Head'!$A$2
A91: 01 | B91: 3 years | E91: 42 | F91: Annex 4.2 | G91: SANCTION | AA91: 1017 | AB91: 10 | AC91: 17 | AD91: 4 | AE91: သင်္ချာ | AH91: PM07_ID | AW91: PA_2_ID | AX91: ='Clean_PA-2_ Head'!$A$2
A92: 02 | B92: 4 years | AW92: PA_3_ID | AX92: ='Clean_PA-3_ Head'!$A$2
A93: 03 | B93: 5 years | E93: 43 | F93: Annex 4.3 | G93: TEACHER ALLOCATION | AA93: 1033 | AB93: 10 | AC93: 33 | AD93: 9 | AE93: ရူပဗေဒ | AH93: PM08_ID | AW93: PCET1_01_ID | AX93: ='Clean_PCET1_01_ Head'!$A$2
A94: 04 | B94: 6 years | E94: 44 | F94: Annex 4.4 | G94: TEACHER TRANSFER | AA94: 1034 | AB94: 10 | AC94: 34 | AD94: 10 | AE94: ဓာတုဗေဒ | AH94: PM09_ID | AW94: PCET1_02_ID | AX94: ='Clean_PCET1_02_ Head'!$A$2
A95: 05 | B95: 7 years | E95: 45 | F95: Annex 4.5 | G95: TEACHER ATTRITION | AA95: 1035 | AB95: 10 | AC95: 35 | AD95: 11 | AE95: ဇီဝဗေဒ | AH95: PM10_ID | AW95: PCET1_06_ID | AX95: ='Clean_PCET1_06_ Head'!$A$2
A96: 06 | B96: 8 years | E96: 46 | F96: Annex 4.6 | G96: TEO OFFICE STAFF | AA96: 1031 | AB96: 10 | AC96: 31 | AD96: 7 | AE96: ပထဝီဝင် | AH96: PM11_ID | AW96: PCET1_07_ID | AX96: ='Clean_PCET1_07_ Head'!$A$2
A97: 07 | B97: 9 years | AA97: 1027 | AB97: 10 | AC97: 27 | AD97: 8 | AE97: မြန်မာ့သမိုင်း | AH97: PM12_ID | AW97: PCET1_08_ID | AX97: ='Clean_PCET1_08_ Head'!$A$2
A98: 08 | B98: 10 years | T98: 1 | V98: 1 | AA98: 1029 | AB98: 10 | AC98: 29 | AD98: 8 | AE98: ကမ္ဘာ့ သမိုင်း | AH98: RowCount_GradeSection | AW98: PCET1_09_ID | AX98: ='Clean_PCET1_09_ Head'!$A$2
A99: 09 | B99: 11 years | E99: Month_ID | F99: Month_Name | G99: Month_SortCode | AA99: 1032 | AB99: 10 | AC99: 32 | AD99: 12 | AE99: ဘောဂဗေဒ | AH99: SA_1_ID | AW99: PCET1_10_ID | AX99: ='Clean_PCET1_10_ Head'!$A$2
A100: 10 | B100: 12 years | E100: 06 | F100: June | G100: 1 | AA100: 1030 | AB100: 10 | AC100: 30 | AD100: 8 | AE100: မြန်မာယိုးဒယားသမိုင်း | AH100: SA_2_ID | AW100: PCET1_11_ID | AX100: ='Clean_PCET1_11_ Head'!$A$2
...

Sheet variables
A1: Selected Control Color | B1: Selected Control Name | C1: Selected_Ward_VT_ID | D1: Selected_Urban_Rural | E1: Selected_Village_ID
A2: 12646612 | C2: 110080180 | D2: 2 | E2: 195703
A4: Selected_School_Level | B4: Selected_School_Level_Exist | D4: TSIndex_SchoolID
A5: ='SA-1'!$C$22 -> 1 | B5: 6 | D5: =CLEAN(IFERROR(Township_Index & RIGHT(Selected_School_ID,6),"")) -> 180018001
A7: Selected_LandOwnership | B7: Selected_LandType
A8: ='SA-1'!$B$43 -> 1 | B8: ='SA-1'!$I$43 -> 2
A10: Selected_SchoolShiftType
A11: ='SA-1'!$D$36 -> 1
A13: Selected_SchoolMediaPlatform
A14: ='SA-1'!$B$101 -> 1

Sheet 3_Townships
C1: Welcome to the Township Education Management System. In order to use this program, click 'Options...' on the Message Bar and select 'Enable this content'. Alternatively, open the file with Macro Control from a Trusted Location.
A2: Township_ID | B2: TS_Pcode | C2: NEMIS_TS_Index | D2: Township_EN | E2: Township_MM | F2: SR_ID | G2: SR_PCode | H2: State_Region | I2: State_Region_MM | J2: D_PCode | K2: District | L2: MYA_INFO_TS_ID | M2: Source | N2: Remark
A3: 11001 | B3: MMR011001 | C3: 173 | D3: Mawlamyine | E3: မော်လမြိုင် | F3: 11 | G3: MMR011 | H3: Mon | I3: မွန်ပြည်နယ် | J3: MMR011D001 | K3: Mawlamyine | L3: ASIMMR011001 | M3: GAD, Aug 2012
A4: 11002 | B4: MMR011002 | C4: 174 | D4: Kyaikmaraw | E4: ကျိုက္မရော | F4: 11 | G4: MMR011 | H4: Mon | I4: မွန်ပြည်နယ် | J4: MMR011D001 | K4: Mawlamyine | L4: ASIMMR011002 | M4: GAD, Aug 2012
A5: 11003 | B5: MMR011003 | C5: 175 | D5: Chaungzon | E5: ချောင်းဆုံ | F5: 11 | G5: MMR011 | H5: Mon | I5: မွန်ပြည်နယ် | J5: MMR011D001 | K5: Mawlamyine | L5: ASIMMR011003 | M5: GAD, Aug 2012
A6: 11004 | B6: MMR011004 | C6: 176 | D6: Thanbyuzayat | E6: သံဖြူဇရပ် | F6: 11 | G6: MMR011 | H6: Mon | I6: မွန်ပြည်နယ် | J6: MMR011D001 | K6: Mawlamyine | L6: ASIMMR011004 | M6: GAD, Aug 2012
A7: 11005 | B7: MMR011005 | C7: 177 | D7: Mudon | E7: မုဒုံ | F7: 11 | G7: MMR011 | H7: Mon | I7: မွန်ပြည်နယ် | J7: MMR011D001 | K7: Mawlamyine | L7: ASIMMR011005 | M7: GAD, Aug 2012
A8: 11006 | B8: MMR011006 | C8: 178 | D8: Ye | E8: ရေး | F8: 11 | G8: MMR011 | H8: Mon | I8: မွန်ပြည်နယ် | J8: MMR011D001 | K8: Mawlamyine | L8: ASIMMR011006 | M8: GAD, Aug 2012
A9: 11007 | B9: MMR011007 | C9: 179 | D9: Thaton | E9: သထုံ | F9: 11 | G9: MMR011 | H9: Mon | I9: မွန်ပြည်နယ် | J9: MMR011D002 | K9: Thaton | L9: ASIMMR011007 | M9: GAD, Aug 2012
A10: 11008 | B10: MMR011008 | C10: 180 | D10: Paung | E10: ပေါင် | F10: 11 | G10: MMR011 | H10: Mon | I10: မွန်ပြည်နယ် | J10: MMR011D002 | K10: Thaton | L10: ASIMMR011008 | M10: GAD, Aug 2012
A11: 11009 | B11: MMR011009 | C11: 181 | D11: Kyaikto | E11: ကျိုက်ထို | F11: 11 | G11: MMR011 | H11: Mon | I11: မွန်ပြည်နယ် | J11: MMR011D002 | K11: Thaton | L11: ASIMMR011009 | M11: GAD, Aug 2012
A12: 11010 | B12: MMR011010 | C12: 182 | D12: Bilin | E12: ဘီးလင်း | F12: 11 | G12: MMR011 | H12: Mon | I12: မွန်ပြည်နယ် | J12: MMR011D002 | K12: Thaton | L12: ASIMMR011010 | M12: GAD, Aug 2012
A15: Sorted by TownshipID

Sheet 6_Village_Tracts
A1: Township_ID | B1: VT_ID | C1: Village_Tract_Name_EN | D1: Village_Tract_Name_MM | E1: TS_Pcode | F1: VT_PCode | G1: MYAINFO_VT_ID | H1: Source | I1: Remark | J1: Old_VT_PCode | K1: SR_ID
A2: 11001 | B2: 110010180 | C2: Hpar Auk | D2: ဖါးအောက် | E2: MMR011001 | F2: MMR011001018 | G2: ASIMMR011001018 | H2: GAD, Aug 2012 | K2: 11
A3: 11001 | B3: 110010010 | C3: Ka Toe | D3: ကတိုး | E3: MMR011001 | F3: MMR011001001 | G3: ASIMMR011001001 | H3: GAD, Aug 2012 | K3: 11
A4: 11001 | B4: 110010070 | C4: Kawt Hlar | D4: ကော့လှာ | E4: MMR011001 | F4: MMR011001007 | G4: ASIMMR011001007 | H4: GAD, Aug 2012 | K4: 11
A5: 11001 | B5: 110010060 | C5: Kawt Hnat | D5: ကော့နှပ် | E5: MMR011001 | F5: MMR011001006 | G5: ASIMMR011001006 | H5: GAD, Aug 2012 | K5: 11
A6: 11001 | B6: 110010170 | C6: Kawt Kha Mei | D6: ကော့ခမယ် | E6: MMR011001 | F6: MMR011001017 | G6: ASIMMR011001017 | H6: GAD, Aug 2012 | K6: 11
A7: 11001 | B7: 110010140 | C7: Kawt Kha Ni | D7: ကော့ခနိ | E7: MMR011001 | F7: MMR011001014 | G7: ASIMMR011001014 | H7: GAD, Aug 2012 | K7: 11
A8: 11001 | B8: 110010080 | C8: Kawt Pauk | D8: ကော့ပေါက် | E8: MMR011001 | F8: MMR011001008 | G8: ASIMMR011001008 | H8: GAD, Aug 2012 | K8: 11
A9: 11001 | B9: 110010050 | C9: Kawt Tun | D9: ကော့တွန် | E9: MMR011001 | F9: MMR011001005 | G9: ASIMMR011001005 | H9: GAD, Aug 2012 | K9: 11
A10: 11001 | B10: 110010020 | C10: Kawt Wein | D10: ကော့ဝိန် | E10: MMR011001 | F10: MMR011001002 | G10: ASIMMR011001002 | H10: GAD, Aug 2012 | K10: 11
A11: 11001 | B11: 110010160 | C11: Kyar Inn | D11: ကြာအင်း | E11: MMR011001 | F11: MMR011001016 | G11: ASIMMR011001016 | H11: GAD, Aug 2012 | K11: 11
A12: 11001 | B12: 110010100 | C12: Min Ywar | D12: မင်းရွာ | E12: MMR011001 | F12: MMR011001010 | G12: ASIMMR011001010 | H12: GAD, Aug 2012 | K12: 11
A13: 11001 | B13: 110010110 | C13: Mu Yaung | D13: မုရောင်း | E13: MMR011001 | F13: MMR011001011 | G13: ASIMMR011001011 | H13: GAD, Aug 2012 | K13: 11
... A174: 11006 | B174: 110060130 | C174: Han Gan | D174: ဟံဂံ | E174: MMR011006 | F174: MMR011006013 | G174: ASIMMR011006013 | H174: GAD, Aug 2012 | K174: 11
A175: 11006 | B175: 110060230 | C175: Hnin Sone (Lamaing Sub-township) | D175: နှင်းစုံ | E175: MMR011006 | F175: MMR011006023 | G175: ASIMMR011006023 | H175: GAD, Aug 2012 | I175: Renamedd from Hnin Sote | K175: 11
A176: 11006 | B176: 110060200 | C176: Hnit Kayin (Lamaing Sub-township) | D176: နှစ်ကရင် | E176: MMR011006 | F176: MMR011006020 | G176: ASIMMR011006020 | H176: GAD, Aug 2012 | K176: 11
A177: 11006 | B177: 110060270 | C177: Ka Byar (Khawzar Sub-township) | D177: ကဗျာ | E177: MMR011006 | F177: MMR011006027 | G177: ASIMMR011006027 | H177: GAD, Aug 2012 | K177: 11
A178: 11006 | B178: 110060070 | C178: Ka Lawt | D178: ကလော့ | E178: MMR011006 | F178: MMR011006007 | G178: ASIMMR011006007 | H178: GAD, Aug 2012 | K178: 11
A179: 11006 | B179: 110060220 | C179: Ka Nin Ka Mawt (Lamaing Sub-township) | D179: ကနင်ကမော့ | E179: MMR011006 | F179: MMR011006022 | G179: ASIMMR011006022 | H179: GAD, Aug 2012 | K179: 11
A180: 11006 | B180: 110060160 | C180: Kawt Dut (Lamaing Sub-township) | D180: ကော့ဒွတ် | E180: MMR011006 | F180: MMR011006016 | G180: ASIMMR011006016 | H180: GAD, Aug 2012 | K180: 11
A181: 11006 | B181: 110060260 | C181: Kawt Hlaing (Khawzar Sub-township) | D181: ကော့လှိုင် | E181: MMR011006 | F181: MMR011006026 | G181: ASIMMR011006026 | H181: GAD, Aug 2012 | K181: 11
A182: 11006 | B182: 110060250 | C182: Koe Maing (Khawzar Sub-township) | D182: ကိုးမိုင် | E182: MMR011006 | F182: MMR011006025 | G182: ASIMMR011006025 | H182: GAD, Aug 2012 | K182: 11
A183: 11006 | B183: 110060170 | C183: Ku Lar Koke (Lamaing Sub-township) | D183: ကုလားကုတ် | E183: MMR011006 | F183: MMR011006017 | G183: ASIMMR011006017 | H183: GAD, Aug 2012 | K183: 11
A184: 11006 | B184: 110060080 | C184: Kyauk Mi Khaung | D184: ကျောက်မိကျောင်း | E184: MMR011006 | F184: MMR011006008 | G184: ASIMMR011006008 | H184: GAD, Aug 2012 | K184: 11
A185: 11006 | B185: 110060050 | C185: Kyaung Ywar | D185: ကျောင်းရွာ | E185: MMR011006 | F185: MMR011006005 | G185: ASIMMR011006005 | H185: GAD, Aug 2012 | K185: 11
A186: 11006 | B186: 110060300 | C186: Kyon Nye (Khawzar Sub-township) | D186: ကျုံညဲ | E186: MMR011006 | F186: MMR011006030 | G186: ASIMMR011006030 | H186: GAD, Aug 2012 | K186: 11
A187: 11006 | B187: 110060280 | C187: Ma Gyi (Khawzar Sub-township) | D187: မကျီး | E187: MMR011006 | F187: MMR011006028 | G187: ASIMMR011006028 | H187: GAD, Aug 2012 | K187: 11
... A378: 11010 | B378: 110100080 | C378: Zwe Ka Lar | D378: ဇွဲကလာ | E378: MMR011010 | F378: MMR011010008 | G378: ASIMMR011010008 | H378: GAD, Aug 2012 | K378: 11
A379: Sorted by TownshipID and VT ID

Sheet 5_Wards
A1: Township_ID | B1: Ward_ID | C1: Ward_Name_EN | D1: Ward_Name_MM | E1: Town_ID | H1: Ward_Pcode | I1: Town_Pcode | J1: TS_Pcode | K1: Town | L1: Ward_Pcode | M1: Source | N1: Remark | O1: SR_ID
A2: 11001 | B2: 110011011 | C2: Shwe Myaing Thi Ri Ward | D2: ရွှေမြိုင်သီရိရပ်ကွက် | E2: 110011 | F2: 01 | G2: 11001001 | H2: MMR011001701501 | I2: MMR011001701 | J2: MMR011001 | K2: Mawlamyine Town | L2: MMR011001701501 | M2: GAD, Aug 2012 | O2: 11
A3: 11001 | B3: 110011021 | C3: Kyaik Hpa Nei Ward | D3: ကျိုက်ဖနဲရပ်ကွက် | E3: 110011 | F3: 02 | G3: 11001002 | H3: MMR011001701502 | I3: MMR011001701 | J3: MMR011001 | K3: Mawlamyine Town | L3: MMR011001701502 | M3: GAD, Aug 2012 | O3: 11
A4: 11001 | B4: 110011031 | C4: Hlaing Shan Su Ward | D4: လှိုင်ရှမ်းစုရပ်ကွက် | E4: 110011 | F4: 03 | G4: 11001003 | H4: MMR011001701503 | I4: MMR011001701 | J4: MMR011001 | K4: Mawlamyine Town | L4: MMR011001701503 | M4: GAD, Aug 2012 | O4: 11
A5: 11001 | B5: 110011041 | C5: Auk Kyin Ward | D5: အောက်ကျင်းရပ်ကွက် | E5: 110011 | F5: 04 | G5: 11001004 | H5: MMR011001701504 | I5: MMR011001701 | J5: MMR011001 | K5: Mawlamyine Town | L5: MMR011001701504 | M5: GAD, Aug 2012 | O5: 11
A6: 11001 | B6: 110011051 | C6: Mandalay Ward | D6: မန္တလေးရပ်ကွက် | E6: 110011 | F6: 05 | G6: 11001005 | H6: MMR011001701505 | I6: MMR011001701 | J6: MMR011001 | K6: Mawlamyine Town | L6: MMR011001701505 | M6: GAD, Aug 2012 | O6: 11
A7: 11001 | B7: 110011061 | C7: Hpet Tan Ward | D7: ဖက်တန်းရပ်ကွက် | E7: 110011 | F7: 06 | G7: 11001006 | H7: MMR011001701506 | I7: MMR011001701 | J7: MMR011001 | K7: Mawlamyine Town | L7: MMR011001701506 | M7: GAD, Aug 2012 | O7: 11
A8: 11001 | B8: 110011071 | C8: Shwe (South) Ward | D8: ရွှေတောင်ရပ်ကွက် | E8: 110011 | F8: 07 | G8: 11001007 | H8: MMR011001701507 | I8: MMR011001701 | J8: MMR011001 | K8: Mawlamyine Town | L8: MMR011001701507 | M8: GAD, Aug 2012 | O8: 11
A9: 11001 | B9: 110011081 | C9: Sit Ke Kone Ward | D9: စစ်ကဲကုန်းရပ်ကွက် | E9: 110011 | F9: 08 | G9: 11001008 | H9: MMR011001701508 | I9: MMR011001701 | J9: MMR011001 | K9: Mawlamyine Town | L9: MMR011001701508 | M9: GAD, Aug 2012 | O9: 11
A10: 11001 | B10: 110011091 | C10: Ma Yan Kone Ward | D10: မရမ်းကုန်းရပ်ကွက် | E10: 110011 | F10: 09 | G10: 11001009 | H10: MMR011001701509 | I10: MMR011001701 | J10: MMR011001 | K10: Mawlamyine Town | L10: MMR011001701509 | M10: GAD, Aug 2012 | O10: 11
A11: 11001 | B11: 110011101 | C11: Pan Be Dan Ward | D11: ပန်းဘဲတန်းရပ်ကွက် | E11: 110011 | F11: 10 | G11: 11001010 | H11: MMR011001701510 | I11: MMR011001701 | J11: MMR011001 | K11: Mawlamyine Town | L11: MMR011001701510 | M11: GAD, Aug 2012 | O11: 11
A12: 11001 | B12: 110011111 | C12: Bo Kone Ward | D12: ဘိုကုန်းရပ်ကွက် | E12: 110011 | F12: 11 | G12: 11001011 | H12: MMR011001701511 | I12: MMR011001701 | J12: MMR011001 | K12: Mawlamyine Town | L12: MMR011001701511 | M12: GAD, Aug 2012 | O12: 11
A13: 11001 | B13: 110011121 | C13: Maung Ngan Ward | D13: မောင်ငံရပ်ကွက် | E13: 110011 | F13: 12 | G13: 11001012 | H13: MMR011001701512 | I13: MMR011001701 | J13: MMR011001 | K13: Mawlamyine Town | L13: MMR011001701512 | M13: GAD, Aug 2012 | O13: 11
... A23: 11001 | B23: 110011221 | C23: Zay Yar Myaing Ward | D23: ဇေယျာမြိုင်ရပ်ကွက် | E23: 110011 | F23: 22 | G23: 11001022 | H23: MMR011001701522 | I23: MMR011001701 | J23: MMR011001 | K23: Mawlamyine Town | L23: MMR011001701522 | M23: GAD, Aug 2012 | O23: 11
A24: 11001 | B24: 110011231 | C24: Kyauk Tan Ward | D24: ကျောက်တန်းရပ်ကွက် | E24: 110011 | F24: 23 | G24: 11001023 | H24: MMR011001701523 | I24: MMR011001701 | J24: MMR011001 | K24: Mawlamyine Town | L24: MMR011001701523 | M24: GAD, Aug 2012 | N24: New Ward changed from VT, GAD 2012 | O24: 11
A25: 11001 | B25: 110011241 | C25: San Gyi Ward | D25: စမ်းကြီးရပ်ကွက် | E25: 110011 | F25: 24 | G25: 11001024 | H25: MMR011001701524 | I25: MMR011001701 | J25: MMR011001 | K25: Mawlamyine Town | L25: MMR011001701524 | M25: GAD, Aug 2012 | N25: New Ward changed from VT, GAD 2012 | O25: 11
A26: 11001 | B26: 110011251 | C26: Gway Kone Ward | D26: ဂွေးကုန်းရပ်ကွက် | E26: 110011 | F26: 25 | G26: 11001025 | H26: MMR011001701525 | I26: MMR011001701 | J26: MMR011001 | K26: Mawlamyine Town | L26: MMR011001701525 | M26: GAD, Aug 2012 | N26: New Ward changed from VT, GAD 2012 | O26: 11
A27: 11001 | B27: 110011261 | C27: Naung Kha Ri Ward | D27: နောင်ခရိရပ်ကွက် | E27: 110011 | F27: 26 | G27: 11001026 | H27: MMR011001701526 | I27: MMR011001701 | J27: MMR011001 | K27: Mawlamyine Town | L27: MMR011001701526 | M27: GAD, Aug 2012 | N27: New Ward changed from VT, GAD 2012 | O27: 11
A28: 11001 | B28: 110011271 | C28: Ngan Tay Ward | D28: ငန်းတေးရပ်ကွက် | E28: 110011 | F28: 27 | G28: 11001027 | H28: MMR011001701527 | I28: MMR011001701 | J28: MMR011001 | K28: Mawlamyine Town | L28: MMR011001701527 | M28: GAD, Aug 2012 | N28: New Ward changed from VT, GAD 2012 | O28: 11
A29: 11001 | B29: 110011281 | C29: Chauk Maing Kywe Chan Kone Ward | D29: ခြောက်မိုင်ကျွဲခြံကုန်းရပ်ကွက် | E29: 110011 | F29: 28 | G29: 11001028 | H29: MMR011001701528 | I29: MMR011001701 | J29: MMR011001 | K29: Mawlamyine Town | L29: MMR011001701528 | M29: GAD, Aug 2012 | N29: New Ward changed from VT, GAD 2012 | O29: 11
A30: 11002 | B30: 110021011 | C30: Shin Saw Pu Ward | D30: ရှင်စောပုရပ်ကွက် | E30: 110021 | F30: 01 | G30: 11002001 | H30: MMR011002701501 | I30: MMR011002701 | J30: MMR011002 | K30: Kyaikmaraw Town | L30: MMR011002701501 | M30: GAD, Aug 2012 | O30: 11
A31: 11002 | B31: 110021021 | C31: Yan Myo Aung Ward | D31: ရန်မျိုးအောင်ရပ်ကွက် | E31: 110021 | F31: 02 | G31: 11002002 | H31: MMR011002701502 | I31: MMR011002701 | J31: MMR011002 | K31: Kyaikmaraw Town | L31: MMR011002701502 | M31: GAD, Aug 2012 | O31: 11
A32: 11003 | B32: 110031011 | C32: Ah Nauk Ward | D32: အနောက်ရပ်ကွက် | E32: 110031 | F32: 01 | G32: 11003001 | H32: MMR011003701501 | I32: MMR011003701 | J32: MMR011003 | K32: Chaungzon Town | L32: MMR011003701501 | M32: GAD, Aug 2012 | O32: 11
A33: 11003 | B33: 110031021 | C33: Ah Shey Ward | D33: အရှေ့ရပ်ကွက် | E33: 110031 | F33: 02 | G33: 11003002 | H33: MMR011003701502 | I33: MMR011003701 | J33: MMR011003 | K33: Chaungzon Town | L33: MMR011003701502 | M33: GAD, Aug 2012 | O33: 11
A34: 11003 | B34: 110031031 | C34: Toe Cheit Ward | D34: တိုးချဲ့ရပ်ကွက် | E34: 110031 | F34: 03 | G34: 11003003 | H34: MMR011003701503 | I34: MMR011003701 | J34: MMR011003 | K34: Chaungzon Town | L34: MMR011003701503 | M34: GAD, Aug 2012 | O34: 11
A35: 11004 | B35: 110041011 | C35: Kyar Kan Ward | D35: ကြာကန်ရပ်ကွက် | E35: 110041 | F35: 01 | G35: 11004001 | H35: MMR011004701501 | I35: MMR011004701 | J35: MMR011004 | K35: Thanpyuzayat Town | L35: MMR011004701501 | M35: GAD, Aug 2012 | O35: 11
A36: 11004 | B36: 110041021 | C36: Aung Chan Thar Ward | D36: အောင်ချမ်းသာရပ်ကွက် | E36: 110041 | F36: 02 | G36: 11004002 | H36: MMR011004701502 | I36: MMR011004701 | J36: MMR011004 | K36: Thanpyuzayat Town | L36: MMR011004701502 | M36: GAD, Aug 2012 | O36: 11
A37: 11004 | B37: 110041031 | C37: Set Thit Ward | D37: စက်သစ်ရပ်ကွက် | E37: 110041 | F37: 03 | G37: 11004003 | H37: MMR011004701503 | I37: MMR011004701 | J37: MMR011004 | K37: Thanpyuzayat Town | L37: MMR011004701503 | M37: GAD, Aug 2012 | O37: 11
A38: 11004 | B38: 110041041 | C38: Aung Min Ga Lar Ward | D38: အောင်မင်္ဂလာရပ်ကွက် | E38: 110041 | F38: 04 | G38: 11004004 | H38: MMR011004701504 | I38: MMR011004701 | J38: MMR011004 | K38: Thanpyuzayat Town | L38: MMR011004701504 | M38: GAD, Aug 2012 | O38: 11
A39: 11004 | B39: 110041051 | C39: Han Thar Wa Di Ward | D39: ဟံသာဝတီရပ်ကွက် | E39: 110041 | F39: 05 | G39: 11004005 | H39: MMR011004701505 | I39: MMR011004701 | J39: MMR011004 | K39: Thanpyuzayat Town | L39: MMR011004701505 | M39: GAD, Aug 2012 | O39: 11
A40: 11004 | B40: 110041061 | C40: Aung Zay Ya Ward | D40: အောင်ဇေယျရပ်ကွက် | E40: 110041 | F40: 06 | G40: 11004006 | H40: MMR011004701506 | I40: MMR011004701 | J40: MMR011004 | K40: Thanpyuzayat Town | L40: MMR011004701506 | M40: GAD, Aug 2012 | O40: 11
A41: 11004 | B41: 110041071 | C41: Kyaung Paing Ward | D41: ကျောင်းပိုင်းရပ်ကွက် | E41: 110041 | F41: 07 | G41: 11004007 | H41: MMR011004701507 | I41: MMR011004701 | J41: MMR011004 | K41: Thanpyuzayat Town | L41: MMR011004701507 | M41: GAD, Aug 2012 | O41: 11
... A87: 11010 | B87: 110101051 | C87: Bo Tay Za Ward | D87: ဗိုလ်တေဇရပ်ကွက် | E87: 110101 | F87: 05 | G87: 11010005 | H87: MMR011010701505 | I87: MMR011010701 | J87: MMR011010 | K87: Bilin Town | L87: MMR011010701505 | M87: GAD, Aug 2012 | O87: 11
A90: Sorted by TownshipID and Ward ID

Sheet Ward_Names_TS
A1: Township_ID | B1: Town_ID | C1: Ward_ID | D1: Ward_Name_EN | E1: Ward_Name_MM | F1: Ward_Name | I1: Ward_Pcode | J1: Town_Pcode | K1: TS_Pcode | L1: Town | M1: Ward_Pcode | N1: Source | O1: Remark | P1: SR_ID
A2: 11001 | B2: 110011 | C2: 110011041 | D2: Auk Kyin Ward | E2: အောက်ကျင်းရပ်ကွက် | F2: Auk Kyin Ward - 110011041 | G2: 04 | H2: 11001004 | I2: MMR011001701504 | J2: MMR011001701 | K2: MMR011001 | L2: Mawlamyine Town | M2: MMR011001701504 | N2: GAD, Aug 2012 | P2: 11
A3: 11001 | B3: 110011 | C3: 110011111 | D3: Bo Kone Ward | E3: ဘိုကုန်းရပ်ကွက် | F3: Bo Kone Ward - 110011111 | G3: 11 | H3: 11001011 | I3: MMR011001701511 | J3: MMR011001701 | K3: MMR011001 | L3: Mawlamyine Town | M3: MMR011001701511 | N3: GAD, Aug 2012 | P3: 11
A4: 11001 | B4: 110011 | C4: 110011281 | D4: Chauk Maing Kywe Chan Kone Ward | E4: ခြောက်မိုင်ကျွဲခြံကုန်းရပ်ကွက် | F4: Chauk Maing Kywe Chan Kone Ward - 110011281 | G4: 28 | H4: 11001028 | I4: MMR011001701528 | J4: MMR011001701 | K4: MMR011001 | L4: Mawlamyine Town | M4: MMR011001701528 | N4: GAD, Aug 2012 | O4: New Ward changed from VT, GAD 2012 | P4: 11
A5: 11001 | B5: 110011 | C5: 110011251 | D5: Gway Kone Ward | E5: ဂွေးကုန်းရပ်ကွက် | F5: Gway Kone Ward - 110011251 | G5: 25 | H5: 11001025 | I5: MMR011001701525 | J5: MMR011001701 | K5: MMR011001 | L5: Mawlamyine Town | M5: MMR011001701525 | N5: GAD, Aug 2012 | O5: New Ward changed from VT, GAD 2012 | P5: 11
A6: 11001 | B6: 110011 | C6: 110011031 | D6: Hlaing Shan Su Ward | E6: လှိုင်ရှမ်းစုရပ်ကွက် | F6: Hlaing Shan Su Ward - 110011031 | G6: 03 | H6: 11001003 | I6: MMR011001701503 | J6: MMR011001701 | K6: MMR011001 | L6: Mawlamyine Town | M6: MMR011001701503 | N6: GAD, Aug 2012 | P6: 11
A7: 11001 | B7: 110011 | C7: 110011061 | D7: Hpet Tan Ward | E7: ဖက်တန်းရပ်ကွက် | F7: Hpet Tan Ward - 110011061 | G7: 06 | H7: 11001006 | I7: MMR011001701506 | J7: MMR011001701 | K7: MMR011001 | L7: Mawlamyine Town | M7: MMR011001701506 | N7: GAD, Aug 2012 | P7: 11
A8: 11001 | B8: 110011 | C8: 110011131 | D8: Kwin Yat Ward | E8: ကွင်းရပ်ရပ်ကွက် | F8: Kwin Yat Ward - 110011131 | G8: 13 | H8: 11001013 | I8: MMR011001701513 | J8: MMR011001701 | K8: MMR011001 | L8: Mawlamyine Town | M8: MMR011001701513 | N8: GAD, Aug 2012 | P8: 11
A9: 11001 | B9: 110011 | C9: 110011021 | D9: Kyaik Hpa Nei Ward | E9: ကျိုက်ဖနဲရပ်ကွက် | F9: Kyaik Hpa Nei Ward - 110011021 | G9: 02 | H9: 11001002 | I9: MMR011001701502 | J9: MMR011001701 | K9: MMR011001 | L9: Mawlamyine Town | M9: MMR011001701502 | N9: GAD, Aug 2012 | P9: 11
A10: 11001 | B10: 110011 | C10: 110011231 | D10: Kyauk Tan Ward | E10: ကျောက်တန်းရပ်ကွက် | F10: Kyauk Tan Ward - 110011231 | G10: 23 | H10: 11001023 | I10: MMR011001701523 | J10: MMR011001701 | K10: MMR011001 | L10: Mawlamyine Town | M10: MMR011001701523 | N10: GAD, Aug 2012 | O10: New Ward changed from VT, GAD 2012 | P10: 11
A11: 11001 | B11: 110011 | C11: 110011091 | D11: Ma Yan Kone Ward | E11: မရမ်းကုန်းရပ်ကွက် | F11: Ma Yan Kone Ward - 110011091 | G11: 09 | H11: 11001009 | I11: MMR011001701509 | J11: MMR011001701 | K11: MMR011001 | L11: Mawlamyine Town | M11: MMR011001701509 | N11: GAD, Aug 2012 | P11: 11
A12: 11001 | B12: 110011 | C12: 110011051 | D12: Mandalay Ward | E12: မန္တလေးရပ်ကွက် | F12: Mandalay Ward - 110011051 | G12: 05 | H12: 11001005 | I12: MMR011001701505 | J12: MMR011001701 | K12: MMR011001 | L12: Mawlamyine Town | M12: MMR011001701505 | N12: GAD, Aug 2012 | P12: 11
A13: 11001 | B13: 110011 | C13: 110011121 | D13: Maung Ngan Ward | E13: မောင်ငံရပ်ကွက် | F13: Maung Ngan Ward - 110011121 | G13: 12 | H13: 11001012 | I13: MMR011001701512 | J13: MMR011001701 | K13: MMR011001 | L13: Mawlamyine Town | M13: MMR011001701512 | N13: GAD, Aug 2012 | P13: 11
A14: 11001 | B14: 110011 | C14: 110011171 | D14: Mu Pon Ward | E14: မုပွန်ရပ်ကွက် | F14: Mu Pon Ward - 110011171 | G14: 17 | H14: 11001017 | I14: MMR011001701517 | J14: MMR011001701 | K14: MMR011001 | L14: Mawlamyine Town | M14: MMR011001701517 | N14: GAD, Aug 2012 | P14: 11
A15: 11001 | B15: 110011 | C15: 110011211 | D15: Myaing Thar Yar Ward | E15: မြိုင်သာယာရပ်ကွက် | F15: Myaing Thar Yar Ward - 110011211 | G15: 21 | H15: 11001021 | I15: MMR011001701521 | J15: MMR011001701 | K15: MMR011001 | L15: Mawlamyine Town | M15: MMR011001701521 | N15: GAD, Aug 2012 | P15: 11
A16: 11001 | B16: 110011 | C16: 110011141 | D16: Myay Ni Kone Ward | E16: မြေနီကုန်းရပ်ကွက် | F16: Myay Ni Kone Ward - 110011141 | G16: 14 | H16: 11001014 | I16: MMR011001701514 | J16: MMR011001701 | K16: MMR011001 | L16: Mawlamyine Town | M16: MMR011001701514 | N16: GAD, Aug 2012 | P16: 11
A17: 11001 | B17: 110011 | C17: 110011261 | D17: Naung Kha Ri Ward | E17: နောင်ခရိရပ်ကွက် | F17: Naung Kha Ri Ward - 110011261 | G17: 26 | H17: 11001026 | I17: MMR011001701526 | J17: MMR011001701 | K17: MMR011001 | L17: Mawlamyine Town | M17: MMR011001701526 | N17: GAD, Aug 2012 | O17: New Ward changed from VT, GAD 2012 | P17: 11
A18: 11001 | B18: 110011 | C18: 110011271 | D18: Ngan Tay Ward | E18: ငန်းတေးရပ်ကွက် | F18: Ngan Tay Ward - 110011271 | G18: 27 | H18: 11001027 | I18: MMR011001701527 | J18: MMR011001701 | K18: MMR011001 | L18: Mawlamyine Town | M18: MMR011001701527 | N18: GAD, Aug 2012 | O18: New Ward changed from VT, GAD 2012 | P18: 11
A19: 11001 | B19: 110011 | C19: 110011101 | D19: Pan Be Dan Ward | E19: ပန်းဘဲတန်းရပ်ကွက် | F19: Pan Be Dan Ward - 110011101 | G19: 10 | H19: 11001010 | I19: MMR011001701510 | J19: MMR011001701 | K19: MMR011001 | L19: Mawlamyine Town | M19: MMR011001701510 | N19: GAD, Aug 2012 | P19: 11
A20: 11001 | B20: 110011 | C20: 110011241 | D20: San Gyi Ward | E20: စမ်းကြီးရပ်ကွက် | F20: San Gyi Ward - 110011241 | G20: 24 | H20: 11001024 | I20: MMR011001701524 | J20: MMR011001701 | K20: MMR011001 | L20: Mawlamyine Town | M20: MMR011001701524 | N20: GAD, Aug 2012 | O20: New Ward changed from VT, GAD 2012 | P20: 11
A21: 11001 | B21: 110011 | C21: 110011071 | D21: Shwe (South) Ward | E21: ရွှေတောင်ရပ်ကွက် | F21: Shwe (South) Ward - 110011071 | G21: 07 | H21: 11001007 | I21: MMR011001701507 | J21: MMR011001701 | K21: MMR011001 | L21: Mawlamyine Town | M21: MMR011001701507 | N21: GAD, Aug 2012 | P21: 11
A22: 11001 | B22: 110011 | C22: 110011011 | D22: Shwe Myaing Thi Ri Ward | E22: ရွှေမြိုင်သီရိရပ်ကွက် | F22: Shwe Myaing Thi Ri Ward - 110011011 | G22: 01 | H22: 11001001 | I22: MMR011001701501 | J22: MMR011001701 | K22: MMR011001 | L22: Mawlamyine Town | M22: MMR011001701501 | N22: GAD, Aug 2012 | P22: 11
A23: 11001 | B23: 110011 | C23: 110011081 | D23: Sit Ke Kone Ward | E23: စစ်ကဲကုန်းရပ်ကွက် | F23: Sit Ke Kone Ward - 110011081 | G23: 08 | H23: 11001008 | I23: MMR011001701508 | J23: MMR011001701 | K23: MMR011001 | L23: Mawlamyine Town | M23: MMR011001701508 | N23: GAD, Aug 2012 | P23: 11
A24: 11001 | B24: 110011 | C24: 110011191 | D24: Thar Yar Aye Ward | E24: သာယာအေးရပ်ကွက် | F24: Thar Yar Aye Ward - 110011191 | G24: 19 | H24: 11001019 | I24: MMR011001701519 | J24: MMR011001701 | K24: MMR011001 | L24: Mawlamyine Town | M24: MMR011001701519 | N24: GAD, Aug 2012 | P24: 11
A25: 11001 | B25: 110011 | C25: 110011201 | D25: Thi Ri Min Ga Lar Ward | E25: သီရိမင်္ဂလာရပ်ကွက် | F25: Thi Ri Min Ga Lar Ward - 110011201 | G25: 20 | H25: 11001020 | I25: MMR011001701520 | J25: MMR011001701 | K25: MMR011001 | L25: Mawlamyine Town | M25: MMR011001701520 | N25: GAD, Aug 2012 | P25: 11
A26: 11001 | B26: 110011 | C26: 110011161 | D26: Thi Ri Myaing Ward | E26: သီရိမြိုင်ရပ်ကွက် | F26: Thi Ri Myaing Ward - 110011161 | G26: 16 | H26: 11001016 | I26: MMR011001701516 | J26: MMR011001701 | K26: MMR011001 | L26: Mawlamyine Town | M26: MMR011001701516 | N26: GAD, Aug 2012 | P26: 11
A27: 11001 | B27: 110011 | C27: 110011151 | D27: Zay Cho Ward | E27: ဈေးချိုရပ်ကွက် | F27: Zay Cho Ward - 110011151 | G27: 15 | H27: 11001015 | I27: MMR011001701515 | J27: MMR011001701 | K27: MMR011001 | L27: Mawlamyine Town | M27: MMR011001701515 | N27: GAD, Aug 2012 | P27: 11
A28: 11001 | B28: 110011 | C28: 110011221 | D28: Zay Yar Myaing Ward | E28: ဇေယျာမြိုင်ရပ်ကွက် | F28: Zay Yar Myaing Ward - 110011221 | G28: 22 | H28: 11001022 | I28: MMR011001701522 | J28: MMR011001701 | K28: MMR011001 | L28: Mawlamyine Town | M28: MMR011001701522 | N28: GAD, Aug 2012 | P28: 11
A29: 11001 | B29: 110011 | C29: 110011181 | D29: Zay Yar Thi Ri Ward | E29: ဇေယျာသီရိရပ်ကွက် | F29: Zay Yar Thi Ri Ward - 110011181 | G29: 18 | H29: 11001018 | I29: MMR011001701518 | J29: MMR011001701 | K29: MMR011001 | L29: Mawlamyine Town | M29: MMR011001701518 | N29: GAD, Aug 2012 | P29: 11
A30: 11002 | B30: 110021 | C30: 110021011 | D30: Shin Saw Pu Ward | E30: ရှင်စောပုရပ်ကွက် | F30: Shin Saw Pu Ward - 110021011 | G30: 01 | H30: 11002001 | I30: MMR011002701501 | J30: MMR011002701 | K30: MMR011002 | L30: Kyaikmaraw Town | M30: MMR011002701501 | N30: GAD, Aug 2012 | P30: 11
A31: 11002 | B31: 110021 | C31: 110021021 | D31: Yan Myo Aung Ward | E31: ရန်မျိုးအောင်ရပ်ကွက် | F31: Yan Myo Aung Ward - 110021021 | G31: 02 | H31: 11002002 | I31: MMR011002701502 | J31: MMR011002701 | K31: MMR011002 | L31: Kyaikmaraw Town | M31: MMR011002701502 | N31: GAD, Aug 2012 | P31: 11
A32: 11003 | B32: 110031 | C32: 110031011 | D32: Ah Nauk Ward | E32: အနောက်ရပ်ကွက် | F32: Ah Nauk Ward - 110031011 | G32: 01 | H32: 11003001 | I32: MMR011003701501 | J32: MMR011003701 | K32: MMR011003 | L32: Chaungzon Town | M32: MMR011003701501 | N32: GAD, Aug 2012 | P32: 11
... A87: 11010 | B87: 110101 | C87: 110101011 | D87: Sa Yar San Ward | E87: ဆရာစံရပ်ကွက် | F87: Sa Yar San Ward - 110101011 | G87: 01 | H87: 11010001 | I87: MMR011010701501 | J87: MMR011010701 | K87: MMR011010 | L87: Bilin Town | M87: MMR011010701501 | N87: GAD, Aug 2012 | P87: 11
A90: Sorted by TownshipID and Ward Name

Sheet Village_Names_TS
A1: Township_ID | B1: VT_ID | C1: Village_ID | D1: Village_EN | E1: Village_MM | F1: Village_Name | G1: SR_ID
A2: 11001 | B2: 110010180 | C2: 194969 | D2: Hpar Auk | E2: ဖားအောက် | F2: Hpar Auk - 194969 | G2: 11
A3: 11001 | B3: 110010070 | C3: 194940 | D3: Hpe Htaw | E3: ဖဲထော် | F3: Hpe Htaw - 194940 | G3: 11
A4: 11001 | B4: 110010010 | C4: 194925 | D4: Ka Toe | E4: ကတိုး | F4: Ka Toe - 194925 | G4: 11
A5: 11001 | B5: 110010070 | C5: 194939 | D5: Kawt Hlar | E5: ကော့လှာ | F5: Kawt Hlar - 194939 | G5: 11
A6: 11001 | B6: 110010060 | C6: 194934 | D6: Kawt Hnat | E6: ကော့နှပ် | F6: Kawt Hnat - 194934 | G6: 11
A7: 11001 | B7: 110010170 | C7: 194966 | D7: Kawt Kha Mei | E7: ကော့ခမယ် | F7: Kawt Kha Mei - 194966 | G7: 11
A8: 11001 | B8: 110010140 | C8: 194957 | D8: Kawt Kha Ni | E8: ကော့ခနိ | F8: Kawt Kha Ni - 194957 | G8: 11
A9: 11001 | B9: 110010170 | C9: 194967 | D9: Kawt Kha Po | E9: ကော့ခပို | F9: Kawt Kha Po - 194967 | G9: 11
A10: 11001 | B10: 110010080 | C10: 194941 | D10: Kawt Pauk | E10: ကော့ပေါက် | F10: Kawt Pauk - 194941 | G10: 11
A11: 11001 | B11: 110010050 | C11: 194931 | D11: Kawt Tun | E11: ကော့တွန် | F11: Kawt Tun - 194931 | G11: 11
A12: 11001 | B12: 110010050 | C12: 194932 | D12: Kawt Tun Kwin Paing | E12: ကော့တွန်ကွင်းပိုင်း | F12: Kawt Tun Kwin Paing - 194932 | G12: 11
A13: 11001 | B13: 110010020 | C13: 194926 | D13: Kawt Wein Ywar Ma | E13: ကော့ဝိန်ရွာမ | F13: Kawt Wein Ywar Ma - 194926 | G13: 11
... A1183: 11010 | B1183: 110100080 | C1183: 195919 | D1183: Zwe Ka Lar | E1183: ဇွဲကလာ | F1183: Zwe Ka Lar - 195919 | G1183: 11
A1186: Sorted by TownshipID and Village Name

Sheet Village_Names_VT
A1: Township_ID | B1: VT_ID | C1: Village_ID | D1: Village_EN | E1: Village_MM | F1: Village_Name | G1: SR_ID
A2: 11001 | B2: 110010010 | C2: 194925 | D2: Ka Toe | E2: ကတိုး | F2: Ka Toe - 194925 | G2: 11
A3: 11001 | B3: 110010020 | C3: 194926 | D3: Kawt Wein Ywar Ma | E3: ကော့ဝိန်ရွာမ | F3: Kawt Wein Ywar Ma - 194926 | G3: 11
A4: 11001 | B4: 110010020 | C4: 194927 | D4: Kawt Wein Ywar Thit | E4: ကော့ဝိန်ရွာသစ် | F4: Kawt Wein Ywar Thit - 194927 | G4: 11
A5: 11001 | B5: 110010050 | C5: 194931 | D5: Kawt Tun | E5: ကော့တွန် | F5: Kawt Tun - 194931 | G5: 11
A6: 11001 | B6: 110010050 | C6: 194932 | D6: Kawt Tun Kwin Paing | E6: ကော့တွန်ကွင်းပိုင်း | F6: Kawt Tun Kwin Paing - 194932 | G6: 11
A7: 11001 | B7: 110010050 | C7: 194933 | D7: Zaw Ya Kyun | E7: ဇော်ရကျွန်း | F7: Zaw Ya Kyun - 194933 | G7: 11
A8: 11001 | B8: 110010060 | C8: 194934 | D8: Kawt Hnat | E8: ကော့နှပ် | F8: Kawt Hnat - 194934 | G8: 11
A9: 11001 | B9: 110010060 | C9: 194935 | D9: Kun Tar | E9: ကွမ်တာ | F9: Kun Tar - 194935 | G9: 11
A10: 11001 | B10: 110010060 | C10: 194936 | D10: Than Ka Paing | E10: သံကပိုင်း | F10: Than Ka Paing - 194936 | G10: 11
A11: 11001 | B11: 110010070 | C11: 194940 | D11: Hpe Htaw | E11: ဖဲထော် | F11: Hpe Htaw - 194940 | G11: 11
A12: 11001 | B12: 110010070 | C12: 194939 | D12: Kawt Hlar | E12: ကော့လှာ | F12: Kawt Hlar - 194939 | G12: 11
A13: 11001 | B13: 110010080 | C13: 194941 | D13: Kawt Pauk | E13: ကော့ပေါက် | F13: Kawt Pauk - 194941 | G13: 11
... A1183: 11010 | B1183: 110100500 | C1183: 196121 | D1183: Thet Kei Kyin | E1183: သက်ကယ်ကျင်း | F1183: Thet Kei Kyin - 196121 | G1183: 11
A1186: Sorted by TownshipID, Village Tract ID and Village Name

Sheet 7_Villages
A1: Township_ID | B1: VT_ID | C1: Village_ID | D1: Village_EN | E1: Village_MM | F1: VT_Pcode | G1: Village_Tract | H1: Village_Alias_EN | I1: Village_Alias_MM | J1: Longitude | K1: Latitude | L1: Source | M1: Remark | N1: Old_Village_Pcode | O1: SR_PCode | P1: SR_ID
A2: 11001 | B2: 110010010 | C2: 194925 | D2: Ka Toe | E2: ကတိုး | F2: MMR011001001 | G2: Ka Toe | J2: 97.66 | K2: 16.58 | L2: GAD, Aug 2012 | P2: 11
A3: 11001 | B3: 110010020 | C3: 194926 | D3: Kawt Wein Ywar Ma | E3: ကော့ဝိန်ရွာမ | F3: MMR011001002 | G3: Kawt Wein | J3: 97.63 | K3: 16.56 | L3: GAD, Aug 2012 | P3: 11
A4: 11001 | B4: 110010020 | C4: 194927 | D4: Kawt Wein Ywar Thit | E4: ကော့ဝိန်ရွာသစ် | F4: MMR011001002 | G4: Kawt Wein | J4: 97.64 | K4: 16.57 | L4: GAD, Aug 2012 | P4: 11
A5: 11001 | B5: 110010050 | C5: 194931 | D5: Kawt Tun | E5: ကော့တွန် | F5: MMR011001005 | G5: Kawt Tun | J5: 97.65 | K5: 16.55 | L5: GAD, Aug 2012 | P5: 11
A6: 11001 | B6: 110010050 | C6: 194932 | D6: Kawt Tun Kwin Paing | E6: ကော့တွန်ကွင်းပိုင်း | F6: MMR011001005 | G6: Kawt Tun | J6: 97.65 | K6: 16.56 | L6: GAD, Aug 2012 | P6: 11
A7: 11001 | B7: 110010050 | C7: 194933 | D7: Zaw Ya Kyun | E7: ဇော်ရကျွန်း | F7: MMR011001005 | G7: Kawt Tun | L7: GAD, Aug 2012 | P7: 11
A8: 11001 | B8: 110010060 | C8: 194934 | D8: Kawt Hnat | E8: ကော့နှပ် | F8: MMR011001006 | G8: Kawt Hnat | J8: 97.66 | K8: 16.58 | L8: GAD, Aug 2012 | P8: 11
A9: 11001 | B9: 110010060 | C9: 194935 | D9: Kun Tar | E9: ကွမ်တာ | F9: MMR011001006 | G9: Kawt Hnat | L9: GAD, Aug 2012 | P9: 11
A10: 11001 | B10: 110010060 | C10: 194936 | D10: Than Ka Paing | E10: သံကပိုင်း | F10: MMR011001006 | G10: Kawt Hnat | L10: GAD, Aug 2012 | P10: 11
A11: 11001 | B11: 110010070 | C11: 194939 | D11: Kawt Hlar | E11: ကော့လှာ | F11: MMR011001007 | G11: Kawt Hlar | J11: 97.68 | K11: 16.57 | L11: GAD, Aug 2012 | P11: 11
A12: 11001 | B12: 110010070 | C12: 194940 | D12: Hpe Htaw | E12: ဖဲထော် | F12: MMR011001007 | G12: Kawt Hlar | J12: 97.68 | K12: 16.58 | L12: GAD, Aug 2012 | P12: 11
A13: 11001 | B13: 110010080 | C13: 194941 | D13: Kawt Pauk | E13: ကော့ပေါက် | F13: MMR011001008 | G13: Kawt Pauk | J13: 97.64 | K13: 16.55 | L13: GAD, Aug 2012 | P13: 11
A14: 11001 | B14: 110010080 | C14: 194942 | D14: Ma Yan | E14: မရမ်း | F14: MMR011001008 | G14: Kawt Pauk | L14: GAD, Aug 2012 | P14: 11
A15: 11001 | B15: 110010080 | C15: 194943 | D15: Ma Yan Kwin | E15: မရမ်းကွင်း | F15: MMR011001008 | G15: Kawt Pauk | L15: GAD, Aug 2012 | P15: 11
A16: 11001 | B16: 110010100 | C16: 194946 | D16: Min Ywar | E16: မင်းရွာ | F16: MMR011001010 | G16: Min Ywar | J16: 97.67 | K16: 16.47 | L16: GAD, Aug 2012 | P16: 11
A17: 11001 | B17: 110010100 | C17: 194947 | D17: Ywar Thin | E17: ရွာသင် | F17: MMR011001010 | G17: Min Ywar | J17: 97.68 | K17: 16.46 | L17: GAD, Aug 2012 | P17: 11
A18: 11001 | B18: 110010100 | C18: 194948 | D18: Put Ta Lu Kone | E18: ပွတ္တလူးကုန်း | F18: MMR011001010 | G18: Min Ywar | L18: GAD, Aug 2012 | P18: 11
A19: 11001 | B19: 110010110 | C19: 194949 | D19: Mu Yaung | E19: မုရောင်း | F19: MMR011001011 | G19: Mu Yaung | J19: 97.69 | K19: 16.44 | L19: GAD, Aug 2012 | P19: 11
A20: 11001 | B20: 110010110 | C20: 194950 | D20: Put Ta Lu Kone | E20: ပွတ္တလူးကုန်း | F20: MMR011001011 | G20: Mu Yaung | L20: GAD, Aug 2012 | P20: 11
A21: 11001 | B21: 110010110 | C21: 194951 | D21: Kyet Thun Kone | E21: ကြက်သွန်ကုန်း | F21: MMR011001011 | G21: Mu Yaung | L21: GAD, Aug 2012 | P21: 11
A22: 11001 | B22: 110010140 | C22: 194957 | D22: Kawt Kha Ni | E22: ကော့ခနိ | F22: MMR011001014 | G22: Kawt Kha Ni | J22: 97.64 | K22: 16.39 | L22: GAD, Aug 2012 | P22: 11
A23: 11001 | B23: 110010140 | C23: 194958 | D23: Kawt Ya | E23: ကော့ရ | F23: MMR011001014 | G23: Kawt Kha Ni | L23: GAD, Aug 2012 | P23: 11
A24: 11001 | B24: 110010160 | C24: 194962 | D24: Kyar Inn | E24: ကြာအင်း | F24: MMR011001016 | G24: Kyar Inn | J24: 97.67 | K24: 16.38 | L24: GAD, Aug 2012 | P24: 11
A25: 11001 | B25: 110010160 | C25: 194963 | D25: Kha Run | E25: ခရွန်း | F25: MMR011001016 | G25: Kyar Inn | L25: GAD, Aug 2012 | P25: 11
A26: 11001 | B26: 110010160 | C26: 194964 | D26: Zaw Kone | E26: ဇော်ကုန်း | F26: MMR011001016 | G26: Kyar Inn | L26: GAD, Aug 2012 | P26: 11
A27: 11001 | B27: 110010160 | C27: 194965 | D27: Shan Ywar | E27: ရှမ်းရွာ | F27: MMR011001016 | G27: Kyar Inn | L27: GAD, Aug 2012 | P27: 11
A28: 11001 | B28: 110010170 | C28: 194966 | D28: Kawt Kha Mei | E28: ကော့ခမယ် | F28: MMR011001017 | G28: Kawt Kha Mei | J28: 97.66 | K28: 16.38 | L28: GAD, Aug 2012 | P28: 11
A29: 11001 | B29: 110010170 | C29: 194967 | D29: Kawt Kha Po | E29: ကော့ခပို | F29: MMR011001017 | G29: Kawt Kha Mei | L29: GAD, Aug 2012 | P29: 11
A30: 11001 | B30: 110010170 | C30: 194968 | D30: Thu Gyi Kone | E30: သူကြီးကုန်း | F30: MMR011001017 | G30: Kawt Kha Mei | L30: GAD, Aug 2012 | P30: 11
A31: 11001 | B31: 110010180 | C31: 194969 | D31: Hpar Auk | E31: ဖားအောက် | F31: MMR011001018 | G31: Hpar Auk | J31: 97.66 | K31: 16.37 | L31: GAD, Aug 2012 | P31: 11
A32: 11001 | B32: 110010190 | C32: 194970 | D32: Yo Go (Ywar Haung) | E32: ရိုးဂိုး (ရွာဟောင်း) | F32: MMR011001019 | G32: Yo Go | J32: 97.67 | K32: 16.36 | L32: GAD, Aug 2012 | P32: 11
A33: 11001 | B33: 110010190 | C33: 194971 | D33: Yo Go (Ywar thit) | E33: ရိုးဂိုး (ရွာသစ်) | F33: MMR011001019 | G33: Yo Go | J33: 97.67 | K33: 16.36 | L33: GAD, Aug 2012 | P33: 11
A34: 11002 | B34: 110020010 | C34: 194972 | D34: An Ka Ye | E34: အံကရဲ | F34: MMR011002001 | G34: An Ka Ye | J34: 97.85 | K34: 16.41 | L34: GAD, Aug 2012 | N34: MMR011002001001 | P34: 11
A35: 11002 | B35: 110020010 | C35: 194973 | D35: Kat Ka Taung | E35: ကပ်ကတောင် | F35: MMR011002001 | G35: An Ka Ye | J35: 97.84 | K35: 16.43 | L35: GAD, Aug 2012 | N35: MMR011002001002 | P35: 11
A36: 11002 | B36: 110020010 | C36: 194974 | D36: Daung Kone | E36: ဒေါင်းကုန်း | F36: MMR011002001 | G36: An Ka Ye | J36: 97.86 | K36: 16.43 | L36: GAD, Aug 2012 | N36: MMR011002001003 | P36: 11
A37: 11002 | B37: 110020020 | C37: 194975 | D37: Ah Hta Yan | E37: အထရံ | F37: MMR011002002 | G37: Ah Hta Yan | L37: GAD, Aug 2012 | N37: MMR011002002001 | P37: 11
A38: 11002 | B38: 110020020 | C38: 194976 | D38: Paw Law Kone | E38: ပေါလောကုန်း | F38: MMR011002002 | G38: Ah Hta Yan | J38: 97.92 | K38: 16.22 | L38: GAD, Aug 2012 | N38: MMR011002002002 | P38: 11
A39: 11002 | B39: 110020020 | C39: 194977 | D39: Mee Thway Kone | E39: မီးသွေးကုန်း | F39: MMR011002002 | G39: Ah Hta Yan | J39: 97.91 | K39: 16.21 | L39: GAD, Aug 2012 | N39: MMR011002002003 | P39: 11
A40: 11002 | B40: 110020020 | C40: 194978 | D40: Kawt Tar | E40: ကော့တာ | F40: MMR011002002 | G40: Ah Hta Yan | L40: GAD, Aug 2012 | N40: MMR011002002004 | P40: 11
A41: 11002 | B41: 110020020 | C41: 220157 | D41: Paw Law Kyun | E41: ပေါလောကျွန်း | F41: MMR011002002 | G41: Ah Hta Yan | L41: GAD, Aug 2012 | M41: New Village, GAD Aug 2012 | P41: 11
A42: 11002 | B42: 110020020 | C42: 220158 | D42: Kyauk Kwe | E42: ကျောက်ကွဲ | F42: MMR011002002 | G42: Ah Hta Yan | L42: GAD, Aug 2012 | M42: New Village, GAD Aug 2012 | P42: 11
A43: 11002 | B43: 110020030 | C43: 194979 | D43: Bar Bu Kone | E43: ဘာဘူကုန်း | F43: MMR011002003 | G43: Bar Bu Kone | J43: 97.68 | K43: 16.52 | L43: GAD, Aug 2012 | N43: MMR011002003001 | P43: 11
A44: 11002 | B44: 110020040 | C44: 194980 | D44: Bein Byaw Set Kone | E44: ဘိန်းဗျောစက်ကုန်း | F44: MMR011002004 | G44: Bein Byaw | L44: GAD, Aug 2012 | N44: MMR011002004001 | P44: 11
A45: 11002 | B45: 110020040 | C45: 194981 | D45: Bein Byaw | E45: ဘိန်းဗျော | F45: MMR011002004 | G45: Bein Byaw | J45: 97.73 | K45: 16.38 | L45: GAD, Aug 2012 | N45: MMR011002004002 | P45: 11
A46: 11002 | B46: 110020040 | C46: 194982 | D46: Bein Byaw Ywar Thit | E46: ဘိန်းဗျောရွာသစ် | F46: MMR011002004 | G46: Bein Byaw | J46: 97.72 | K46: 16.38 | L46: GAD, Aug 2012 | N46: MMR011002004003 | P46: 11
A47: 11002 | B47: 110020040 | C47: 194983 | D47: Nat San | E47: နတ်စမ်း | F47: MMR011002004 | G47: Bein Byaw | J47: 97.7 | K47: 16.39 | L47: GAD, Aug 2012 | N47: MMR011002004004 | P47: 11
A48: 11002 | B48: 110020040 | C48: 194984 | D48: Hpa Yar Kone | E48: ဘုရားကုန်း | F48: MMR011002004 | G48: Bein Byaw | J48: 97.72 | K48: 16.38 | L48: GAD, Aug 2012 | N48: MMR011002004005 | P48: 11
A49: 11002 | B49: 110020040 | C49: 220159 | D49: Ma Yan Chan | E49: မရမ်းခြံ | F49: MMR011002004 | G49: Bein Byaw | L49: GAD, Aug 2012 | M49: New Village, GAD Aug 2012 | P49: 11
A50: 11002 | B50: 110020040 | C50: 220160 | D50: San Hnit Khwa | E50: စမ်းနှစ်ခွ | F50: MMR011002004 | G50: Bein Byaw | L50: GAD, Aug 2012 | M50: New Village, GAD Aug 2012 | P50: 11
A51: 11002 | B51: 110020040 | C51: 220161 | D51: Aye Yeik Thar | E51: အေးရိပ်သာ | F51: MMR011002004 | G51: Bein Byaw | L51: GAD, Aug 2012 | M51: New Village, GAD Aug 2012 | P51: 11
A52: 11002 | B52: 110020040 | C52: 220162 | D52: Ah Hta Yan | E52: အထရံ | F52: MMR011002004 | G52: Bein Byaw | L52: GAD, Aug 2012 | M52: New Village, GAD Aug 2012 | P52: 11
A53: 11002 | B53: 110020040 | C53: 220163 | D53: Ye Mon | E53: ရဲမွန် | F53: MMR011002004 | G53: Bein Byaw | L53: GAD, Aug 2012 | M53: New Village, GAD Aug 2012 | P53: 11
A54: 11002 | B54: 110020050 | C54: 194985 | D54: Dhamma Tha | E54: ဓမ္မဿ | F54: MMR011002005 | G54: Dhamma Tha | J54: 97.82 | K54: 16.51 | L54: GAD, Aug 2012 | N54: MMR011002005001 | P54: 11
A55: 11002 | B55: 110020060 | C55: 194986 | D55: Hla Ka Zaing | E55: လှကဇိုင်း | F55: MMR011002006 | G55: Hla Ka Zaing | J55: 97.91 | K55: 16.16 | L55: GAD, Aug 2012 | N55: MMR011002006001 | P55: 11
A56: 11002 | B56: 110020060 | C56: 194987 | D56: Taung Kalay | E56: တောင်ကလေး | F56: MMR011002006 | G56: Hla Ka Zaing | J56: 97.9 | K56: 16.19 | L56: GAD, Aug 2012 | N56: MMR011002006002 | P56: 11
A57: 11002 | B57: 110020060 | C57: 194988 | D57: Mei Ta Ri | E57: မယ်တရိ | F57: MMR011002006 | G57: Hla Ka Zaing | J57: 97.94 | K57: 16.18 | L57: GAD, Aug 2012 | N57: MMR011002006003 | P57: 11
A58: 11002 | B58: 110020060 | C58: 194989 | D58: Hpet Tay Kone | E58: ဖက်တေးကုန်း | F58: MMR011002006 | G58: Hla Ka Zaing | J58: 97.94 | K58: 16.18 | L58: GAD, Aug 2012 | N58: MMR011002006004 | P58: 11
A59: 11002 | B59: 110020060 | C59: 194990 | D59: Htaw Pa Lawt | E59: ထော်ပလော့ | F59: MMR011002006 | G59: Hla Ka Zaing | J59: 97.89 | K59: 16.15 | L59: GAD, Aug 2012 | N59: MMR011002006005 | P59: 11
A60: 11002 | B60: 110020070 | C60: 194991 | D60: Ka Dar | E60: ကဒါ | F60: MMR011002007 | G60: Ka Dar | J60: 97.84 | K60: 16.23 | L60: GAD, Aug 2012 | N60: MMR011002007001 | P60: 11
A61: 11002 | B61: 110020070 | C61: 194992 | D61: Tha Yet Kone | E61: သရက်ကုန်း | F61: MMR011002007 | G61: Ka Dar | J61: 97.87 | K61: 16.24 | L61: GAD, Aug 2012 | N61: MMR011002007002 | P61: 11
A62: 11002 | B62: 110020070 | C62: 194993 | D62: Kyan Taw | E62: ကြံတော | F62: MMR011002007 | G62: Ka Dar | J62: 97.88 | K62: 16.21 | L62: GAD, Aug 2012 | N62: MMR011002007003 | P62: 11
A63: 11002 | B63: 110020070 | C63: 194994 | D63: Hlaing Ka Mein | E63: လှိုင်ကမိန် | F63: MMR011002007 | G63: Ka Dar | L63: GAD, Aug 2012 | N63: MMR011002007004 | P63: 11
A64: 11002 | B64: 110020070 | C64: 194995 | D64: Ka Naing Lo | E64: ကနိုင်လို | F64: MMR011002007 | G64: Ka Dar | L64: GAD, Aug 2012 | N64: MMR011002007005 | P64: 11
A65: 11002 | B65: 110020070 | C65: 220164 | D65: Ka Dar Shan Ywar | E65: ကဒါရှမ်းရွာ | F65: MMR011002007 | G65: Ka Dar | L65: GAD, Aug 2012 | M65: New Village, GAD Aug 2012 | P65: 11
A66: 11002 | B66: 110020070 | C66: 220165 | D66: Nwut Li | E66: နွတ်လီ | F66: MMR011002007 | G66: Ka Dar | L66: GAD, Aug 2012 | M66: New Village, GAD Aug 2012 | P66: 11
A67: 11002 | B67: 110020070 | C67: 220166 | D67: Kawt Ka Lain Taung | E67: ကော့ကလိမ်တောင် | F67: MMR011002007 | G67: Ka Dar | L67: GAD, Aug 2012 | M67: New Village, GAD Aug 2012 | P67: 11
A68: 11002 | B68: 110020070 | C68: 220167 | D68: Paw Taw Mu | E68: ပေါ်တော်မူ | F68: MMR011002007 | G68: Ka Dar | L68: GAD, Aug 2012 | M68: New Village, GAD Aug 2012 | P68: 11
A69: 11002 | B69: 110020070 | C69: 220168 | D69: Lone Pi Myauk | E69: လုံပိမြောက် | F69: MMR011002007 | G69: Ka Dar | L69: GAD, Aug 2012 | M69: New Village, GAD Aug 2012 | P69: 11
A70: 11002 | B70: 110020080 | C70: 194997 | D70: Ka Laing Ka Naing | E70: ကလိုင်းကနိုင် | F70: MMR011002008 | G70: Ka Laing Ka Naing | J70: 97.73 | K70: 16.35 | L70: GAD, Aug 2012 | N70: MMR011002008001 | P70: 11
A71: 11002 | B71: 110020080 | C71: 194998 | D71: Ah Paw Ywar | E71: အပေါ်ရွာ | F71: MMR011002008 | G71: Ka Laing Ka Naing | L71: GAD, Aug 2012 | N71: MMR011002008002 | P71: 11
A72: 11002 | B72: 110020080 | C72: 194999 | D72: Thone Ein Su | E72: သုံးအိမ်စု | F72: MMR011002008 | G72: Ka Laing Ka Naing | L72: GAD, Aug 2012 | N72: MMR011002008003 | P72: 11
A73: 11002 | B73: 110020080 | C73: 195000 | D73: Auk Ywar | E73: အောက်ရွာ | F73: MMR011002008 | G73: Ka Laing Ka Naing | J73: 97.73 | K73: 16.36 | L73: GAD, Aug 2012 | N73: MMR011002008004 | P73: 11
A74: 11002 | B74: 110020080 | C74: 195001 | D74: Ka Zun Kone | E74: ကဇွန်းကုန်း | F74: MMR011002008 | G74: Ka Laing Ka Naing | L74: GAD, Aug 2012 | N74: MMR011002008005 | P74: 11
A75: 11002 | B75: 110020090 | C75: 195002 | D75: Kha Naung | E75: ခနောင် | F75: MMR011002009 | G75: Kha Naung | J75: 97.71 | K75: 16.42 | L75: GAD, Aug 2012 | N75: MMR011002009001 | P75: 11
A76: 11002 | B76: 110020100 | C76: 195003 | D76: Kawt Bwee | E76: ကော့ဘွီး | F76: MMR011002010 | G76: Kawt Bwee | J76: 97.75 | K76: 16.46 | L76: GAD, Aug 2012 | N76: MMR011002010001 | P76: 11
A77: 11002 | B77: 110020100 | C77: 195004 | D77: Kawt Wan | E77: ကော့ဝမ်း | F77: MMR011002010 | G77: Kawt Bwee | J77: 97.79 | K77: 16.42 | L77: GAD, Aug 2012 | N77: MMR011002010002 | P77: 11
A78: 11002 | B78: 110020100 | C78: 195005 | D78: Ah Hlat Kone | E78: အလှပ်ကုန်း | F78: MMR011002010 | G78: Kawt Bwee | J78: 97.78 | K78: 16.46 | L78: GAD, Aug 2012 | N78: MMR011002010003 | P78: 11
A79: 11002 | B79: 110020100 | C79: 195006 | D79: An Ka Sin | E79: အံကစင် | F79: MMR011002010 | G79: Kawt Bwee | J79: 97.79 | K79: 16.45 | L79: GAD, Aug 2012 | N79: MMR011002010004 | P79: 11
A80: 11002 | B80: 110020110 | C80: 195007 | D80: Kawt Kha Lein | E80: ကော့ခလိန် | F80: MMR011002011 | G80: Kawt Kha Lein | J80: 97.85 | K80: 16.45 | L80: GAD, Aug 2012 | N80: MMR011002011001 | P80: 11
A81: 11002 | B81: 110020110 | C81: 195008 | D81: Kawt Kyaik | E81: ကော့ကျိုက် | F81: MMR011002011 | G81: Kawt Kha Lein | J81: 97.83 | K81: 16.47 | L81: GAD, Aug 2012 | N81: MMR011002011002 | P81: 11
A82: 11002 | B82: 110020110 | C82: 195009 | D82: Kyar Inn Chaung | E82: ကြာအင်းချောင် | F82: MMR011002011 | G82: Kawt Kha Lein | J82: 97.83 | K82: 16.45 | L82: GAD, Aug 2012 | N82: MMR011002011003 | P82: 11
A83: 11002 | B83: 110020120 | C83: 195010 | D83: Kawt Pa Laing | E83: ကော့ပလိုင် | F83: MMR011002012 | G83: Kawt Pa Laing | L83: GAD, Aug 2012 | N83: MMR011002012001 | P83: 11
A84: 11002 | B84: 110020130 | C84: 195011 | D84: Kawt Ka Lawt | E84: ကော့ကလော့ | F84: MMR011002013 | G84: Kawt Ka Lawt | J84: 97.8 | K84: 16.3 | L84: GAD, Aug 2012 | N84: MMR011002013001 | P84: 11
A85: 11002 | B85: 110020130 | C85: 195012 | D85: Ka Ton Ka Ye | E85: ကတုံကရဲ | F85: MMR011002013 | G85: Kawt Ka Lawt | L85: GAD, Aug 2012 | N85: MMR011002013002 | P85: 11
A86: 11002 | B86: 110020130 | C86: 195013 | D86: Pan Kone | E86: ပန်းကုန်း | F86: MMR011002013 | G86: Kawt Ka Lawt | J86: 97.78 | K86: 16.29 | L86: GAD, Aug 2012 | N86: MMR011002013003 | P86: 11
A87: 11002 | B87: 110020130 | C87: 195014 | D87: Thin Gan Chaung | E87: သင်္ဃန်းချောင် | F87: MMR011002013 | G87: Kawt Ka Lawt | J87: 97.79 | K87: 16.29 | L87: GAD, Aug 2012 | N87: MMR011002013004 | P87: 11
A88: 11002 | B88: 110020130 | C88: 195015 | D88: Me Ka Than | E88: မဲကသံ | F88: MMR011002013 | G88: Kawt Ka Lawt | J88: 97.83 | K88: 16.32 | L88: GAD, Aug 2012 | N88: MMR011002013005 | P88: 11
A89: 11002 | B89: 110020130 | C89: 195016 | D89: U To Chaung | E89: ဦးတိုချောင် | F89: MMR011002013 | G89: Kawt Ka Lawt | J89: 97.79 | K89: 16.28 | L89: GAD, Aug 2012 | N89: MMR011002013006 | P89: 11
A90: 11002 | B90: 110020130 | C90: 195017 | D90: Kawt Dun | E90: ကော့ဒွန်း | F90: MMR011002013 | G90: Kawt Ka Lawt | J90: 97.81 | K90: 16.31 | L90: GAD, Aug 2012 | N90: MMR011002013007 | P90: 11
A91: 11002 | B91: 110020130 | C91: 195018 | D91: Shan Ywar Gyi | E91: ရှမ်းရွာကြီး | F91: MMR011002013 | G91: Kawt Ka Lawt | J91: 97.77 | K91: 16.31 | L91: GAD, Aug 2012 | N91: MMR011002013008 | P91: 11
A92: 11002 | B92: 110020130 | C92: 195019 | D92: Mway Hauk | E92: မွေဟောက် | F92: MMR011002013 | G92: Kawt Ka Lawt | J92: 97.78 | K92: 16.3 | L92: GAD, Aug 2012 | N92: MMR011002013009 | P92: 11
A93: 11002 | B93: 110020140 | C93: 195020 | D93: Kawt Pa Naw | E93: ကော့ပနော | F93: MMR011002014 | G93: Kawt Pa Naw | J93: 97.81 | K93: 16.39 | L93: GAD, Aug 2012 | N93: MMR011002014001 | P93: 11
A94: 11002 | B94: 110020140 | C94: 195021 | D94: Kawt Dun | E94: ကော့ဒွန်း | F94: MMR011002014 | G94: Kawt Pa Naw | J94: 97.81 | K94: 16.38 | L94: GAD, Aug 2012 | N94: MMR011002014002 | P94: 11
A95: 11002 | B95: 110020140 | C95: 195022 | D95: Wea Ngeit | E95: ဝဲငဲ့ | F95: MMR011002014 | G95: Kawt Pa Naw | J95: 97.81 | K95: 16.4 | L95: GAD, Aug 2012 | N95: MMR011002014003 | P95: 11
A96: 11002 | B96: 110020150 | C96: 195023 | D96: Kawt That | E96: ကော့သတ် | F96: MMR011002015 | G96: Kawt That | J96: 97.76 | K96: 16.52 | L96: GAD, Aug 2012 | N96: MMR011002015001 | P96: 11
A97: 11002 | B97: 110020160 | C97: 195024 | D97: Kha Yon | E97: ခရုံ | F97: MMR011002016 | G97: Kha Yon | J97: 97.7 | K97: 16.54 | L97: GAD, Aug 2012 | N97: MMR011002016001 | P97: 11
... A100: 11002 | B100: 110020180 | C100: 195027 | D100: Kyaik Pa Yan | E100: ကျိုက်ပရံ | F100: MMR011002018 | G100: Kyaik Pa Yan | J100: 97.71 | K100: 16.47 | L100: GAD, Aug 2012 | N100: MMR011002018001 | P100: 11
A101: 11002 | B101: 110020180 | C101: 195028 | D101: Kawt Pyay | E101: ကော့ပြည် | F101: MMR011002018 | G101: Kyaik Pa Yan | L101: GAD, Aug 2012 | N101: MMR011002018002 | P101: 11
A102: 11002 | B102: 110020190 | C102: 195029 | D102: Kyee Oke | E102: ကြီးအုပ် | F102: MMR011002019 | G102: Kyee Oke | J102: 97.94 | K102: 16.4 | L102: GAD, Aug 2012 | N102: MMR011002019001 | P102: 11
...

Sheet Clean_SchoolInfo
A1: School_ID | B1: VT_Ward_ID | C1: Village_ID | D1: School_Name | E1: Academic_Year_ID | F1: Latitude | G1: Longitude
A2: =CLEAN(Selected_School_ID) -> 11008018001 | B2: =Selected_Ward_VT_ID -> 110080180 | C2: =IFERROR(Selected_Village_ID,"") -> 195703 | D2: =CLEAN(Selected_School_Name) -> အ.ထ.က ရင်ငြိမ် | E2: =AcademicYear_ID -> 2014 | F2: ='SA-1'!$L$31 -> 0 | G2: ='SA-1'!$L$35 -> 0
A4: =LEN(A2) -> 11 | B4: =LEN(B2) -> 9 | C4: =LEN(C2) -> 6 | D4: =LEN(D2) -> 14 | E4: =LEN(E2) -> 4

Sheet Clean_School_AYInfo
A1: School_AY_Info_ID | B1: School_ID | C1: Academic_Year_ID
A2: ="30" & AcademicYear_ID& "" & Selected_School_ID -> 30201411008018001 | B2: =CLEAN(Selected_School_ID) -> 11008018001 | C2: =AcademicYear_ID -> 2014
A5: =LEN(SchoolAY_Info_ID) -> 17 | B5: =LEN(B2) -> 11 | C5: =LEN(C2) -> 4

Sheet Form_Setup
C1: Welcome to the Township Education Management System. In order to use this program, click 'Options...' on the Message Bar and select 'Enable this content'. Alternatively, open the file with Macro Control from a Trusted Location.
A3: Township_ID | B3: TS_PCode | C3: NEMIS_TS_Index | D3: Township_EN | E3: Township_MM | F3: State / Region ID | G3: SR_PCode | H3: State_Region_EN | I3: State_Region_MM | J3: D_PCode | K3: District | L3: MYA_INFO_TS_ID | M3: Source | N3: Remark
A4: 11008 | B4: MMR011008 | C4: 180 | D4: Paung | E4: ပေါင် | F4: 11 | G4: MMR011 | H4: Mon | I4: မွန်ပြည်နယ် | J4: MMR011D002 | K4: Thaton | L4: ASIMMR011008 | M4: GAD, Aug 2012
B7: Academic Start Date | C7: Academic End Date | F7: IncomeTypeCode | G7: IncomeTypeName | I7: ExpenditureTypeCode | J7: ExpenditureTypeName
B8: 41426 | C8: 41727 | F8: 1 | G8: School Fees | I8: 1 | J8: Ordinary
F9: 2 | I9: 2 | J9: Lump Sum
F10: 3 | I10: 3
F11: 4 | I11: 4
F12: 5 | I12: 5
B14: Monitoring Learning Achievement (Grade 9, 10, 11) (Every half year test)
C15: Month Name | D15: Moth in Digits
B16: First-Half Year End Test | C16: September | D16: =INDEX(Month_List,MATCH($C16,Month_Name,0),1) -> 09
B17: Second-Half Year End Test | C17: February | D17: =INDEX(Month_List,MATCH($C17,Month_Name,0),1) -> 02
B20: Today Date | C20: 41727
B22: Current System Date | C22: =TODAY() -> 42072

Sheet SA-1
B1: The Republic of the Union of Myanmar
B2: Ministry of Education
B3: Township Education Management Information System
B4: SCHOOL INFORMATION (END OF FEBRUARY)
F6: Academic Year | G6: =AcademicYear_Name -> 2013-2014 | J6: Feb
D8: Township | E8: =Township_Name_EN -> Paung | J8: State / Region | K8: =StateRegion_Name_EN -> Mon
D9: TS_Myanmar | E9: =Township_Name_MM -> ပေါင် | J9: SR_Myanmar | K9: =StateRegion_Name_MM -> မွန်ပြည်နယ်
A11: 1 | B11: Location
A13: 2 | B13: Village Tract / Ward | H13: =IFERROR(IF(CLEAN(Selected_Urban_Rural)=CLEAN(1),INDEX('5_Wards'!B2:D87,MATCH(CLEAN(Selected_Ward_VT_ID),'5_Wards'!B2:B87,0),3),INDEX('6_Village_Tracts'!B2:D378,MATCH(CLEAN(Selected_Ward_VT_ID),'6_Village_Tracts'!B2:B378,0),3)),"") -> ရင်းငြိမ် (မြောက်)
A15: 3 | B15: Village | H15: =IFERROR(IF(CLEAN(Selected_Urban_Rural)=CLEAN(1),$A$1,INDEX('7_Villages'!C2:E1183,MATCH(VALUE(Selected_Village_ID),'7_Villages'!C2:C1183,0),3)),"") -> ရင်းငြိမ် (မြောက်)
A17: 4 | B17: School Suffix ID | D17: =IFERROR(CLEAN(Selected_Ward_VT_ID),"") -> 110080180 | F17: 01 | H17: School ID | I17: =IFERROR( CLEAN(Selected_Ward_VT_ID) & F17,"") -> 11008018001
B19: School Name | D19: အ.ထ.က ရင်ငြိမ်
A22: 5 | B22: School Level | C22: =SUM(PRODUCT(C25*1),PRODUCT(D25*2),PRODUCT(E25*3),PRODUCT(F25*4),PRODUCT(G25*5),PRODUCT(H25*6),PRODUCT(I25*7),PRODUCT(J25*8),PRODUCT(K25*9),PRODUCT(L25*10),PRODUCT(M25*11),PRODUCT(N25*12)) -> 1
B24: School Level | C24: SHS | D24: SMS | E24: SPS | F24: Br-High | G24: Br-Mid | H24: Br-Pri | I24: Af-High | J24: Af-Mid | K24: Af-Pri | L24: Post-Pri | M24: Monastic | N24: Community
C25: 1 | D25: 0 | E25: 0 | F25: 0 | G25: 0 | H25: 0 | I25: 0 | J25: 0 | K25: 0 | L25: 0 | M25: 0 | N25: 0
C27: Level exist | L27: GeoLocation
A29: 6 | B29: If your school is an affiliated or branch or post primary school, which main school is your school attached to? | L29: Latitude
C31: Main School Suffix ID | D31: =Township_ID -> 11008 | H31: Main School ID | I31: =Township_ID & E31 -> 11008
C33: Main school name | L33: Longitude
A35: 7 | B35: Shift of school | D35: One | E35: Two | F35: 8 | G35: School Board of Trustee | I35: Yes | J35: No
D36: 1 | I36: 1
A39: 9 | B39: Distance from TEO office | D39: 12 | E39: Mile
A41: 10 | B41: School land ownership | J41: If Govt
C42: Land Ownership | D42: Govt | E42: Monastery | F42: Private | G42: Faith | H42: Other | J42: Govt Land Type | K42: Garan | L42: Lana39 | M42: F-105
B43: =SUM(PRODUCT(D43,1),PRODUCT(E43,2),PRODUCT(F43,3),PRODUCT(G43,4),PRODUCT(H43,5)) -> 1 | D43: 1 | E43: 0 | F43: 0 | G43: 0 | H43: 0 | I43: =SUM(PRODUCT(K43,1),PRODUCT(L43,2),PRODUCT(M43,3)) -> 2 | K43: 0 | L43: 1 | M43: 0
A45: 11 | B45: Area of school compound | D45: Length | F45: feet | G45: Width | I45: feet | K45: In Area | L45: 9.84 | M45: Acre
A48: 12 | B48: School Facilities (Number)
C50: 4 | D50: Four seated Tables | F50: 41 | G50: =INDEX(Facility_List,MATCH(D50,Facility_Name,0),1) -> 1 | H50: 4 | I50: Four seated Chairs | K50: 41 | L50: =INDEX(Facility_List,MATCH(I50,Facility_Name,0),1) -> 2
C52: 3 | D52: Three seated Tables | F52: 218 | G52: =INDEX(Facility_List,MATCH(D52,Facility_Name,0),1) -> 3 | H52: 3 | I52: Three seated Chairs | K52: 218 | L52: =INDEX(Facility_List,MATCH(I52,Facility_Name,0),1) -> 4
C54: 2 | D54: Two seated Tables | G54: =INDEX(Facility_List,MATCH(D54,Facility_Name,0),1) -> 5 | H54: 2 | I54: Two seated Chairs | L54: =INDEX(Facility_List,MATCH(I54,Facility_Name,0),1) -> 6
C56: 1 | D56: One seated Tables | F56: 184 | G56: =INDEX(Facility_List,MATCH(D56,Facility_Name,0),1) -> 7 | H56: 1 | I56: One seated Chairs | K56: 184 | L56: =INDEX(Facility_List,MATCH(I56,Facility_Name,0),1) -> 8
D58: Tables (4 seated; low) | G58: =INDEX(Facility_List,MATCH(D58,Facility_Name,0),1) -> 9
D60: Teacher Tables | F60: 17 | G60: =INDEX(Facility_List,MATCH(D60,Facility_Name,0),1) -> 10 | I60: Teacher Chairs | K60: 17 | L60: =INDEX(Facility_List,MATCH(I60,Facility_Name,0),1) -> 11
D62: Black/White board | F62: 17 | G62: =INDEX(Facility_List,MATCH(D62,Facility_Name,0),1) -> 12 | I62: OHP/LCD | L62: =INDEX(Facility_List,MATCH(I62,Facility_Name,0),1) -> 13
D64: Total Computers | F64: 4 | G64: =INDEX(Facility_List,MATCH(D64,Facility_Name,0),1) -> 14 | I64: Usable Computers | K64: 1 | L64: =INDEX(Facility_List,MATCH(I64,Facility_Name,0),1) -> 15
D66: Total Printers | F66: 1 | G66: =INDEX(Facility_List,MATCH(D66,Facility_Name,0),1) -> 16 | I66: Usable Printers | K66: 1 | L66: =INDEX(Facility_List,MATCH(I66,Facility_Name,0),1) -> 17
D68: Total Type Writers | F68: 1 | G68: =INDEX(Facility_List,MATCH(D68,Facility_Name,0),1) -> 18 | I68: Usable Type Writers | K68: 0 | L68: =INDEX(Facility_List,MATCH(I68,Facility_Name,0),1) -> 19
D70: Total Radio Cassette | F70: 1 | G70: =INDEX(Facility_List,MATCH(D70,Facility_Name,0),1) -> 20 | I70: Usable Radio Cassette | K70: 1 | L70: =INDEX(Facility_List,MATCH(I70,Facility_Name,0),1) -> 21
D72: Total TV | F72: 3 | G72: =INDEX(Facility_List,MATCH(D72,Facility_Name,0),1) -> 22 | I72: Usable TV | K72: 3 | L72: =INDEX(Facility_List,MATCH(I72,Facility_Name,0),1) -> 23
D74: Total VCD | G74: =INDEX(Facility_List,MATCH(D74,Facility_Name,0),1) -> 24 | I74: Usable VCD | L74: =INDEX(Facility_List,MATCH(I74,Facility_Name,0),1) -> 25
D76: Total Copier | F76: 1 | G76: =INDEX(Facility_List,MATCH(D76,Facility_Name,0),1) -> 26 | I76: Usable Copier | K76: 1 | L76: =INDEX(Facility_List,MATCH(I76,Facility_Name,0),1) -> 27
D78: Total Fans | F78: 3 | G78: =INDEX(Facility_List,MATCH(D78,Facility_Name,0),1) -> 28 | I78: Usable Fans | K78: 3 | L78: =INDEX(Facility_List,MATCH(I78,Facility_Name,0),1) -> 29
D80: Cupboards | F80: 15 | G80: =INDEX(Facility_List,MATCH(D80,Facility_Name,0),1) -> 30
A83: 13 | B83: School Library
C84: School Library | D84: Yes | F84: 1 | H84: If yes, is it a separate room? adequate for teaching
D85: No | H85: School Library | I85: Yes | J85: 1
I86: No
B88: Number of books in library | D88: 500 | H88: If yes, are the students allowed to borrow?
H89: School Library | I89: Yes | J89: 1
I90: No
A93: 14 | B93: Science Lab
C94: School Lab | D94: Yes | F94: 1 | H94: If yes, are there enough lab facilities? adequate for teaching
D95: No | H95: School Lab | I95: Yes | J95: 0
I96: No
A99: 15 | B99: Media / Platform
C100: Media / Platform | D100: Media | E100: 3 Platforms | F100: 2 Platforms | G100: 1 Platform | J100: Are they in use?
B101: =SUM(PRODUCT(D101,1),PRODUCT(E101,2),PRODUCT(F101,3),PRODUCT(G101,4)) -> 1 | D101: 1 | E101: 0 | F101: 0 | G101: 0 | I101: Media / Platform | J101: In Use | K101: 1
J102: Not in use
A105: 16 | B105: E-learning
C106: E-Learning Centre | D106: Yes | E106: 1 | H106: Are they in use?
D107: No | G107: E-Learning Centre | H107: In Use | I107: 1
H108: Not in use
M111: Paper Form Signed By
M112: Name | P112: ငွေဝင်း
M113: Office Post | P113: 7
M114: Signed Date (DD/MM/YYYY) | P114: 41768

Sheet Clean_SA_1 _Head
A1: SA_1_ID | B1: School_AY_Info_ID | C1: AcdemicMonth
A2: ="31" & C2 & AcademicYear_ID& "" & TSIndex_SchoolID -> 31022014180018001 | B2: =CLEAN(SchoolAY_Info_ID) -> 30201411008018001 | C2: 02
A5: =LEN($A$2) -> 17 | B5: =LEN($B$2) -> 17 | C5: =LEN($C$2) -> 2 | D5: =LEN($D$2) -> 0 | E5: =LEN($E$2) -> 0 | F5: =LEN($F$2) -> 0
E7: =8+11 -> 19

Sheet Clean_SA_1 SchoolDetailInfo
A1: SA_1_ID | B1: SchoolLevel_ID | C1: SchoolLevelExist_ID | D1: MainSchool_ID | E1: ShiftOfSchool_ID | F1: BoardOfTrustee_YN
A2: =SA_1_ID -> 31022014180018001 | B2: =Selected_School_Level -> 1 | C2: =Selected_School_Level_Exist -> 6 | D2: =IFERROR(Selected_School_ID,"") -> 11008018001 | E2: =Selected_SchoolShiftType -> 1 | F2: ='SA-1'!$I$36 -> 1
A5: =LEN($A$2) -> 17 | B5: =LEN($B$2) -> 1 | C5: =LEN($C$2) -> 1 | D5: =LEN($D$2) -> 11 | E5: =LEN($E$2) -> 1 | F5: =LEN($F$2) -> 1

Sheet Clean_SA_1 _SchoolLandInfo
A1: SA_1_ID | B1: SchoolLandOwnershipType_ID | C1: SchoolLandType_ID | D1: SchoolCompound_Length_Feet | E1: SchoolCompound_Width_Feet | F1: SchoolCompound_Area_Arca
A2: =SA_1_ID -> 31022014180018001 | B2: =Selected_LandOwnership -> 1 | C2: =IF(Selected_LandType>0,Selected_LandType,"") -> 2 | D2: ='SA-1'!$E$45 -> 0 | E2: ='SA-1'!$H$45 -> 0 | F2: ='SA-1'!$L$45 -> 9.84
A5: =LEN($A$2) -> 17 | B5: =LEN($B$2) -> 1 | C5: =LEN($C$2) -> 1 | D5: =LEN($D$2) -> 1 | E5: =LEN($E$2) -> 1 | F5: =LEN($F$2) -> 4

Sheet Clean_SA_1 Facilities_Info
A1: SA_1_FacilityID | B1: SA_1_ID | C1: Facility_ID | E1: Facility_Capacity
A2: =B2&C2 -> 310220141800180011 | B2: =SA_1_ID -> 31022014180018001 | C2: ='SA-1'!$G$50 -> 1 | D2: FourSeated_Table | E2: ='SA-1'!$F$50 -> 41
A3: =B3&C3 -> 310220141800180012 | B3: =SA_1_ID -> 31022014180018001 | C3: ='SA-1'!$L$50 -> 2 | D3: FourSeated_Chair | E3: ='SA-1'!$K$50 -> 41
A4: =B4&C4 -> 310220141800180013 | B4: =SA_1_ID -> 31022014180018001 | C4: ='SA-1'!$G$52 -> 3 | D4: ThreeSeated_Table | E4: ='SA-1'!$F$52 -> 218
A5: =B5&C5 -> 310220141800180014 | B5: =SA_1_ID -> 31022014180018001 | C5: ='SA-1'!$L$52 -> 4 | D5: ThreeSeated_Chair | E5: ='SA-1'!$K$52 -> 218
A6: =B6&C6 -> 310220141800180017 | B6: =SA_1_ID -> 31022014180018001 | C6: ='SA-1'!$G$56 -> 7 | D6: TwoSeated_Table | E6: ='SA-1'!$F$56 -> 184
A7: =B7&C7 -> 310220141800180016 | B7: =SA_1_ID -> 31022014180018001 | C7: ='SA-1'!$L$54 -> 6 | D7: TwoSeated_Chair | E7: ='SA-1'!$K$54 -> 0
A8: =B8&C8 -> 310220141800180017 | B8: =SA_1_ID -> 31022014180018001 | C8: ='SA-1'!$G$56 -> 7 | D8: OneSeated_Table | E8: ='SA-1'!$F$56 -> 184
A9: =B9&C9 -> 310220141800180018 | B9: =SA_1_ID -> 31022014180018001 | C9: ='SA-1'!$L$56 -> 8 | D9: OneSeated_Chair | E9: ='SA-1'!$K$56 -> 184
A10: =B10&C10 -> 310220141800180019 | B10: =SA_1_ID -> 31022014180018001 | C10: ='SA-1'!$G$58 -> 9 | D10: Short_Table | E10: ='SA-1'!$F$58 -> 0
A11: =B11&C11 -> 3102201418001800110 | B11: =SA_1_ID -> 31022014180018001 | C11: ='SA-1'!$G$60 -> 10 | D11: Teacher_Table | E11: ='SA-1'!$F$60 -> 17
A12: =B12&C12 -> 3102201418001800111 | B12: =SA_1_ID -> 31022014180018001 | C12: ='SA-1'!$L$60 -> 11 | D12: Teacher_Chair | E12: ='SA-1'!$K$60 -> 17
A13: =B13&C13 -> 3102201418001800112 | B13: =SA_1_ID -> 31022014180018001 | C13: ='SA-1'!$G$62 -> 12 | D13: BlackWhite_Board | E13: ='SA-1'!$F$62 -> 17
A14: =B14&C14 -> 3102201418001800113 | B14: =SA_1_ID -> 31022014180018001 | C14: ='SA-1'!$L$62 -> 13 | D14: OHP_LCD | E14: ='SA-1'!$K$62 -> 0
A15: =B15&C15 -> 3102201418001800114 | B15: =SA_1_ID -> 31022014180018001 | C15: ='SA-1'!$G$64 -> 14 | D15: Total_Computer | E15: ='SA-1'!$F$64 -> 4
A16: =B16&C16 -> 3102201418001800115 | B16: =SA_1_ID -> 31022014180018001 | C16: ='SA-1'!$L$64 -> 15 | D16: Usable_Computer | E16: ='SA-1'!$K$64 -> 1
A17: =B17&C17 -> 3102201418001800116 | B17: =SA_1_ID -> 31022014180018001 | C17: ='SA-1'!$G$66 -> 16 | D17: Total_Printer | E17: ='SA-1'!$F$66 -> 1
A18: =B18&C18 -> 3102201418001800117 | B18: =SA_1_ID -> 31022014180018001 | C18: ='SA-1'!$L$66 -> 17 | D18: Usable_Printer | E18: ='SA-1'!$K$66 -> 1
A19: =B19&C19 -> 3102201418001800118 | B19: =SA_1_ID -> 31022014180018001 | C19: ='SA-1'!$G$68 -> 18 | D19: Total_TypeWriter | E19: ='SA-1'!$F$68 -> 1
A20: =B20&C20 -> 3102201418001800119 | B20: =SA_1_ID -> 31022014180018001 | C20: ='SA-1'!$L$68 -> 19 | D20: Usable_TypeWriter | E20: ='SA-1'!$K$68 -> 0
A21: =B21&C21 -> 3102201418001800120 | B21: =SA_1_ID -> 31022014180018001 | C21: ='SA-1'!$G$70 -> 20 | D21: Total_RadioCassette | E21: ='SA-1'!$F$70 -> 1
A22: =B22&C22 -> 3102201418001800121 | B22: =SA_1_ID -> 31022014180018001 | C22: ='SA-1'!$L$70 -> 21 | D22: Usable_RadioCassette | E22: ='SA-1'!$K$70 -> 1
A23: =B23&C23 -> 3102201418001800122 | B23: =SA_1_ID -> 31022014180018001 | C23: ='SA-1'!$G$72 -> 22 | D23: Total_TV | E23: ='SA-1'!$F$72 -> 3
A24: =B24&C24 -> 3102201418001800123 | B24: =SA_1_ID -> 31022014180018001 | C24: ='SA-1'!$L$72 -> 23 | D24: Usable_TV | E24: ='SA-1'!$K$72 -> 3
A25: =B25&C25 -> 3102201418001800124 | B25: =SA_1_ID -> 31022014180018001 | C25: ='SA-1'!$G$74 -> 24 | D25: Total_VCD | E25: ='SA-1'!$F$74 -> 0
A26: =B26&C26 -> 3102201418001800125 | B26: =SA_1_ID -> 31022014180018001 | C26: ='SA-1'!$L$74 -> 25 | D26: Usable_VCD | E26: ='SA-1'!$K$74 -> 0
A27: =B27&C27 -> 3102201418001800126 | B27: =SA_1_ID -> 31022014180018001 | C27: ='SA-1'!$G$76 -> 26 | D27: Total_Copier | E27: ='SA-1'!$F$76 -> 1
A28: =B28&C28 -> 3102201418001800127 | B28: =SA_1_ID -> 31022014180018001 | C28: ='SA-1'!$L$76 -> 27 | D28: Usable_Copier | E28: ='SA-1'!$K$76 -> 1
A29: =B29&C29 -> 3102201418001800128 | B29: =SA_1_ID -> 31022014180018001 | C29: ='SA-1'!$G$78 -> 28 | D29: Total_Fan | E29: ='SA-1'!$F$78 -> 3
A30: =B30&C30 -> 3102201418001800129 | B30: =SA_1_ID -> 31022014180018001 | C30: ='SA-1'!$L$78 -> 29 | D30: Usable_Fan | E30: ='SA-1'!$K$78 -> 3
A31: =B31&C31 -> 3102201418001800130 | B31: =SA_1_ID -> 31022014180018001 | C31: ='SA-1'!$G$80 -> 30 | D31: Cupboard | E31: ='SA-1'!$F$80 -> 15
A33: =LEN($A$31) -> 19

Sheet Clean_SA_1 LibraryInfo
A1: SA_1_ID | B1: SchoolLibrary_YN | C1: LibrarySeperate_YN | D1: NoOfBooksInLibrary | E1: Borrowable_YN
A2: =SA_1_ID -> 31022014180018001 | B2: 1 | C2: 0 | D2: ='SA-1'!D88 -> 500 | E2: 0
A5: =LEN($A$2) -> 17 | B5: =LEN($B$2) -> 1 | C5: =LEN($C$2) -> 1 | D5: =LEN($D$2) -> 3 | E5: =LEN($E$2) -> 1 | F5: =LEN($F$2) -> 0

Sheet Clean_SA_1 LabMediaElearn_Info
A1: SA_1_ID | B1: ScienceLab_YN | C1: LabTeaching_YN | D1: MediaPlatform_ID | E1: MediaPlatformUse_YN | F1: Elearning_YN | G1: ElearnUse_YN
A2: =SA_1_ID -> 31022014180018001 | B2: 1 | C2: 0 | D2: =Selected_SchoolMediaPlatform -> 1 | E2: 1 | F2: 0 | G2: 0
A5: =LEN($A$2) -> 17 | B5: =LEN($B$2) -> 1 | C5: =LEN($C$2) -> 1 | D5: =LEN($D$2) -> 1 | E5: =LEN($E$2) -> 1 | F5: =LEN($F$2) -> 1

Sheet Clean_31_Signed
A1: SA_1_ID | B1: SignedName_31 | C1: SignedPost_31 | D1: SignedDate_31
A2: =SA_1_ID -> 31022014180018001 | B2: =FormSignedName_31 -> ငွေဝင်း | C2: =FormPost_31 -> 7 | D2: =FormDate_31 -> 41768
A5: =LEN($A$2) -> 17 | B5: =LEN($B$2) -> 7 | C5: =LEN($C$2) -> 1 | D5: =LEN($D$2) -> 5 | E5: =LEN($E$2) -> 0 | F5: =LEN($F$2) -> 0

Sheet Clean_SA_2 _Head
A1: SA_2_ID | B1: School_AY_Info_ID | C1: AcdemicMonth
A2: ="32" & C2 & AcademicYear_ID& "" & TSIndex_SchoolID -> 32022014180018001 | B2: =CLEAN(SchoolAY_Info_ID) -> 30201411008018001 | C2: 02
A5: =LEN($A$2) -> 17 | B5: =LEN($B$2) -> 17 | C5: =LEN($C$2) -> 2 | D5: =LEN($D$2) -> 0 | E5: =LEN($E$2) -> 0 | F5: =LEN($F$2) -> 0

Sheet Clean_SA_2_SchoolBuildingsInfo
A1: id | B1: SchBuilding_ID | C1: SA_2_ID | D1: Buliding_No | E1: Storeys | F1: Total_Classroom_Area (Sqft) | G1: Total_Sections | H1: Classroom_Permanent | I1: Classroom_Temporary | J1: Office_Room | K1: Other_Room | L1: YearBuilt(StartEnd) | M1: Wall_Type | N1: Wall_Condition | O1: Roof_Type | P1: Roof_Condition | Q1: Floor_Type | R1: Floor_Condition
A2: 1 | B2: =C2& A2 -> 320220141800180011 | C2: =SA_2_ID -> 32022014180018001 | D2: ='SA-2'!B21 -> 1 | E2: ='SA-2'!C21 -> 2 | F2: ='SA-2'!D21 -> 6040 | G2: ='SA-2'!E21 -> 7 | H2: ='SA-2'!F21 -> 7 | I2: ='SA-2'!G21 -> 0 | J2: ='SA-2'!H21 -> 1 | K2: ='SA-2'!I21 -> 0 | L2: ='SA-2'!J21 -> 2003 | M2: ='SA-2'!L21 -> 2 | N2: ='SA-2'!M21 -> 1 | O2: ='SA-2'!O21 -> 6 | P2: ='SA-2'!P21 -> 1 | Q2: ='SA-2'!R21 -> 1 | R2: ='SA-2'!S21 -> 1
A3: 2 | B3: =C3& A3 -> 320220141800180012 | C3: =SA_2_ID -> 32022014180018001 | D3: ='SA-2'!B22 -> 2 | E3: ='SA-2'!C22 -> 1 | F3: ='SA-2'!D22 -> 2160 | G3: ='SA-2'!E22 -> 3 | H3: ='SA-2'!F22 -> 3 | I3: ='SA-2'!G22 -> 0 | J3: ='SA-2'!H22 -> 0 | K3: ='SA-2'!I22 -> 0 | L3: ='SA-2'!J22 -> 1991 | M3: ='SA-2'!L22 -> 2 | N3: ='SA-2'!M22 -> 1 | O3: ='SA-2'!O22 -> 6 | P3: ='SA-2'!P22 -> 3 | Q3: ='SA-2'!R22 -> 1 | R3: ='SA-2'!S22 -> 1
A4: 3 | B4: =C4& A4 -> 320220141800180013 | C4: =SA_2_ID -> 32022014180018001 | D4: ='SA-2'!B23 -> 3 | E4: ='SA-2'!C23 -> 2 | F4: ='SA-2'!D23 -> 5040 | G4: ='SA-2'!E23 -> 7 | H4: ='SA-2'!F23 -> 7 | I4: ='SA-2'!G23 -> 0 | J4: ='SA-2'!H23 -> 0 | K4: ='SA-2'!I23 -> 3 | L4: ='SA-2'!J23 -> 1983 | M4: ='SA-2'!L23 -> 2 | N4: ='SA-2'!M23 -> 1 | O4: ='SA-2'!O23 -> 6 | P4: ='SA-2'!P23 -> 3 | Q4: ='SA-2'!R23 -> 1 | R4: ='SA-2'!S23 -> 1
A5: 4 | B5: =C5& A5 -> 320220141800180014 | C5: =SA_2_ID -> 32022014180018001 | D5: ='SA-2'!B24 -> 4 | E5: ='SA-2'!C24 -> 2 | F5: ='SA-2'!D24 -> 720 | G5: ='SA-2'!E24 -> 0 | H5: ='SA-2'!F24 -> 0 | I5: ='SA-2'!G24 -> 0 | J5: ='SA-2'!H24 -> 0 | K5: ='SA-2'!I24 -> 1 | L5: ='SA-2'!J24 -> 1993 | M5: ='SA-2'!L24 -> 2 | N5: ='SA-2'!M24 -> 4 | O5: ='SA-2'!O24 -> 6 | P5: ='SA-2'!P24 -> 4 | Q5: ='SA-2'!R24 -> 3 | R5: ='SA-2'!S24 -> 4
A6: 5 | B6: =C6& A6 -> 320220141800180015 | C6: =SA_2_ID -> 32022014180018001 | D6: ='SA-2'!B25 -> 5 | E6: ='SA-2'!C25 -> 0 | F6: ='SA-2'!D25 -> 0 | G6: ='SA-2'!E25 -> 0 | H6: ='SA-2'!F25 -> 0 | I6: ='SA-2'!G25 -> 0 | J6: ='SA-2'!H25 -> 0 | K6: ='SA-2'!I25 -> 0 | L6: ='SA-2'!J25 -> 0 | M6: ='SA-2'!L25 -> 0 | N6: ='SA-2'!M25 -> 0 | O6: ='SA-2'!O25 -> 0 | P6: ='SA-2'!P25 -> 0 | Q6: ='SA-2'!R25 -> 0 | R6: ='SA-2'!S25 -> 0
A7: 6 | B7: =C7& A7 -> 320220141800180016 | C7: =SA_2_ID -> 32022014180018001 | D7: ='SA-2'!B26 -> 6 | E7: ='SA-2'!C26 -> 0 | F7: ='SA-2'!D26 -> 0 | G7: ='SA-2'!E26 -> 0 | H7: ='SA-2'!F26 -> 0 | I7: ='SA-2'!G26 -> 0 | J7: ='SA-2'!H26 -> 0 | K7: ='SA-2'!I26 -> 0 | L7: ='SA-2'!J26 -> 0 | M7: ='SA-2'!L26 -> 0 | N7: ='SA-2'!M26 -> 0 | O7: ='SA-2'!O26 -> 0 | P7: ='SA-2'!P26 -> 0 | Q7: ='SA-2'!R26 -> 0 | R7: ='SA-2'!S26 -> 0
A8: 7 | B8: =C8& A8 -> 320220141800180017 | C8: =SA_2_ID -> 32022014180018001 | D8: ='SA-2'!B27 -> 7 | E8: ='SA-2'!C27 -> 0 | F8: ='SA-2'!D27 -> 0 | G8: ='SA-2'!E27 -> 0 | H8: ='SA-2'!F27 -> 0 | I8: ='SA-2'!G27 -> 0 | J8: ='SA-2'!H27 -> 0 | K8: ='SA-2'!I27 -> 0 | L8: ='SA-2'!J27 -> 0 | M8: ='SA-2'!L27 -> 0 | N8: ='SA-2'!M27 -> 0 | O8: ='SA-2'!O27 -> 0 | P8: ='SA-2'!P27 -> 0 | Q8: ='SA-2'!R27 -> 0 | R8: ='SA-2'!S27 -> 0
A11: =LEN($A$2) -> 1 | B11: =LEN($B$2) -> 18 | C11: =LEN($C$2) -> 17 | D11: =LEN($D$2) -> 1 | E11: =LEN($E$2) -> 1 | F11: =LEN($F$2) -> 4

Sheet Clean_SA_2_PlaygroundFence
A1: SA_2_ID | B1: SchoolPlayground_YN | C1: Playground_Length | D1: Playground_Width | E1: Playground_Area | F1: With_Root_Percent | G1: SchoolSecureFence_SA2_YN
A2: =SA_2_ID -> 32022014180018001 | B2: ='SA-2'!$J$61 -> 1 | C2: ='SA-2'!$F$63 -> 140 | D2: ='SA-2'!$J$63 -> 70 | E2: ='SA-2'!$O$63 -> 0.22497615 | F2: ='SA-2'!$T$63 -> 0 | G2: ='SA-2'!$C$57 -> 1
A5: =LEN($A$2) -> 17 | B5: =LEN($B$2) -> 1 | C5: =LEN($C$2) -> 3 | D5: =LEN($D$2) -> 2 | E5: =LEN($E$2) -> 10 | F5: =LEN($F$2) -> 1

Sheet SA-2
C2: The Republic of the Union of Myanmar
C3: Ministry of Education
C4: Township Education Management Information System
C5: SCHOOL INFRASTRUCTURE (END OF FEBRUARY)
G7: Academic Year | H7: =AcademicYear_Name -> 2013-2014 | P7: Feb
E9: Township | F9: =Township_Name_EN -> Paung | L9: State / Region | M9: =StateRegion_Name_EN -> Mon
E10: TS_Myanmar | F10: =Township_Name_MM -> ပေါင် | L10: SR_Myanmar | M10: =StateRegion_Name_MM -> မွန်ပြည်နယ်
D12: School ID | E12: =CLEAN(Selected_School_ID) -> 11008018001 | J12: School Name | K12: =CLEAN(Selected_School_Name) -> အ.ထ.က ရင်ငြိမ်
A15: 1 | B15: Buildings | H15: No of Buildings | I15: =COUNTA(C21:C50) -> 4
L17: Wall | O17: Roof | R17: Floor
B18: Build No. | C18: # Storey | D18: Total classroom area (Sq-ft) | E18: # Sections | F18: No of classrooms | H18: Office | I18: Other | J18: Year Built (start/end) | L18: Type | M18: Condi-tion | O18: Type | P18: Condi-tion | R18: Type | S18: Condi-tion
F19: Permanent | G19: Temporary
B20: No | C20: 1 | D20: 2 | E20: 3 | F20: 4 | G20: 5 | H20: 6 | I20: 7 | J20: 8 | K20: 0 | L20: 9 | M20: 10 | N20: 02 | O20: 11 | P20: 12 | Q20: 03 | R20: 13 | S20: 14 | T20: 04
B21: =IFERROR(B20+1,1) -> 1 | C21: 2 | D21: 6040 | E21: 7 | F21: 7 | H21: 1 | J21: 2003 | L21: 2 | M21: 1 | O21: 6 | P21: 1 | R21: 1 | S21: 1
B22: =IFERROR(B21+1,1) -> 2 | C22: 1 | D22: 2160 | E22: 3 | F22: 3 | J22: 1991 | L22: 2 | M22: 1 | O22: 6 | P22: 3 | R22: 1 | S22: 1
B23: =IFERROR(B22+1,1) -> 3 | C23: 2 | D23: 5040 | E23: 7 | F23: 7 | I23: 3 | J23: 1983 | L23: 2 | M23: 1 | O23: 6 | P23: 3 | R23: 1 | S23: 1
B24: =IFERROR(B23+1,1) -> 4 | C24: 2 | D24: 720 | I24: 1 | J24: 1993 | L24: 2 | M24: 4 | O24: 6 | P24: 4 | R24: 3 | S24: 4
B25: =IFERROR(B24+1,1) -> 5
B26: =IFERROR(B25+1,1) -> 6
B27: =IFERROR(B26+1,1) -> 7
B28: =IFERROR(B27+1,1) -> 8
B29: =IFERROR(B28+1,1) -> 9
B30: =IFERROR(B29+1,1) -> 10
B31: =IFERROR(B30+1,1) -> 11
B32: =IFERROR(B31+1,1) -> 12
B33: =IFERROR(B32+1,1) -> 13
B34: =IFERROR(B33+1,1) -> 14
B35: =IFERROR(B34+1,1) -> 15
B36: =IFERROR(B35+1,1) -> 16
... B50: =IFERROR(B49+1,1) -> 30
B51: Type | D51: 1=Concrete 2=Bricks 3=Stone 5=Bamboo 6=Zinc sheet 7=None 8=Part of Them 9=Other 10=Thet-Kal
B52: Condition | D52: 1=Good | F52: 2=Fair | G52: 3=Bad | I52: 4=Very bad
A55: 2 | D55: School secure fence Exist
E56: Yes | F56: 1
C57: =$F$56 -> 1 | E57: No
A60: 3 | B60: School Playground | K60: School Playground Exist | L60: Yes | M60: 1
J61: =$M$60 -> 1 | L61: No
B63: If yes, playground area | E63: Length | F63: 140 | G63: feet | I63: Width | J63: 70 | K63: feet | L63: OR | N63: In Area | O63: =PRODUCT( PRODUCT(F63,J63),0.00002295675) -> 0.22497615 | P63: Acre | S63: With Roof % | T63: 0
A66: 4 | B66: Water and Sanitation
C68: No of Latrines | E68: Boys | F68: Girls | G68: Both
C69: Total | E69: 10 | F69: 17
C70: Needed to Repaired
C72: Main source | E72: Piped | F72: Tube well | G72: Well | H72: Hand Pump | I72: Rain | J72: River | K72: Pond | L72: Bottled/ Tank water | M72: No | O72: Safe to drink?
E73: 1 | I73: 1 | L73: 1 | O73: Yes | P73: 1
O74: No | Q74: =$P$73 -> 1
C76: Distance from school to water source | E76: In school compound | G76: <100 ft | I76: 100-200 ft | K76: > 200 ft | M76: =SUM(PRODUCT(1,SA2_P4_WaterSourceSchCom),PRODUCT(2,SA2_P4_WaterSourceL100),PRODUCT(3,SA2_P4_WaterSourceB100N200),PRODUCT(4,SA2_P4_WaterSourceG200)) -> 2
E78: 0 | G78: 1 | I78: 0 | K78: 0
E80: Enough to drink for whole year | F80: Yes | G80: 1 | L80: Enough for other use
C81: =$G$80 -> 1 | F81: No | K81: Yes | L81: 1
I82: =$L$81 -> 1 | K82: No
A85: 5 | B85: Electricity | D85: =SUM(PRODUCT(1,SA2_P5_ElectricNo),PRODUCT(2,SA2_P5_ElectricL2),PRODUCT(3,SA2_P5_ElectricB2N4),PRODUCT(4,SA2_P5_ElectricB4N6), PRODUCT(5,SA2_P5_ElectricB6N8),PRODUCT(6,SA2_P5_ElectricB8N10),PRODUCT(7,SA2_P5_ElectricB10N12),PRODUCT(8,SA2_P5_ElectricB12N14)) -> 8
D87: How many | E87: hours per day (7 am to 9 pm) | J87: do you have electricity in your school on average?
D89: No electricity | E89: 0 | H89: <2 hours | I89: 0 | L89: 2-4 hours | M89: 0 | R89: 4-6 hours | S89: 0
D91: 6-8 hours | E91: 0 | H91: 8-10 hours | I91: 0 | L91: 10-12 hours | M91: 0 | R91: 12-14 hours | S91: 1
P96: Paper Form Signed By
P97: Name | V97: =FormSignedName_31 -> ငွေဝင်း
P98: Office Post | V98: 7
P99: Signed Date (DD/MM/YYYY) | V99: 41768

Sheet Clean_SA_2_Sanitation
A1: SA_2_ID | B1: TotalToilet_Gent | C1: TotalToilet_Lady | D1: TotalToilet_Unisex | E1: FunctionalToilet_Gent | F1: FunctionalToilet_Lady | G1: FunctionalToilet_Unisex
A2: =SA_2_ID -> 32022014180018001 | B2: ='SA-2'!$E$69 -> 10 | C2: ='SA-2'!$F$69 -> 17 | D2: ='SA-2'!$G$69 -> 0 | E2: ='SA-2'!$E$70 -> 0 | F2: ='SA-2'!$F$70 -> 0 | G2: ='SA-2'!$G$70 -> 0
A5: =LEN($A$2) -> 17 | B5: =LEN($B$2) -> 2 | C5: =LEN($C$2) -> 2 | D5: =LEN($D$2) -> 1 | E5: =LEN($E$2) -> 1 | F5: =LEN($F$2) -> 1

Sheet Clean_SA_2_Water
A1: SA_2_ID | B1: WaterSource_Piped | C1: WaterSource_Tube well | D1: WaterSource_Well | E1: WaterSource_Hand Pump | F1: WaterSource_Rain | G1: WaterSource_River | H1: WaterSource_Pond | I1: WaterSource_Bottled/ Tank water | J1: WaterSource_No | K1: NearestDistanceToWaterSource | L1: SafeToDrink_YN | M1: EnoughToDrinkWholeYear_YN | N1: EnoughforOtherUse_YN
A2: =SA_2_ID -> 32022014180018001 | B2: ='SA-2'!$E$73 -> 1 | C2: ='SA-2'!$F$73 -> 0 | D2: ='SA-2'!$G$73 -> 0 | E2: ='SA-2'!$H$73 -> 0 | F2: ='SA-2'!$I$73 -> 1 | G2: ='SA-2'!$J$73 -> 0 | H2: ='SA-2'!$K$73 -> 0 | I2: ='SA-2'!$L$73 -> 1 | J2: ='SA-2'!$M$73 -> 0 | K2: =WaterSourceDistance -> 2 | L2: ='SA-2'!$Q$74 -> 1 | M2: ='SA-2'!$C$81 -> 1 | N2: ='SA-2'!$I$82 -> 1
A5: =LEN($A$2) -> 17 | B5: =LEN($B$2) -> 1 | C5: =LEN($C$2) -> 1 | D5: =LEN($D$2) -> 1 | E5: =LEN($E$2) -> 1 | F5: =LEN($F$2) -> 1

Sheet Clean_SA_2_Electricity
A1: SA_2_ID | B1: Electricity_Availability_Desc | C1: Electricity_Availability_Code
A2: =SA_2_ID -> 32022014180018001 | B2: ='SA-2'!$E$87 -> hours per day (7 am to 9 pm) | C2: =Electricity_Availability -> 8
A5: =LEN($A$2) -> 17 | B5: =LEN($B$2) -> 28 | C5: =LEN($C$2) -> 1 | D5: =LEN($D$2) -> 0 | E5: =LEN($E$2) -> 0 | F5: =LEN($F$2) -> 0

Sheet Clean_32_Signed
A1: SA_2_ID | B1: SignedName_31 | C1: SignedPost_31 | D1: SignedDate_31
A2: =SA_2_ID -> 32022014180018001 | B2: =CLEAN('SA-2'!V97) -> ငွေဝင်း | C2: =FormPost_32 -> 7 | D2: ='SA-2'!V99 -> 41768
A5: =LEN($A$2) -> 17 | B5: =LEN($B$2) -> 7 | C5: =LEN($C$2) -> 1 | D5: =LEN($D$2) -> 5 | E5: =LEN($E$2) -> 0 | F5: =LEN($F$2) -> 0

Sheet SA-3
C2: The Republic of the Union of Myanmar
C3: Ministry of Education
C4: Township Education Management Information System
C5: SCHOOL CATCHMENT AREA (FOR ALL SCHOOLS WITH PRIMARY LEVEL CLASSES) (END OF MAY) | X5: Paper Form Signed By
F7: Academic Year | G7: =AcademicYear_Name -> 2013-2014 | O7: =AcademicYear_Name -> 2013-2014 | X7: Name | Y7: =FormSignedName_31 -> ငွေဝင်း
D9: Township | E9: =Township_Name_EN -> Paung | F9: State / Region | H9: State / Region | I9: =StateRegion_Name_EN -> Mon | N9: State / Region | O9: =StateRegion_Name_EN -> Mon | X9: Office Post | Y9: 7
D10: TS_Myanmar | E10: =Township_Name_MM -> ပေါင် | F10: SR_Myanmar | H10: SR_Myanmar | I10: =StateRegion_Name_MM -> မွန်ပြည်နယ် | N10: SR_Myanmar | O10: =StateRegion_Name_MM -> မွန်ပြည်နယ် | X10: Signed Date (DD/MM/YYYY) | Y10: 41768
D12: School ID | E12: =CLEAN(Selected_School_ID) -> 11008018001 | F12: School Name | O12: =CLEAN(Selected_School_Name) -> အ.ထ.က ရင်ငြိမ်
D14: Ward / Village | E14: Ward / Village | F14: Ward / Village | G14: Children Population | O14: Children Population | Q14: Ways to school from village
Q15: 1 | R15: 2 | S15: 3 | T15: 4 | U15: Distance in miles
B16: Sr | C16: W/V | D16: English Name | E16: Myanmar Name | F16: ID | G16: Boy1 | H16: Girl1 | I16: Boy2 | J16: Girl2 | K16: Boy3 | L16: Girl3 | M16: Boy4 | N16: Girl4 | O16: Boy | P16: Girl | Q16: Lane | R16: Road | S16: Water way | T16: No street | U16: from school to village
B17: =IFERROR(B16+1,1) -> 1 | C17: V | D17: Yin Nyein (North) - 195703 | E17: =CLEAN(IFERROR(IF(tblSA3[[#This Row],[W/V]]="W",INDEX(Ward_Names_TS!$C$2:$F$87,MATCH(CLEAN($D17),Ward_Name_Sort_TS,0),3),INDEX(Village_Names_TS!$C$2:$F$1183,MATCH(CLEAN($D17),Village_Name_Sort_TS,0),3)),$A$1)) -> ရင်းငြိမ် (မြောက်) | F17: =CLEAN(IFERROR(IF(tblSA3[[#This Row],[W/V]]="W",INDEX(Ward_Names_TS!$C$2:$F$87,MATCH(CLEAN($D17),Ward_Name_Sort_TS,0),1),INDEX(Village_Names_TS!$C$2:$F$1183,MATCH(CLEAN($D17),Village_Name_Sort_TS,0),1)),$A$1)) -> 195703 | O17: 480 | R17: 1
B18: =IFERROR(B17+1,1) -> 2 | C18: V | D18: Yin Nyein (South) - 195708 | E18: =CLEAN(IFERROR(IF(tblSA3[[#This Row],[W/V]]="W",INDEX(Ward_Names_TS!$C$2:$F$87,MATCH(CLEAN($D18),Ward_Name_Sort_TS,0),3),INDEX(Village_Names_TS!$C$2:$F$1183,MATCH(CLEAN($D18),Village_Name_Sort_TS,0),3)),$A$1)) -> ရင်းငြိမ် (တောင်) | F18: =CLEAN(IFERROR(IF(tblSA3[[#This Row],[W/V]]="W",INDEX(Ward_Names_TS!$C$2:$F$87,MATCH(CLEAN($D18),Ward_Name_Sort_TS,0),1),INDEX(Village_Names_TS!$C$2:$F$1183,MATCH(CLEAN($D18),Village_Name_Sort_TS,0),1)),$A$1)) -> 195708 | O18: 326 | R18: 1 | U18: 1
B19: =IFERROR(B18+1,1) -> 3 | C19: V | D19: Ywar Tan Shey - 195711 | E19: =CLEAN(IFERROR(IF(tblSA3[[#This Row],[W/V]]="W",INDEX(Ward_Names_TS!$C$2:$F$87,MATCH(CLEAN($D19),Ward_Name_Sort_TS,0),3),INDEX(Village_Names_TS!$C$2:$F$1183,MATCH(CLEAN($D19),Village_Name_Sort_TS,0),3)),$A$1)) -> ရွာတန်းရှည် | F19: =CLEAN(IFERROR(IF(tblSA3[[#This Row],[W/V]]="W",INDEX(Ward_Names_TS!$C$2:$F$87,MATCH(CLEAN($D19),Ward_Name_Sort_TS,0),1),INDEX(Village_Names_TS!$C$2:$F$1183,MATCH(CLEAN($D19),Village_Name_Sort_TS,0),1)),$A$1)) -> 195711 | O19: 115 | R19: 1 | U19: 2
B20: =IFERROR(B19+1,1) -> 4 | C20: V | D20: Tha Byu Chaung - 195704 | E20: =CLEAN(IFERROR(IF(tblSA3[[#This Row],[W/V]]="W",INDEX(Ward_Names_TS!$C$2:$F$87,MATCH(CLEAN($D20),Ward_Name_Sort_TS,0),3),INDEX(Village_Names_TS!$C$2:$F$1183,MATCH(CLEAN($D20),Village_Name_Sort_TS,0),3)),$A$1)) -> သဗြုချောင် | F20: =CLEAN(IFERROR(IF(tblSA3[[#This Row],[W/V]]="W",INDEX(Ward_Names_TS!$C$2:$F$87,MATCH(CLEAN($D20),Ward_Name_Sort_TS,0),1),INDEX(Village_Names_TS!$C$2:$F$1183,MATCH(CLEAN($D20),Village_Name_Sort_TS,0),1)),$A$1)) -> 195704 | O20: 75 | R20: 1 | U20: 3
B21: =IFERROR(B20+1,1) -> 5 | E21: =CLEAN(IFERROR(IF(tblSA3[[#This Row],[W/V]]="W",INDEX(Ward_Names_TS!$C$2:$F$87,MATCH(CLEAN($D21),Ward_Name_Sort_TS,0),3),INDEX(Village_Names_TS!$C$2:$F$1183,MATCH(CLEAN($D21),Village_Name_Sort_TS,0),3)),$A$1)) | F21: =CLEAN(IFERROR(IF(tblSA3[[#This Row],[W/V]]="W",INDEX(Ward_Names_TS!$C$2:$F$87,MATCH(CLEAN($D21),Ward_Name_Sort_TS,0),1),INDEX(Village_Names_TS!$C$2:$F$1183,MATCH(CLEAN($D21),Village_Name_Sort_TS,0),1)),$A$1))
B22: =IFERROR(B21+1,1) -> 6 | E22: =CLEAN(IFERROR(IF(tblSA3[[#This Row],[W/V]]="W",INDEX(Ward_Names_TS!$C$2:$F$87,MATCH(CLEAN($D22),Ward_Name_Sort_TS,0),3),INDEX(Village_Names_TS!$C$2:$F$1183,MATCH(CLEAN($D22),Village_Name_Sort_TS,0),3)),$A$1)) | F22: =CLEAN(IFERROR(IF(tblSA3[[#This Row],[W/V]]="W",INDEX(Ward_Names_TS!$C$2:$F$87,MATCH(CLEAN($D22),Ward_Name_Sort_TS,0),1),INDEX(Village_Names_TS!$C$2:$F$1183,MATCH(CLEAN($D22),Village_Name_Sort_TS,0),1)),$A$1))
B23: =IFERROR(B22+1,1) -> 7 | E23: =CLEAN(IFERROR(IF(tblSA3[[#This Row],[W/V]]="W",INDEX(Ward_Names_TS!$C$2:$F$87,MATCH(CLEAN($D23),Ward_Name_Sort_TS,0),3),INDEX(Village_Names_TS!$C$2:$F$1183,MATCH(CLEAN($D23),Village_Name_Sort_TS,0),3)),$A$1)) | F23: =CLEAN(IFERROR(IF(tblSA3[[#This Row],[W/V]]="W",INDEX(Ward_Names_TS!$C$2:$F$87,MATCH(CLEAN($D23),Ward_Name_Sort_TS,0),1),INDEX(Village_Names_TS!$C$2:$F$1183,MATCH(CLEAN($D23),Village_Name_Sort_TS,0),1)),$A$1))
B24: =IFERROR(B23+1,1) -> 8 | E24: =CLEAN(IFERROR(IF(tblSA3[[#This Row],[W/V]]="W",INDEX(Ward_Names_TS!$C$2:$F$87,MATCH(CLEAN($D24),Ward_Name_Sort_TS,0),3),INDEX(Village_Names_TS!$C$2:$F$1183,MATCH(CLEAN($D24),Village_Name_Sort_TS,0),3)),$A$1)) | F24: =CLEAN(IFERROR(IF(tblSA3[[#This Row],[W/V]]="W",INDEX(Ward_Names_TS!$C$2:$F$87,MATCH(CLEAN($D24),Ward_Name_Sort_TS,0),1),INDEX(Village_Names_TS!$C$2:$F$1183,MATCH(CLEAN($D24),Village_Name_Sort_TS,0),1)),$A$1))
B25: =IFERROR(B24+1,1) -> 9 | E25: =CLEAN(IFERROR(IF(tblSA3[[#This Row],[W/V]]="W",INDEX(Ward_Names_TS!$C$2:$F$87,MATCH(CLEAN($D25),Ward_Name_Sort_TS,0),3),INDEX(Village_Names_TS!$C$2:$F$1183,MATCH(CLEAN($D25),Village_Name_Sort_TS,0),3)),$A$1)) | F25: =CLEAN(IFERROR(IF(tblSA3[[#This Row],[W/V]]="W",INDEX(Ward_Names_TS!$C$2:$F$87,MATCH(CLEAN($D25),Ward_Name_Sort_TS,0),1),INDEX(Village_Names_TS!$C$2:$F$1183,MATCH(CLEAN($D25),Village_Name_Sort_TS,0),1)),$A$1))
B26: =IFERROR(B25+1,1) -> 10 | E26: =CLEAN(IFERROR(IF(tblSA3[[#This Row],[W/V]]="W",INDEX(Ward_Names_TS!$C$2:$F$87,MATCH(CLEAN($D26),Ward_Name_Sort_TS,0),3),INDEX(Village_Names_TS!$C$2:$F$1183,MATCH(CLEAN($D26),Village_Name_Sort_TS,0),3)),$A$1)) | F26: =CLEAN(IFERROR(IF(tblSA3[[#This Row],[W/V]]="W",INDEX(Ward_Names_TS!$C$2:$F$87,MATCH(CLEAN($D26),Ward_Name_Sort_TS,0),1),INDEX(Village_Names_TS!$C$2:$F$1183,MATCH(CLEAN($D26),Village_Name_Sort_TS,0),1)),$A$1))
B27: =IFERROR(B26+1,1) -> 11 | E27: =CLEAN(IFERROR(IF(tblSA3[[#This Row],[W/V]]="W",INDEX(Ward_Names_TS!$C$2:$F$87,MATCH(CLEAN($D27),Ward_Name_Sort_TS,0),3),INDEX(Village_Names_TS!$C$2:$F$1183,MATCH(CLEAN($D27),Village_Name_Sort_TS,0),3)),$A$1)) | F27: =CLEAN(IFERROR(IF(tblSA3[[#This Row],[W/V]]="W",INDEX(Ward_Names_TS!$C$2:$F$87,MATCH(CLEAN($D27),Ward_Name_Sort_TS,0),1),INDEX(Village_Names_TS!$C$2:$F$1183,MATCH(CLEAN($D27),Village_Name_Sort_TS,0),1)),$A$1))
B28: =IFERROR(B27+1,1) -> 12 | E28: =CLEAN(IFERROR(IF(tblSA3[[#This Row],[W/V]]="W",INDEX(Ward_Names_TS!$C$2:$F$87,MATCH(CLEAN($D28),Ward_Name_Sort_TS,0),3),INDEX(Village_Names_TS!$C$2:$F$1183,MATCH(CLEAN($D28),Village_Name_Sort_TS,0),3)),$A$1)) | F28: =CLEAN(IFERROR(IF(tblSA3[[#This Row],[W/V]]="W",INDEX(Ward_Names_TS!$C$2:$F$87,MATCH(CLEAN($D28),Ward_Name_Sort_TS,0),1),INDEX(Village_Names_TS!$C$2:$F$1183,MATCH(CLEAN($D28),Village_Name_Sort_TS,0),1)),$A$1))

Sheet Clean_SA_3 _Head
A1: SA_3_ID | B1: School_AY_Info_ID | C1: AcdemicMonth
A2: ="33" & C2 & AcademicYear_ID& "" & TSIndex_SchoolID -> 33052014180018001 | B2: =CLEAN(SchoolAY_Info_ID) -> 30201411008018001 | C2: 05
A5: =LEN($A$2) -> 17 | B5: =LEN($B$2) -> 17 | C5: =LEN($C$2) -> 2 | D5: =LEN($D$2) -> 0 | E5: =LEN($E$2) -> 0 | F5: =LEN($F$2) -> 0

Sheet Clean_SA_3 _SchoolCatchmentInfo
A1: id | B1: SA_3_Catchment_ID | C1: SA_3_ID | D1: Village_ID | E1: Boy1 | F1: Girl1 | G1: Boy2 | H1: Girl2 | I1: Boy3 | J1: Girl3 | K1: Boy4 | L1: Girl4 | M1: Lane_Way | N1: Road_Way | O1: Water_Way | P1: No_Street | Q1: Distance_School_Village(Miles)
A2: 1 | B2: =C2&A2 -> 330520141800180011 | C2: =SA_3_ID -> 33052014180018001 | D2: ='SA-3'!F17 -> 195703 | E2: ='SA-3'!G17 -> 0 | F2: ='SA-3'!H17 -> 0 | G2: ='SA-3'!I17 -> 0 | H2: ='SA-3'!J17 -> 0 | I2: ='SA-3'!K17 -> 0 | J2: ='SA-3'!L17 -> 0 | K2: ='SA-3'!M17 -> 0 | L2: ='SA-3'!N17 -> 0 | M2: ='SA-3'!Q17 -> 0 | N2: ='SA-3'!R17 -> 1 | O2: ='SA-3'!S17 -> 0 | P2: ='SA-3'!T17 -> 0 | Q2: ='SA-3'!U17 -> 0
A3: 2 | B3: =C3&A3 -> 330520141800180012 | C3: =SA_3_ID -> 33052014180018001 | D3: ='SA-3'!F18 -> 195708 | E3: ='SA-3'!G18 -> 0 | F3: ='SA-3'!H18 -> 0 | G3: ='SA-3'!I18 -> 0 | H3: ='SA-3'!J18 -> 0 | I3: ='SA-3'!K18 -> 0 | J3: ='SA-3'!L18 -> 0 | K3: ='SA-3'!M18 -> 0 | L3: ='SA-3'!N18 -> 0 | M3: ='SA-3'!Q18 -> 0 | N3: ='SA-3'!R18 -> 1 | O3: ='SA-3'!S18 -> 0 | P3: ='SA-3'!T18 -> 0 | Q3: ='SA-3'!U18 -> 1
A4: 3 | B4: =C4&A4 -> 330520141800180013 | C4: =SA_3_ID -> 33052014180018001 | D4: ='SA-3'!F19 -> 195711 | E4: ='SA-3'!G19 -> 0 | F4: ='SA-3'!H19 -> 0 | G4: ='SA-3'!I19 -> 0 | H4: ='SA-3'!J19 -> 0 | I4: ='SA-3'!K19 -> 0 | J4: ='SA-3'!L19 -> 0 | K4: ='SA-3'!M19 -> 0 | L4: ='SA-3'!N19 -> 0 | M4: ='SA-3'!Q19 -> 0 | N4: ='SA-3'!R19 -> 1 | O4: ='SA-3'!S19 -> 0 | P4: ='SA-3'!T19 -> 0 | Q4: ='SA-3'!U19 -> 2
A5: 4 | B5: =C5&A5 -> 330520141800180014 | C5: =SA_3_ID -> 33052014180018001 | D5: ='SA-3'!F20 -> 195704 | E5: ='SA-3'!G20 -> 0 | F5: ='SA-3'!H20 -> 0 | G5: ='SA-3'!I20 -> 0 | H5: ='SA-3'!J20 -> 0 | I5: ='SA-3'!K20 -> 0 | J5: ='SA-3'!L20 -> 0 | K5: ='SA-3'!M20 -> 0 | L5: ='SA-3'!N20 -> 0 | M5: ='SA-3'!Q20 -> 0 | N5: ='SA-3'!R20 -> 1 | O5: ='SA-3'!S20 -> 0 | P5: ='SA-3'!T20 -> 0 | Q5: ='SA-3'!U20 -> 3
A6: 5 | B6: =C6&A6 -> 330520141800180015 | C6: =SA_3_ID -> 33052014180018001 | D6: ='SA-3'!F21 | E6: ='SA-3'!G21 -> 0 | F6: ='SA-3'!H21 -> 0 | G6: ='SA-3'!I21 -> 0 | H6: ='SA-3'!J21 -> 0 | I6: ='SA-3'!K21 -> 0 | J6: ='SA-3'!L21 -> 0 | K6: ='SA-3'!M21 -> 0 | L6: ='SA-3'!N21 -> 0 | M6: ='SA-3'!Q21 -> 0 | N6: ='SA-3'!R21 -> 0 | O6: ='SA-3'!S21 -> 0 | P6: ='SA-3'!T21 -> 0 | Q6: ='SA-3'!U21 -> 0
A7: 6 | B7: =C7&A7 -> 330520141800180016 | C7: =SA_3_ID -> 33052014180018001 | D7: ='SA-3'!F22 | E7: ='SA-3'!G22 -> 0 | F7: ='SA-3'!H22 -> 0 | G7: ='SA-3'!I22 -> 0 | H7: ='SA-3'!J22 -> 0 | I7: ='SA-3'!K22 -> 0 | J7: ='SA-3'!L22 -> 0 | K7: ='SA-3'!M22 -> 0 | L7: ='SA-3'!N22 -> 0 | M7: ='SA-3'!Q22 -> 0 | N7: ='SA-3'!R22 -> 0 | O7: ='SA-3'!S22 -> 0 | P7: ='SA-3'!T22 -> 0 | Q7: ='SA-3'!U22 -> 0
A8: 7 | B8: =C8&A8 -> 330520141800180017 | C8: =SA_3_ID -> 33052014180018001 | D8: ='SA-3'!F23 | E8: ='SA-3'!G23 -> 0 | F8: ='SA-3'!H23 -> 0 | G8: ='SA-3'!I23 -> 0 | H8: ='SA-3'!J23 -> 0 | I8: ='SA-3'!K23 -> 0 | J8: ='SA-3'!L23 -> 0 | K8: ='SA-3'!M23 -> 0 | L8: ='SA-3'!N23 -> 0 | M8: ='SA-3'!Q23 -> 0 | N8: ='SA-3'!R23 -> 0 | O8: ='SA-3'!S23 -> 0 | P8: ='SA-3'!T23 -> 0 | Q8: ='SA-3'!U23 -> 0
A9: 8 | B9: =C9&A9 -> 330520141800180018 | C9: =SA_3_ID -> 33052014180018001 | D9: ='SA-3'!F24 | E9: ='SA-3'!G24 -> 0 | F9: ='SA-3'!H24 -> 0 | G9: ='SA-3'!I24 -> 0 | H9: ='SA-3'!J24 -> 0 | I9: ='SA-3'!K24 -> 0 | J9: ='SA-3'!L24 -> 0 | K9: ='SA-3'!M24 -> 0 | L9: ='SA-3'!N24 -> 0 | M9: ='SA-3'!Q24 -> 0 | N9: ='SA-3'!R24 -> 0 | O9: ='SA-3'!S24 -> 0 | P9: ='SA-3'!T24 -> 0 | Q9: ='SA-3'!U24 -> 0
A10: 9 | B10: =C10&A10 -> 330520141800180019 | C10: =SA_3_ID -> 33052014180018001 | D10: ='SA-3'!F25 | E10: ='SA-3'!G25 -> 0 | F10: ='SA-3'!H25 -> 0 | G10: ='SA-3'!I25 -> 0 | H10: ='SA-3'!J25 -> 0 | I10: ='SA-3'!K25 -> 0 | J10: ='SA-3'!L25 -> 0 | K10: ='SA-3'!M25 -> 0 | L10: ='SA-3'!N25 -> 0 | M10: ='SA-3'!Q25 -> 0 | N10: ='SA-3'!R25 -> 0 | O10: ='SA-3'!S25 -> 0 | P10: ='SA-3'!T25 -> 0 | Q10: ='SA-3'!U25 -> 0
A11: 10 | B11: =C11&A11 -> 3305201418001800110 | C11: =SA_3_ID -> 33052014180018001 | D11: ='SA-3'!F26 | E11: ='SA-3'!G26 -> 0 | F11: ='SA-3'!H26 -> 0 | G11: ='SA-3'!I26 -> 0 | H11: ='SA-3'!J26 -> 0 | I11: ='SA-3'!K26 -> 0 | J11: ='SA-3'!L26 -> 0 | K11: ='SA-3'!M26 -> 0 | L11: ='SA-3'!N26 -> 0 | M11: ='SA-3'!Q26 -> 0 | N11: ='SA-3'!R26 -> 0 | O11: ='SA-3'!S26 -> 0 | P11: ='SA-3'!T26 -> 0 | Q11: ='SA-3'!U26 -> 0
A12: 11 | B12: =C12&A12 -> 3305201418001800111 | C12: =SA_3_ID -> 33052014180018001 | D12: ='SA-3'!F27 | E12: ='SA-3'!G27 -> 0 | F12: ='SA-3'!H27 -> 0 | G12: ='SA-3'!I27 -> 0 | H12: ='SA-3'!J27 -> 0 | I12: ='SA-3'!K27 -> 0 | J12: ='SA-3'!L27 -> 0 | K12: ='SA-3'!M27 -> 0 | L12: ='SA-3'!N27 -> 0 | M12: ='SA-3'!Q27 -> 0 | N12: ='SA-3'!R27 -> 0 | O12: ='SA-3'!S27 -> 0 | P12: ='SA-3'!T27 -> 0 | Q12: ='SA-3'!U27 -> 0
A13: 12 | B13: =C13&A13 -> 3305201418001800112 | C13: =SA_3_ID -> 33052014180018001 | D13: ='SA-3'!F28 | E13: ='SA-3'!G28 -> 0 | F13: ='SA-3'!H28 -> 0 | G13: ='SA-3'!I28 -> 0 | H13: ='SA-3'!J28 -> 0 | I13: ='SA-3'!K28 -> 0 | J13: ='SA-3'!L28 -> 0 | K13: ='SA-3'!M28 -> 0 | L13: ='SA-3'!N28 -> 0 | M13: ='SA-3'!Q28 -> 0 | N13: ='SA-3'!R28 -> 0 | O13: ='SA-3'!S28 -> 0 | P13: ='SA-3'!T28 -> 0 | Q13: ='SA-3'!U28 -> 0
A16: =LEN($A$2) -> 1 | B16: =LEN($B$13) -> 19 | C16: =LEN($C$2) -> 17 | D16: =LEN($D$2) -> 6 | E16: =LEN($E$2) -> 1 | F16: =LEN($F$2) -> 1

Sheet Clean_33_Signed
A1: SA_3_ID | B1: SignedName_31 | C1: SignedPost_31 | D1: SignedDate_31
A2: =SA_3_ID -> 33052014180018001 | B2: =CLEAN('SA-3'!$Y$7) -> ငွေဝင်း | C2: =FormPost_33 -> 7 | D2: ='SA-3'!$Y$10 -> 41768
A5: =LEN($A$2) -> 17 | B5: =LEN($B$2) -> 7 | C5: =LEN($C$2) -> 1 | D5: =LEN($D$2) -> 5 | E5: =LEN($E$2) -> 0 | F5: =LEN($F$2) -> 0

Sheet SA-4
C2: The Republic of the Union of Myanmar
C3: Ministry of Education
C4: Township Education Management Information System
C5: FINANCIAL SOURCES (END OF MARCH) | J5: Paper Form Signed By
D7: Academic Year | E7: =AcademicYear_Name -> 2013-2014 | J7: Name | K7: =FormSignedName_31 -> ငွေဝင်း
D9: Township | E9: =Township_Name_EN -> Paung | F9: State / Region | G9: =StateRegion_Name_EN -> Mon | J9: Office Post | K9: =FormDate_31 -> 41768
D10: TS_Myanmar | E10: =Township_Name_MM -> ပေါင် | F10: SR_Myanmar | G10: =StateRegion_Name_MM -> မွန်ပြည်နယ် | J10: Signed Date (DD/MM/YYYY) | K10: 41768
D12: School ID | E12: =CLEAN(Selected_School_ID) -> 11008018001
D13: School Name | E13: =CLEAN(Selected_School_Name) -> အ.ထ.က ရင်ငြိမ်
E15: In Cash (Kyats) | F15: In Kind s(Kyats)
E16: 1 | F16: 2 | G16: 3
C17: Sr | D17: Sources | E17: Totlal | F17: Material | G17: Labour
C18: =IFERROR(C17+1,1) -> 1 | D18: Ministry of Education | E18: 2000000
C19: =IFERROR(C18+1,1) -> 2 | D19: Local Authorities
C20: =IFERROR(C19+1,1) -> 3 | D20: UN/International and local NGOs
C21: =IFERROR(C20+1,1) -> 4 | D21: Well Wishers | E21: 700000
C22: =IFERROR(C21+1,1) -> 5 | D22: Community | E22: 3500000
C23: =IFERROR(C22+1,1) -> 6 | D23: PTA
C24: =IFERROR(C23+1,1) -> 7 | D24: BOT
C25: =IFERROR(C24+1,1) -> 8 | D25: Others
C26: =IFERROR(C25+1,1) -> 9

Sheet BQ
B2: The Republic of the Union of Myanmar
B3: Ministry of Education
B4: Township Education Management Information System
B5: BUDGET PLAN (AUG,NOV,FEB) | M5: Paper Form Signed By
E7: Academic Year | F7: =AcademicYear_Name -> 2013-2014 | G7: Budget Plan | H7: ="Aug " & Academic_Start_Year -> Aug 2013 | M7: Name | N7: =FormSignedName_31 -> ငွေဝင်း
E9: Township | F9: =Township_Name_EN -> Paung | G9: State / Region | H9: =StateRegion_Name_EN -> Mon | M9: Office Post | N9: 7
E10: TS_Myanmar | F10: =Township_Name_MM -> ပေါင် | G10: SR_Myanmar | H10: =StateRegion_Name_MM -> မွန်ပြည်နယ် | M10: Signed Date (DD/MM/YYYY) | N10: 41768
E12: School ID | F12: =CLEAN(Selected_School_ID) -> 11008018001 | G12: School Name | H12: =CLEAN(Selected_School_Name) -> အ.ထ.က ရင်ငြိမ်
D15: Income
D17: Account Title | G17: Budgeted | H17: Up to this month Budget Received
C18: =IFERROR(C17+1,1) -> 1 | D18: =CLEAN(Form_Setup!$G$8) -> School Fees | H18: 748500
C19: =IFERROR(C18+1,1) -> 2 | D19: =CLEAN(Form_Setup!$G$9) | H19: 1050701
C20: =IFERROR(C19+1,1) -> 3 | D20: =CLEAN(Form_Setup!$G$10) | H20: 1799201
C21: =IFERROR(C20+1,1) -> 4 | D21: =CLEAN(Form_Setup!$G$11)
C22: =IFERROR(C21+1,1) -> 5 | D22: =CLEAN(Form_Setup!$G$11)
D23: Total Income | G23: =SUM(G18:G21) -> 0 | H23: =SUM(H18:H21) -> 3598402
D26: Expenditure
D28: Ordinary
F29: Item | G29: Budgeted Amount | H29: Expenditure Amount
D30: Ordinary | E30: 0101
E31: 0102
E32: 0103
E33: 0104
E34: Item 01 Total | G34: =SUM(G30:G33) -> 0 | H34: =SUM(H30:H33) -> 0
E35: 0201
E36: 0202
E37: 0203
E38: 0204
E39: Item 02 Total | G39: =SUM(G35:G38) -> 0 | H39: =SUM(H35:H38) -> 0
E40: 0301 | H40: 260000
E41: 0302
E42: 0303 | H42: 110000
E43: 0304 | H43: 120000
E44: 0305 | H44: 712500
E45: 0306
E46: 0307
E47: 0308
E48: 0309 | H48: 187575
E49: 0310
E50: 0311
E51: 0312
E52: 0313 | H52: 182500
E53: 0314 | H53: 62500
E54: 0315
E55: 0316
E56: 0317
E57: 0318
E58: 0319
E59: 0320
E60: 0321
E61: 0322
E62: 0323
E63: 0324
E64: 0325 | H64: 220000
E65: 0326 | H65: 99000
E66: 0327
E67: 0328
E68: 0329
E69: 0330
E70: Item 03 Total | G70: =SUM(G40:G69) -> 0 | H70: =SUM(H40:H69) -> 1954075
E71: 0401 | H71: 65000
E72: 0402
E73: 0403
E74: 0404
E75: 0405
E76: 0406
E77: 0407
E78: 0408
E79: 0409
E80: 0410
E81: Item 04 Total | H81: =SUM(H71:H80) -> 65000
E82: 0501
E83: 0502
E84: 0503
E85: 0504
E86: 0505
E87: 0506
E88: 0507
E89: 0508
E90: 0509
E91: 0510
E92: 0511
E93: 0512
E94: Item 05 Total | G94: =SUM(G82:G93) -> 0 | H94: =SUM(H82:H93) -> 0
E95: 0601
E96: 0602
E97: 0606
E98: 0604
E99: Item 06 Total | G99: =SUM(G95:G98) -> 0 | H99: =SUM(H95:H98) -> 0
E100: 0701
E101: 0702
E102: 0707
E103: 0704
E104: Item 07 Total | G104: =SUM(G100:G103) -> 0 | H104: =SUM(H100:H103) -> 0
E105: Ordinary Total | G105: =SUM(G34,G39,G70,G81,G94) -> 0 | H105: =SUM(H34,H39,H70,H81,H94) -> 2019075
D107: Lump Sum
D108: Lump sum | E108: Building | F108: (၄၀ X ၃၀)ပေ(၁)ထပ်
F109: (၄၀ X ၃၀)ပေ(၂)ထပ်
F110: (၆၀ X ၃၀)ပေ(၁)ထပ်
F111: (၆၀ X ၃၀)ပေ(၂)ထပ်
...

Sheet TQ_Jul
C2: The Republic of the Union of Myanmar
C3: Ministry of Education
C4: Township Education Management Information System
C5: TEACHER ATTENDANCE (FEB) | U5: Paper Form Signed By
G7: Academic Year | H7: =AcademicYear_Name -> 2013-2014 | N7: Attendance Period | O7: ="Jul " & Academic_Start_Year -> Jul 2013 | U7: Name | V7: =FormSignedName_31 -> ငွေဝင်း
G9: Township | H9: =Township_Name_EN -> Paung | N9: State / Region | O9: =StateRegion_Name_EN -> Mon | U9: Office Post | V9: 7
G10: TS_Myanmar | H10: =Township_Name_MM -> ပေါင် | N10: SR_Myanmar | O10: =StateRegion_Name_MM -> မွန်ပြည်နယ် | U10: Signed Date (DD/MM/YYYY) | V10: 41768
E12: School ID | F12: =CLEAN(Selected_School_ID) -> 11008018001 | K12: School Name | L12: =CLEAN(Selected_School_Name) -> အ.ထ.က ရင်ငြိမ်
C16: School open days for each period (Dec-Feb) | K16: 63
H18: Teacher ID | M18: Days of absence for teaching | R18: Total teacher attendance for each period
M19: 1 | N19: 2 | O19: 3 | Q19: 4 | R19: 5
C20: Sr. | D20: State ID | E20: State Name | F20: TS Symbol | G20: TS ID | H20: ID Type | I20: ID | J20: NRC/Passport No | K20: Teacher NRC ID | L20: Teacher ID | M20: Other duty | N20: Certified leave | O20: Uncertified leave | P20: Without Pay | Q20: Total Leave | R20: (June-Aug/ Sept-Nov/Dec-Aug)
A21: =IF(AND(NOT($G21=""),COUNTIF(TearcherID_Feb,$G21)>1),TRUE,FALSE) | C21: =IFERROR(C20+1,1) -> 1 | D21: 10 | E21: =CLEAN(IFERROR(INDEX(NRCState_List,MATCH(tblTQ_Jul[[#This Row],[State ID]],NRCState_ID,0),2),"")) -> Mon | F21: ပမန | G21: =CLEAN(IFERROR(INDEX(MyanmarLetter_List,MATCH(LEFT(tblTQ_Jul[[#This Row],[TS Symbol]],1),MyanmarLetter_MM,0),1),""))&CLEAN(IFERROR(INDEX(MyanmarLetter_List,MATCH(MID(tblTQ_Jul[[#This Row],[TS Symbol]],2,1),MyanmarLetter_MM,0),1),""))&CLEAN(IFERROR(INDEX(MyanmarLetter_List,MATCH(RIGHT(tblTQ_Jul[[#This Row],[TS Symbol]],1),MyanmarLetter_MM,0),1),"")) -> 222621 | H21: n | I21: =CLEAN(IFERROR(INDEX(NRCType_List,MATCH(tblTQ_Jul[[#This Row],[ID Type]],NRCType_Code,0),1),"")) -> 1 | J21: 030552 | K21: =tblTQ_Jul[[#This Row],[State ID]] & "/" & tblTQ_Jul[[#This Row],[TS Symbol]] &CLEAN(IFERROR( " (" & INDEX(NRCType_List,MATCH($H21,NRCType_Code,0),4)& ") ","")) & tblTQ_Jul[[#This Row],[NRC/Passport No]] -> 10/ပမန (နိုင်) 030552 | L21: =tblTQ_Jul[[#This Row],[State ID]]&tblTQ_Jul[[#This Row],[TS ID]]&tblTQ_Jul[[#This Row],[ID]]&tblTQ_Jul[[#This Row],[NRC/Passport No]] -> 102226211030552 | N21: 1 | Q21: =SUM($M21:$P21) -> 1 | R21: =SchoolOpenDays_Feb-tblTQ_Jul[[#This Row],[Total Leave]] -> 62
C22: =IFERROR(C21+1,1) -> 2 | D22: 10 | E22: =CLEAN(IFERROR(INDEX(NRCState_List,MATCH(tblTQ_Jul[[#This Row],[State ID]],NRCState_ID,0),2),"")) -> Mon | F22: ပမန | G22: =CLEAN(IFERROR(INDEX(MyanmarLetter_List,MATCH(LEFT(tblTQ_Jul[[#This Row],[TS Symbol]],1),MyanmarLetter_MM,0),1),""))&CLEAN(IFERROR(INDEX(MyanmarLetter_List,MATCH(MID(tblTQ_Jul[[#This Row],[TS Symbol]],2,1),MyanmarLetter_MM,0),1),""))&CLEAN(IFERROR(INDEX(MyanmarLetter_List,MATCH(RIGHT(tblTQ_Jul[[#This Row],[TS Symbol]],1),MyanmarLetter_MM,0),1),"")) -> 222621 | H22: n | I22: =CLEAN(IFERROR(INDEX(NRCType_List,MATCH(tblTQ_Jul[[#This Row],[ID Type]],NRCType_Code,0),1),"")) -> 1 | J22: 030979 | K22: =tblTQ_Jul[[#This Row],[State ID]] & "/" & tblTQ_Jul[[#This Row],[TS Symbol]] &CLEAN(IFERROR( " (" & INDEX(NRCType_List,MATCH($H22,NRCType_Code,0),4)& ") ","")) & tblTQ_Jul[[#This Row],[NRC/Passport No]] -> 10/ပမန (နိုင်) 030979 | L22: =tblTQ_Jul[[#This Row],[State ID]]&tblTQ_Jul[[#This Row],[TS ID]]&tblTQ_Jul[[#This Row],[ID]]&tblTQ_Jul[[#This Row],[NRC/Passport No]] -> 102226211030979 | N22: 1 | Q22: =SUM($M22:$P22) -> 1 | R22: =SchoolOpenDays_Feb-tblTQ_Jul[[#This Row],[Total Leave]] -> 62
C23: =IFERROR(C22+1,1) -> 3 | D23: 10 | E23: =CLEAN(IFERROR(INDEX(NRCState_List,MATCH(tblTQ_Jul[[#This Row],[State ID]],NRCState_ID,0),2),"")) -> Mon | F23: ပမန | G23: =CLEAN(IFERROR(INDEX(MyanmarLetter_List,MATCH(LEFT(tblTQ_Jul[[#This Row],[TS Symbol]],1),MyanmarLetter_MM,0),1),""))&CLEAN(IFERROR(INDEX(MyanmarLetter_List,MATCH(MID(tblTQ_Jul[[#This Row],[TS Symbol]],2,1),MyanmarLetter_MM,0),1),""))&CLEAN(IFERROR(INDEX(MyanmarLetter_List,MATCH(RIGHT(tblTQ_Jul[[#This Row],[TS Symbol]],1),MyanmarLetter_MM,0),1),"")) -> 222621 | H23: n | I23: =CLEAN(IFERROR(INDEX(NRCType_List,MATCH(tblTQ_Jul[[#This Row],[ID Type]],NRCType_Code,0),1),"")) -> 1 | J23: 135754 | K23: =tblTQ_Jul[[#This Row],[State ID]] & "/" & tblTQ_Jul[[#This Row],[TS Symbol]] &CLEAN(IFERROR( " (" & INDEX(NRCType_List,MATCH($H23,NRCType_Code,0),4)& ") ","")) & tblTQ_Jul[[#This Row],[NRC/Passport No]] -> 10/ပမန (နိုင်) 135754 | L23: =tblTQ_Jul[[#This Row],[State ID]]&tblTQ_Jul[[#This Row],[TS ID]]&tblTQ_Jul[[#This Row],[ID]]&tblTQ_Jul[[#This Row],[NRC/Passport No]] -> 102226211135754 | Q23: =SUM($M23:$P23) -> 0 | R23: =SchoolOpenDays_Feb-tblTQ_Jul[[#This Row],[Total Leave]] -> 63
C24: =IFERROR(C23+1,1) -> 4 | D24: 10 | E24: =CLEAN(IFERROR(INDEX(NRCState_List,MATCH(tblTQ_Jul[[#This Row],[State ID]],NRCState_ID,0),2),"")) -> Mon | F24: ပမန | G24: =CLEAN(IFERROR(INDEX(MyanmarLetter_List,MATCH(LEFT(tblTQ_Jul[[#This Row],[TS Symbol]],1),MyanmarLetter_MM,0),1),""))&CLEAN(IFERROR(INDEX(MyanmarLetter_List,MATCH(MID(tblTQ_Jul[[#This Row],[TS Symbol]],2,1),MyanmarLetter_MM,0),1),""))&CLEAN(IFERROR(INDEX(MyanmarLetter_List,MATCH(RIGHT(tblTQ_Jul[[#This Row],[TS Symbol]],1),MyanmarLetter_MM,0),1),"")) -> 222621 | H24: n | I24: =CLEAN(IFERROR(INDEX(NRCType_List,MATCH(tblTQ_Jul[[#This Row],[ID Type]],NRCType_Code,0),1),"")) -> 1 | J24: 031075 | K24: =tblTQ_Jul[[#This Row],[State ID]] & "/" & tblTQ_Jul[[#This Row],[TS Symbol]] &CLEAN(IFERROR( " (" & INDEX(NRCType_List,MATCH($H24,NRCType_Code,0),4)& ") ","")) & tblTQ_Jul[[#This Row],[NRC/Passport No]] -> 10/ပမန (နိုင်) 031075 | L24: =tblTQ_Jul[[#This Row],[State ID]]&tblTQ_Jul[[#This Row],[TS ID]]&tblTQ_Jul[[#This Row],[ID]]&tblTQ_Jul[[#This Row],[NRC/Passport No]] -> 102226211031075 | N24: 2 | Q24: =SUM($M24:$P24) -> 2 | R24: =SchoolOpenDays_Feb-tblTQ_Jul[[#This Row],[Total Leave]] -> 61
C25: =IFERROR(C24+1,1) -> 5 | D25: 10 | E25: =CLEAN(IFERROR(INDEX(NRCState_List,MATCH(tblTQ_Jul[[#This Row],[State ID]],NRCState_ID,0),2),"")) -> Mon | F25: ပမန | G25: =CLEAN(IFERROR(INDEX(MyanmarLetter_List,MATCH(LEFT(tblTQ_Jul[[#This Row],[TS Symbol]],1),MyanmarLetter_MM,0),1),""))&CLEAN(IFERROR(INDEX(MyanmarLetter_List,MATCH(MID(tblTQ_Jul[[#This Row],[TS Symbol]],2,1),MyanmarLetter_MM,0),1),""))&CLEAN(IFERROR(INDEX(MyanmarLetter_List,MATCH(RIGHT(tblTQ_Jul[[#This Row],[TS Symbol]],1),MyanmarLetter_MM,0),1),"")) -> 222621 | H25: n | I25: =CLEAN(IFERROR(INDEX(NRCType_List,MATCH(tblTQ_Jul[[#This Row],[ID Type]],NRCType_Code,0),1),"")) -> 1 | J25: 031065 | K25: =tblTQ_Jul[[#This Row],[State ID]] & "/" & tblTQ_Jul[[#This Row],[TS Symbol]] &CLEAN(IFERROR( " (" & INDEX(NRCType_List,MATCH($H25,NRCType_Code,0),4)& ") ","")) & tblTQ_Jul[[#This Row],[NRC/Passport No]] -> 10/ပမန (နိုင်) 031065 | L25: =tblTQ_Jul[[#This Row],[State ID]]&tblTQ_Jul[[#This Row],[TS ID]]&tblTQ_Jul[[#This Row],[ID]]&tblTQ_Jul[[#This Row],[NRC/Passport No]] -> 102226211031065 | Q25: =SUM($M25:$P25) -> 0 | R25: =SchoolOpenDays_Feb-tblTQ_Jul[[#This Row],[Total Leave]] -> 63
C26: =IFERROR(C25+1,1) -> 6 | D26: 10 | E26: =CLEAN(IFERROR(INDEX(NRCState_List,MATCH(tblTQ_Jul[[#This Row],[State ID]],NRCState_ID,0),2),"")) -> Mon | F26: ပမန | G26: =CLEAN(IFERROR(INDEX(MyanmarLetter_List,MATCH(LEFT(tblTQ_Jul[[#This Row],[TS Symbol]],1),MyanmarLetter_MM,0),1),""))&CLEAN(IFERROR(INDEX(MyanmarLetter_List,MATCH(MID(tblTQ_Jul[[#This Row],[TS Symbol]],2,1),MyanmarLetter_MM,0),1),""))&CLEAN(IFERROR(INDEX(MyanmarLetter_List,MATCH(RIGHT(tblTQ_Jul[[#This Row],[TS Symbol]],1),MyanmarLetter_MM,0),1),"")) -> 222621 | H26: n | I26: =CLEAN(IFERROR(INDEX(NRCType_List,MATCH(tblTQ_Jul[[#This Row],[ID Type]],NRCType_Code,0),1),"")) -> 1 | J26: 035362 | K26: =tblTQ_Jul[[#This Row],[State ID]] & "/" & tblTQ_Jul[[#This Row],[TS Symbol]] &CLEAN(IFERROR( " (" & INDEX(NRCType_List,MATCH($H26,NRCType_Code,0),4)& ") ","")) & tblTQ_Jul[[#This Row],[NRC/Passport No]] -> 10/ပမန (နိုင်) 035362 | L26: 102226211035362 | N26: 2 | Q26: =SUM($M26:$P26) -> 2 | R26: =SchoolOpenDays_Feb-tblTQ_Jul[[#This Row],[Total Leave]] -> 61
C27: =IFERROR(C26+1,1) -> 7 | D27: 10 | E27: =CLEAN(IFERROR(INDEX(NRCState_List,MATCH(tblTQ_Jul[[#This Row],[State ID]],NRCState_ID,0),2),"")) -> Mon | F27: ပမန | G27: =CLEAN(IFERROR(INDEX(MyanmarLetter_List,MATCH(LEFT(tblTQ_Jul[[#This Row],[TS Symbol]],1),MyanmarLetter_MM,0),1),""))&CLEAN(IFERROR(INDEX(MyanmarLetter_List,MATCH(MID(tblTQ_Jul[[#This Row],[TS Symbol]],2,1),MyanmarLetter_MM,0),1),""))&CLEAN(IFERROR(INDEX(MyanmarLetter_List,MATCH(RIGHT(tblTQ_Jul[[#This Row],[TS Symbol]],1),MyanmarLetter_MM,0),1),"")) -> 222621 | H27: n | I27: =CLEAN(IFERROR(INDEX(NRCType_List,MATCH(tblTQ_Jul[[#This Row],[ID Type]],NRCType_Code,0),1),"")) -> 1 | J27: 094980 | K27: =tblTQ_Jul[[#This Row],[State ID]] & "/" & tblTQ_Jul[[#This Row],[TS Symbol]] &CLEAN(IFERROR( " (" & INDEX(NRCType_List,MATCH($H27,NRCType_Code,0),4)& ") ","")) & tblTQ_Jul[[#This Row],[NRC/Passport No]] -> 10/ပမန (နိုင်) 094980 | N27: 2 | Q27: =SUM($M27:$P27) -> 2 | R27: =SchoolOpenDays_Feb-tblTQ_Jul[[#This Row],[Total Leave]] -> 61
C28: =IFERROR(C27+1,1) -> 8 | D28: 10 | E28: =CLEAN(IFERROR(INDEX(NRCState_List,MATCH(tblTQ_Jul[[#This Row],[State ID]],NRCState_ID,0),2),"")) -> Mon | F28: ပမန | G28: =CLEAN(IFERROR(INDEX(MyanmarLetter_List,MATCH(LEFT(tblTQ_Jul[[#This Row],[TS Symbol]],1),MyanmarLetter_MM,0),1),""))&CLEAN(IFERROR(INDEX(MyanmarLetter_List,MATCH(MID(tblTQ_Jul[[#This Row],[TS Symbol]],2,1),MyanmarLetter_MM,0),1),""))&CLEAN(IFERROR(INDEX(MyanmarLetter_List,MATCH(RIGHT(tblTQ_Jul[[#This Row],[TS Symbol]],1),MyanmarLetter_MM,0),1),"")) -> 222621 | H28: n | I28: =CLEAN(IFERROR(INDEX(NRCType_List,MATCH(tblTQ_Jul[[#This Row],[ID Type]],NRCType_Code,0),1),"")) -> 1 | J28: 126133 | K28: =tblTQ_Jul[[#This Row],[State ID]] & "/" & tblTQ_Jul[[#This Row],[TS Symbol]] &CLEAN(IFERROR( " (" & INDEX(NRCType_List,MATCH($H28,NRCType_Code,0),4)& ") ","")) & tblTQ_Jul[[#This Row],[NRC/Passport No]] -> 10/ပမန (နိုင်) 126133 | L28: =tblTQ_Jul[[#This Row],[State ID]]&tblTQ_Jul[[#This Row],[TS ID]]&tblTQ_Jul[[#This Row],[ID]]&tblTQ_Jul[[#This Row],[NRC/Passport No]] -> 102226211126133 | N28: 1 | Q28: =SUM($M28:$P28) -> 1 | R28: =SchoolOpenDays_Feb-tblTQ_Jul[[#This Row],[Total Leave]] -> 62
C29: =IFERROR(C28+1,1) -> 9 | D29: 7 | E29: =CLEAN(IFERROR(INDEX(NRCState_List,MATCH(tblTQ_Jul[[#This Row],[State ID]],NRCState_ID,0),2),"")) -> Bago | F29: အတန | G29: =CLEAN(IFERROR(INDEX(MyanmarLetter_List,MATCH(LEFT(tblTQ_Jul[[#This Row],[TS Symbol]],1),MyanmarLetter_MM,0),1),""))&CLEAN(IFERROR(INDEX(MyanmarLetter_List,MATCH(MID(tblTQ_Jul[[#This Row],[TS Symbol]],2,1),MyanmarLetter_MM,0),1),""))&CLEAN(IFERROR(INDEX(MyanmarLetter_List,MATCH(RIGHT(tblTQ_Jul[[#This Row],[TS Symbol]],1),MyanmarLetter_MM,0),1),"")) -> 341721 | H29: n | I29: =CLEAN(IFERROR(INDEX(NRCType_List,MATCH(tblTQ_Jul[[#This Row],[ID Type]],NRCType_Code,0),1),"")) -> 1 | J29: 070487 | K29: =tblTQ_Jul[[#This Row],[State ID]] & "/" & tblTQ_Jul[[#This Row],[TS Symbol]] &CLEAN(IFERROR( " (" & INDEX(NRCType_List,MATCH($H29,NRCType_Code,0),4)& ") ","")) & tblTQ_Jul[[#This Row],[NRC/Passport No]] -> 7/အတန (နိုင်) 070487 | Q29: =SUM($M29:$P29) -> 0 | R29: =SchoolOpenDays_Feb-tblTQ_Jul[[#This Row],[Total Leave]] -> 63
C30: =IFERROR(C29+1,1) -> 10 | D30: 10 | E30: =CLEAN(IFERROR(INDEX(NRCState_List,MATCH(tblTQ_Jul[[#This Row],[State ID]],NRCState_ID,0),2),"")) -> Mon | F30: ပမန | G30: =CLEAN(IFERROR(INDEX(MyanmarLetter_List,MATCH(LEFT(tblTQ_Jul[[#This Row],[TS Symbol]],1),MyanmarLetter_MM,0),1),""))&CLEAN(IFERROR(INDEX(MyanmarLetter_List,MATCH(MID(tblTQ_Jul[[#This Row],[TS Symbol]],2,1),MyanmarLetter_MM,0),1),""))&CLEAN(IFERROR(INDEX(MyanmarLetter_List,MATCH(RIGHT(tblTQ_Jul[[#This Row],[TS Symbol]],1),MyanmarLetter_MM,0),1),"")) -> 222621 | H30: n | I30: =CLEAN(IFERROR(INDEX(NRCType_List,MATCH(tblTQ_Jul[[#This Row],[ID Type]],NRCType_Code,0),1),"")) -> 1 | J30: 133059 | K30: =tblTQ_Jul[[#This Row],[State ID]] & "/" & tblTQ_Jul[[#This Row],[TS Symbol]] &CLEAN(IFERROR( " (" & INDEX(NRCType_List,MATCH($H30,NRCType_Code,0),4)& ") ","")) & tblTQ_Jul[[#This Row],[NRC/Passport No]] -> 10/ပမန (နိုင်) 133059 | L30: =tblTQ_Jul[[#This Row],[State ID]]&tblTQ_Jul[[#This Row],[TS ID]]&tblTQ_Jul[[#This Row],[ID]]&tblTQ_Jul[[#This Row],[NRC/Passport No]] -> 102226211133059 | Q30: =SUM($M30:$P30) -> 0 | R30: =SchoolOpenDays_Feb-tblTQ_Jul[[#This Row],[Total Leave]] -> 63
C31: =IFERROR(C30+1,1) -> 11 | D31: 10 | E31: =CLEAN(IFERROR(INDEX(NRCState_List,MATCH(tblTQ_Jul[[#This Row],[State ID]],NRCState_ID,0),2),"")) -> Mon | F31: ပမန | G31: =CLEAN(IFERROR(INDEX(MyanmarLetter_List,MATCH(LEFT(tblTQ_Jul[[#This Row],[TS Symbol]],1),MyanmarLetter_MM,0),1),""))&CLEAN(IFERROR(INDEX(MyanmarLetter_List,MATCH(MID(tblTQ_Jul[[#This Row],[TS Symbol]],2,1),MyanmarLetter_MM,0),1),""))&CLEAN(IFERROR(INDEX(MyanmarLetter_List,MATCH(RIGHT(tblTQ_Jul[[#This Row],[TS Symbol]],1),MyanmarLetter_MM,0),1),"")) -> 222621 | H31: n | I31: =CLEAN(IFERROR(INDEX(NRCType_List,MATCH(tblTQ_Jul[[#This Row],[ID Type]],NRCType_Code,0),1),"")) -> 1 | J31: 001832 | K31: =tblTQ_Jul[[#This Row],[State ID]] & "/" & tblTQ_Jul[[#This Row],[TS Symbol]] &CLEAN(IFERROR( " (" & INDEX(NRCType_List,MATCH($H31,NRCType_Code,0),4)& ") ","")) & tblTQ_Jul[[#This Row],[NRC/Passport No]] -> 10/ပမန (နိုင်) 001832 | L31: =tblTQ_Jul[[#This Row],[State ID]]&tblTQ_Jul[[#This Row],[TS ID]]&tblTQ_Jul[[#This Row],[ID]]&tblTQ_Jul[[#This Row],[NRC/Passport No]] -> 102226211001832 | Q31: =SUM($M31:$P31) -> 0 | R31: =SchoolOpenDays_Feb-tblTQ_Jul[[#This Row],[Total Leave]] -> 63
C32: =IFERROR(C31+1,1) -> 12 | D32: 10 | E32: =CLEAN(IFERROR(INDEX(NRCState_List,MATCH(tblTQ_Jul[[#This Row],[State ID]],NRCState_ID,0),2),"")) -> Mon | F32: ပမန | G32: =CLEAN(IFERROR(INDEX(MyanmarLetter_List,MATCH(LEFT(tblTQ_Jul[[#This Row],[TS Symbol]],1),MyanmarLetter_MM,0),1),""))&CLEAN(IFERROR(INDEX(MyanmarLetter_List,MATCH(MID(tblTQ_Jul[[#This Row],[TS Symbol]],2,1),MyanmarLetter_MM,0),1),""))&CLEAN(IFERROR(INDEX(MyanmarLetter_List,MATCH(RIGHT(tblTQ_Jul[[#This Row],[TS Symbol]],1),MyanmarLetter_MM,0),1),"")) -> 222621 | H32: n | I32: =CLEAN(IFERROR(INDEX(NRCType_List,MATCH(tblTQ_Jul[[#This Row],[ID Type]],NRCType_Code,0),1),"")) -> 1 | J32: 195067 | K32: =tblTQ_Jul[[#This Row],[State ID]] & "/" & tblTQ_Jul[[#This Row],[TS Symbol]] &CLEAN(IFERROR( " (" & INDEX(NRCType_List,MATCH($H32,NRCType_Code,0),4)& ") ","")) & tblTQ_Jul[[#This Row],[NRC/Passport No]] -> 10/ပမန (နိုင်) 195067 | L32: =tblTQ_Jul[[#This Row],[State ID]]&tblTQ_Jul[[#This Row],[TS ID]]&tblTQ_Jul[[#This Row],[ID]]&tblTQ_Jul[[#This Row],[NRC/Passport No]] -> 102226211195067 | Q32: =SUM($M32:$P32) -> 0 | R32: =SchoolOpenDays_Feb-tblTQ_Jul[[#This Row],[Total Leave]] -> 63
C33: =IFERROR(C32+1,1) -> 13 | D33: 10 | E33: =CLEAN(IFERROR(INDEX(NRCState_List,MATCH(tblTQ_Jul[[#This Row],[State ID]],NRCState_ID,0),2),"")) -> Mon | F33: ပမန | G33: =CLEAN(IFERROR(INDEX(MyanmarLetter_List,MATCH(LEFT(tblTQ_Jul[[#This Row],[TS Symbol]],1),MyanmarLetter_MM,0),1),""))&CLEAN(IFERROR(INDEX(MyanmarLetter_List,MATCH(MID(tblTQ_Jul[[#This Row],[TS Symbol]],2,1),MyanmarLetter_MM,0),1),""))&CLEAN(IFERROR(INDEX(MyanmarLetter_List,MATCH(RIGHT(tblTQ_Jul[[#This Row],[TS Symbol]],1),MyanmarLetter_MM,0),1),"")) -> 222621 | H33: n | I33: =CLEAN(IFERROR(INDEX(NRCType_List,MATCH(tblTQ_Jul[[#This Row],[ID Type]],NRCType_Code,0),1),"")) -> 1 | J33: 003215 | K33: =tblTQ_Jul[[#This Row],[State ID]] & "/" & tblTQ_Jul[[#This Row],[TS Symbol]] &CLEAN(IFERROR( " (" & INDEX(NRCType_List,MATCH($H33,NRCType_Code,0),4)& ") ","")) & tblTQ_Jul[[#This Row],[NRC/Passport No]] -> 10/ပမန (နိုင်) 003215 | L33: =tblTQ_Jul[[#This Row],[State ID]]&tblTQ_Jul[[#This Row],[TS ID]]&tblTQ_Jul[[#This Row],[ID]]&tblTQ_Jul[[#This Row],[NRC/Passport No]] -> 102226211003215 | N33: 2 | Q33: =SUM($M33:$P33) -> 2 | R33: =SchoolOpenDays_Feb-tblTQ_Jul[[#This Row],[Total Leave]] -> 61
C34: =IFERROR(C33+1,1) -> 14 | D34: 10 | E34: =CLEAN(IFERROR(INDEX(NRCState_List,MATCH(tblTQ_Jul[[#This Row],[State ID]],NRCState_ID,0),2),"")) -> Mon | F34: ပမန | G34: =CLEAN(IFERROR(INDEX(MyanmarLetter_List,MATCH(LEFT(tblTQ_Jul[[#This Row],[TS Symbol]],1),MyanmarLetter_MM,0),1),""))&CLEAN(IFERROR(INDEX(MyanmarLetter_List,MATCH(MID(tblTQ_Jul[[#This Row],[TS Symbol]],2,1),MyanmarLetter_MM,0),1),""))&CLEAN(IFERROR(INDEX(MyanmarLetter_List,MATCH(RIGHT(tblTQ_Jul[[#This Row],[TS Symbol]],1),MyanmarLetter_MM,0),1),"")) -> 222621 | H34: n | I34: =CLEAN(IFERROR(INDEX(NRCType_List,MATCH(tblTQ_Jul[[#This Row],[ID Type]],NRCType_Code,0),1),"")) -> 1 | J34: 031273 | K34: =tblTQ_Jul[[#This Row],[State ID]] & "/" & tblTQ_Jul[[#This Row],[TS Symbol]] &CLEAN(IFERROR( " (" & INDEX(NRCType_List,MATCH($H34,NRCType_Code,0),4)& ") ","")) & tblTQ_Jul[[#This Row],[NRC/Passport No]] -> 10/ပမန (နိုင်) 031273 | L34: =tblTQ_Jul[[#This Row],[State ID]]&tblTQ_Jul[[#This Row],[TS ID]]&tblTQ_Jul[[#This Row],[ID]]&tblTQ_Jul[[#This Row],[NRC/Passport No]] -> 102226211031273 | N34: 1 | Q34: =SUM($M34:$P34) -> 1 | R34: =SchoolOpenDays_Feb-tblTQ_Jul[[#This Row],[Total Leave]] -> 62
C35: =IFERROR(C34+1,1) -> 15 | D35: 10 | E35: =CLEAN(IFERROR(INDEX(NRCState_List,MATCH(tblTQ_Jul[[#This Row],[State ID]],NRCState_ID,0),2),"")) -> Mon | F35: ပမန | G35: =CLEAN(IFERROR(INDEX(MyanmarLetter_List,MATCH(LEFT(tblTQ_Jul[[#This Row],[TS Symbol]],1),MyanmarLetter_MM,0),1),""))&CLEAN(IFERROR(INDEX(MyanmarLetter_List,MATCH(MID(tblTQ_Jul[[#This Row],[TS Symbol]],2,1),MyanmarLetter_MM,0),1),""))&CLEAN(IFERROR(INDEX(MyanmarLetter_List,MATCH(RIGHT(tblTQ_Jul[[#This Row],[TS Symbol]],1),MyanmarLetter_MM,0),1),"")) -> 222621 | H35: n | I35: =CLEAN(IFERROR(INDEX(NRCType_List,MATCH(tblTQ_Jul[[#This Row],[ID Type]],NRCType_Code,0),1),"")) -> 1 | J35: 031274 | K35: =tblTQ_Jul[[#This Row],[State ID]] & "/" & tblTQ_Jul[[#This Row],[TS Symbol]] &CLEAN(IFERROR( " (" & INDEX(NRCType_List,MATCH($H35,NRCType_Code,0),4)& ") ","")) & tblTQ_Jul[[#This Row],[NRC/Passport No]] -> 10/ပမန (နိုင်) 031274 | L35: =tblTQ_Jul[[#This Row],[State ID]]&tblTQ_Jul[[#This Row],[TS ID]]&tblTQ_Jul[[#This Row],[ID]]&tblTQ_Jul[[#This Row],[NRC/Passport No]] -> 102226211031274 | N35: 2 | Q35: =SUM($M35:$P35) -> 2 | R35: =SchoolOpenDays_Feb-tblTQ_Jul[[#This Row],[Total Leave]] -> 61
C36: =IFERROR(C35+1,1) -> 16 | D36: 10 | E36: =CLEAN(IFERROR(INDEX(NRCState_List,MATCH(tblTQ_Jul[[#This Row],[State ID]],NRCState_ID,0),2),"")) -> Mon | F36: ပမန | G36: =CLEAN(IFERROR(INDEX(MyanmarLetter_List,MATCH(LEFT(tblTQ_Jul[[#This Row],[TS Symbol]],1),MyanmarLetter_MM,0),1),""))&CLEAN(IFERROR(INDEX(MyanmarLetter_List,MATCH(MID(tblTQ_Jul[[#This Row],[TS Symbol]],2,1),MyanmarLetter_MM,0),1),""))&CLEAN(IFERROR(INDEX(MyanmarLetter_List,MATCH(RIGHT(tblTQ_Jul[[#This Row],[TS Symbol]],1),MyanmarLetter_MM,0),1),"")) -> 222621 | H36: n | I36: =CLEAN(IFERROR(INDEX(NRCType_List,MATCH(tblTQ_Jul[[#This Row],[ID Type]],NRCType_Code,0),1),"")) -> 1 | J36: 030858 | K36: =tblTQ_Jul[[#This Row],[State ID]] & "/" & tblTQ_Jul[[#This Row],[TS Symbol]] &CLEAN(IFERROR( " (" & INDEX(NRCType_List,MATCH($H36,NRCType_Code,0),4)& ") ","")) & tblTQ_Jul[[#This Row],[NRC/Passport No]] -> 10/ပမန (နိုင်) 030858 | L36: =tblTQ_Jul[[#This Row],[State ID]]&tblTQ_Jul[[#This Row],[TS ID]]&tblTQ_Jul[[#This Row],[ID]]&tblTQ_Jul[[#This Row],[NRC/Passport No]] -> 102226211030858 | Q36: =SUM($M36:$P36) -> 0 | R36: =SchoolOpenDays_Feb-tblTQ_Jul[[#This Row],[Total Leave]] -> 63
C37: =IFERROR(C36+1,1) -> 17 | D37: 10 | E37: =CLEAN(IFERROR(INDEX(NRCState_List,MATCH(tblTQ_Jul[[#This Row],[State ID]],NRCState_ID,0),2),"")) -> Mon | F37: ပမန | G37: =CLEAN(IFERROR(INDEX(MyanmarLetter_List,MATCH(LEFT(tblTQ_Jul[[#This Row],[TS Symbol]],1),MyanmarLetter_MM,0),1),""))&CLEAN(IFERROR(INDEX(MyanmarLetter_List,MATCH(MID(tblTQ_Jul[[#This Row],[TS Symbol]],2,1),MyanmarLetter_MM,0),1),""))&CLEAN(IFERROR(INDEX(MyanmarLetter_List,MATCH(RIGHT(tblTQ_Jul[[#This Row],[TS Symbol]],1),MyanmarLetter_MM,0),1),"")) -> 222621 | H37: n | I37: =CLEAN(IFERROR(INDEX(NRCType_List,MATCH(tblTQ_Jul[[#This Row],[ID Type]],NRCType_Code,0),1),"")) -> 1 | J37: 003334 | K37: =tblTQ_Jul[[#This Row],[State ID]] & "/" & tblTQ_Jul[[#This Row],[TS Symbol]] &CLEAN(IFERROR( " (" & INDEX(NRCType_List,MATCH($H37,NRCType_Code,0),4)& ") ","")) & tblTQ_Jul[[#This Row],[NRC/Passport No]] -> 10/ပမန (နိုင်) 003334 | L37: =tblTQ_Jul[[#This Row],[State ID]]&tblTQ_Jul[[#This Row],[TS ID]]&tblTQ_Jul[[#This Row],[ID]]&tblTQ_Jul[[#This Row],[NRC/Passport No]] -> 102226211003334 | Q37: =SUM($M37:$P37) -> 0 | R37: =SchoolOpenDays_Feb-tblTQ_Jul[[#This Row],[Total Leave]] -> 63
C38: =IFERROR(C37+1,1) -> 18 | D38: 10 | E38: =CLEAN(IFERROR(INDEX(NRCState_List,MATCH(tblTQ_Jul[[#This Row],[State ID]],NRCState_ID,0),2),"")) -> Mon | F38: ပမန | G38: =CLEAN(IFERROR(INDEX(MyanmarLetter_List,MATCH(LEFT(tblTQ_Jul[[#This Row],[TS Symbol]],1),MyanmarLetter_MM,0),1),""))&CLEAN(IFERROR(INDEX(MyanmarLetter_List,MATCH(MID(tblTQ_Jul[[#This Row],[TS Symbol]],2,1),MyanmarLetter_MM,0),1),""))&CLEAN(IFERROR(INDEX(MyanmarLetter_List,MATCH(RIGHT(tblTQ_Jul[[#This Row],[TS Symbol]],1),MyanmarLetter_MM,0),1),"")) -> 222621 | H38: n | I38: =CLEAN(IFERROR(INDEX(NRCType_List,MATCH(tblTQ_Jul[[#This Row],[ID Type]],NRCType_Code,0),1),"")) -> 1 | J38: 013348 | K38: =tblTQ_Jul[[#This Row],[State ID]] & "/" & tblTQ_Jul[[#This Row],[TS Symbol]] &CLEAN(IFERROR( " (" & INDEX(NRCType_List,MATCH($H38,NRCType_Code,0),4)& ") ","")) & tblTQ_Jul[[#This Row],[NRC/Passport No]] -> 10/ပမန (နိုင်) 013348 | L38: =tblTQ_Jul[[#This Row],[State ID]]&tblTQ_Jul[[#This Row],[TS ID]]&tblTQ_Jul[[#This Row],[ID]]&tblTQ_Jul[[#This Row],[NRC/Passport No]] -> 102226211013348 | N38: 1 | Q38: =SUM($M38:$P38) -> 1 | R38: =SchoolOpenDays_Feb-tblTQ_Jul[[#This Row],[Total Leave]] -> 62
C39: =IFERROR(C38+1,1) -> 19 | D39: 10 | E39: =CLEAN(IFERROR(INDEX(NRCState_List,MATCH(tblTQ_Jul[[#This Row],[State ID]],NRCState_ID,0),2),"")) -> Mon | F39: ပမန | G39: =CLEAN(IFERROR(INDEX(MyanmarLetter_List,MATCH(LEFT(tblTQ_Jul[[#This Row],[TS Symbol]],1),MyanmarLetter_MM,0),1),""))&CLEAN(IFERROR(INDEX(MyanmarLetter_List,MATCH(MID(tblTQ_Jul[[#This Row],[TS Symbol]],2,1),MyanmarLetter_MM,0),1),""))&CLEAN(IFERROR(INDEX(MyanmarLetter_List,MATCH(RIGHT(tblTQ_Jul[[#This Row],[TS Symbol]],1),MyanmarLetter_MM,0),1),"")) -> 222621 | H39: n | I39: =CLEAN(IFERROR(INDEX(NRCType_List,MATCH(tblTQ_Jul[[#This Row],[ID Type]],NRCType_Code,0),1),"")) -> 1 | J39: 000938 | K39: =tblTQ_Jul[[#This Row],[State ID]] & "/" & tblTQ_Jul[[#This Row],[TS Symbol]] &CLEAN(IFERROR( " (" & INDEX(NRCType_List,MATCH($H39,NRCType_Code,0),4)& ") ","")) & tblTQ_Jul[[#This Row],[NRC/Passport No]] -> 10/ပမန (နိုင်) 000938 | L39: =tblTQ_Jul[[#This Row],[State ID]]&tblTQ_Jul[[#This Row],[TS ID]]&tblTQ_Jul[[#This Row],[ID]]&tblTQ_Jul[[#This Row],[NRC/Passport No]] -> 102226211000938 | N39: 1 | Q39: =SUM($M39:$P39) -> 1 | R39: =SchoolOpenDays_Feb-tblTQ_Jul[[#This Row],[Total Leave]] -> 62
C40: =IFERROR(C39+1,1) -> 20 | D40: 10 | E40: =CLEAN(IFERROR(INDEX(NRCState_List,MATCH(tblTQ_Jul[[#This Row],[State ID]],NRCState_ID,0),2),"")) -> Mon | F40: ပမန | G40: =CLEAN(IFERROR(INDEX(MyanmarLetter_List,MATCH(LEFT(tblTQ_Jul[[#This Row],[TS Symbol]],1),MyanmarLetter_MM,0),1),""))&CLEAN(IFERROR(INDEX(MyanmarLetter_List,MATCH(MID(tblTQ_Jul[[#This Row],[TS Symbol]],2,1),MyanmarLetter_MM,0),1),""))&CLEAN(IFERROR(INDEX(MyanmarLetter_List,MATCH(RIGHT(tblTQ_Jul[[#This Row],[TS Symbol]],1),MyanmarLetter_MM,0),1),"")) -> 222621 | H40: n | I40: =CLEAN(IFERROR(INDEX(NRCType_List,MATCH(tblTQ_Jul[[#This Row],[ID Type]],NRCType_Code,0),1),"")) -> 1 | J40: 198796 | K40: =tblTQ_Jul[[#This Row],[State ID]] & "/" & tblTQ_Jul[[#This Row],[TS Symbol]] &CLEAN(IFERROR( " (" & INDEX(NRCType_List,MATCH($H40,NRCType_Code,0),4)& ") ","")) & tblTQ_Jul[[#This Row],[NRC/Passport No]] -> 10/ပမန (နိုင်) 198796 | L40: =tblTQ_Jul[[#This Row],[State ID]]&tblTQ_Jul[[#This Row],[TS ID]]&tblTQ_Jul[[#This Row],[ID]]&tblTQ_Jul[[#This Row],[NRC/Passport No]] -> 102226211198796 | N40: 1 | Q40: =SUM($M40:$P40) -> 1 | R40: =SchoolOpenDays_Feb-tblTQ_Jul[[#This Row],[Total Leave]] -> 62
C41: =IFERROR(C40+1,1) -> 21 | D41: 10 | E41: =CLEAN(IFERROR(INDEX(NRCState_List,MATCH(tblTQ_Jul[[#This Row],[State ID]],NRCState_ID,0),2),"")) -> Mon | F41: ပမန | G41: =CLEAN(IFERROR(INDEX(MyanmarLetter_List,MATCH(LEFT(tblTQ_Jul[[#This Row],[TS Symbol]],1),MyanmarLetter_MM,0),1),""))&CLEAN(IFERROR(INDEX(MyanmarLetter_List,MATCH(MID(tblTQ_Jul[[#This Row],[TS Symbol]],2,1),MyanmarLetter_MM,0),1),""))&CLEAN(IFERROR(INDEX(MyanmarLetter_List,MATCH(RIGHT(tblTQ_Jul[[#This Row],[TS Symbol]],1),MyanmarLetter_MM,0),1),"")) -> 222621 | H41: n | I41: =CLEAN(IFERROR(INDEX(NRCType_List,MATCH(tblTQ_Jul[[#This Row],[ID Type]],NRCType_Code,0),1),"")) -> 1 | J41: 111061 | K41: =tblTQ_Jul[[#This Row],[State ID]] & "/" & tblTQ_Jul[[#This Row],[TS Symbol]] &CLEAN(IFERROR( " (" & INDEX(NRCType_List,MATCH($H41,NRCType_Code,0),4)& ") ","")) & tblTQ_Jul[[#This Row],[NRC/Passport No]] -> 10/ပမန (နိုင်) 111061 | L41: =tblTQ_Jul[[#This Row],[State ID]]&tblTQ_Jul[[#This Row],[TS ID]]&tblTQ_Jul[[#This Row],[ID]]&tblTQ_Jul[[#This Row],[NRC/Passport No]] -> 102226211111061 | Q41: =SUM($M41:$P41) -> 0 | R41: =SchoolOpenDays_Feb-tblTQ_Jul[[#This Row],[Total Leave]] -> 63
C42: =IFERROR(C41+1,1) -> 22 | D42: 10 | E42: =CLEAN(IFERROR(INDEX(NRCState_List,MATCH(tblTQ_Jul[[#This Row],[State ID]],NRCState_ID,0),2),"")) -> Mon | F42: ပမန | G42: =CLEAN(IFERROR(INDEX(MyanmarLetter_List,MATCH(LEFT(tblTQ_Jul[[#This Row],[TS Symbol]],1),MyanmarLetter_MM,0),1),""))&CLEAN(IFERROR(INDEX(MyanmarLetter_List,MATCH(MID(tblTQ_Jul[[#This Row],[TS Symbol]],2,1),MyanmarLetter_MM,0),1),""))&CLEAN(IFERROR(INDEX(MyanmarLetter_List,MATCH(RIGHT(tblTQ_Jul[[#This Row],[TS Symbol]],1),MyanmarLetter_MM,0),1),"")) -> 222621 | H42: n | I42: =CLEAN(IFERROR(INDEX(NRCType_List,MATCH(tblTQ_Jul[[#This Row],[ID Type]],NRCType_Code,0),1),"")) -> 1 | J42: 006110 | K42: =tblTQ_Jul[[#This Row],[State ID]] & "/" & tblTQ_Jul[[#This Row],[TS Symbol]] &CLEAN(IFERROR( " (" & INDEX(NRCType_List,MATCH($H42,NRCType_Code,0),4)& ") ","")) & tblTQ_Jul[[#This Row],[NRC/Passport No]] -> 10/ပမန (နိုင်) 006110 | L42: =tblTQ_Jul[[#This Row],[State ID]]&tblTQ_Jul[[#This Row],[TS ID]]&tblTQ_Jul[[#This Row],[ID]]&tblTQ_Jul[[#This Row],[NRC/Passport No]] -> 102226211006110 | N42: 1 | Q42: =SUM($M42:$P42) -> 1 | R42: =SchoolOpenDays_Feb-tblTQ_Jul[[#This Row],[Total Leave]] -> 62
C43: =IFERROR(C42+1,1) -> 23 | D43: 10 | E43: =CLEAN(IFERROR(INDEX(NRCState_List,MATCH(tblTQ_Jul[[#This Row],[State ID]],NRCState_ID,0),2),"")) -> Mon | F43: ပမန | G43: =CLEAN(IFERROR(INDEX(MyanmarLetter_List,MATCH(LEFT(tblTQ_Jul[[#This Row],[TS Symbol]],1),MyanmarLetter_MM,0),1),""))&CLEAN(IFERROR(INDEX(MyanmarLetter_List,MATCH(MID(tblTQ_Jul[[#This Row],[TS Symbol]],2,1),MyanmarLetter_MM,0),1),""))&CLEAN(IFERROR(INDEX(MyanmarLetter_List,MATCH(RIGHT(tblTQ_Jul[[#This Row],[TS Symbol]],1),MyanmarLetter_MM,0),1),"")) -> 222621 | H43: n | I43: =CLEAN(IFERROR(INDEX(NRCType_List,MATCH(tblTQ_Jul[[#This Row],[ID Type]],NRCType_Code,0),1),"")) -> 1 | J43: 123699 | K43: =tblTQ_Jul[[#This Row],[State ID]] & "/" & tblTQ_Jul[[#This Row],[TS Symbol]] &CLEAN(IFERROR( " (" & INDEX(NRCType_List,MATCH($H43,NRCType_Code,0),4)& ") ","")) & tblTQ_Jul[[#This Row],[NRC/Passport No]] -> 10/ပမန (နိုင်) 123699 | L43: =tblTQ_Jul[[#This Row],[State ID]]&tblTQ_Jul[[#This Row],[TS ID]]&tblTQ_Jul[[#This Row],[ID]]&tblTQ_Jul[[#This Row],[NRC/Passport No]] -> 102226211123699 | Q43: =SUM($M43:$P43) -> 0 | R43: =SchoolOpenDays_Feb-tblTQ_Jul[[#This Row],[Total Leave]] -> 63
C44: =IFERROR(C43+1,1) -> 24 | E44: =CLEAN(IFERROR(INDEX(NRCState_List,MATCH(tblTQ_Jul[[#This Row],[State ID]],NRCState_ID,0),2),"")) | G44: =CLEAN(IFERROR(INDEX(MyanmarLetter_List,MATCH(LEFT(tblTQ_Jul[[#This Row],[TS Symbol]],1),MyanmarLetter_MM,0),1),""))&CLEAN(IFERROR(INDEX(MyanmarLetter_List,MATCH(MID(tblTQ_Jul[[#This Row],[TS Symbol]],2,1),MyanmarLetter_MM,0),1),""))&CLEAN(IFERROR(INDEX(MyanmarLetter_List,MATCH(RIGHT(tblTQ_Jul[[#This Row],[TS Symbol]],1),MyanmarLetter_MM,0),1),"")) | I44: =CLEAN(IFERROR(INDEX(NRCType_List,MATCH(tblTQ_Jul[[#This Row],[ID Type]],NRCType_Code,0),1),"")) | K44: =tblTQ_Jul[[#This Row],[State ID]] & "/" & tblTQ_Jul[[#This Row],[TS Symbol]] &CLEAN(IFERROR( " (" & INDEX(NRCType_List,MATCH($H44,NRCType_Code,0),4)& ") ","")) & tblTQ_Jul[[#This Row],[NRC/Passport No]] -> / | L44: =tblTQ_Jul[[#This Row],[State ID]]&tblTQ_Jul[[#This Row],[TS ID]]&tblTQ_Jul[[#This Row],[ID]]&tblTQ_Jul[[#This Row],[NRC/Passport No]] | Q44: =SUM($M44:$P44) -> 0 | R44: =SchoolOpenDays_Feb-tblTQ_Jul[[#This Row],[Total Leave]] -> 63
C45: =IFERROR(C44+1,1) -> 25 | E45: =CLEAN(IFERROR(INDEX(NRCState_List,MATCH(tblTQ_Jul[[#This Row],[State ID]],NRCState_ID,0),2),"")) | G45: =CLEAN(IFERROR(INDEX(MyanmarLetter_List,MATCH(LEFT(tblTQ_Jul[[#This Row],[TS Symbol]],1),MyanmarLetter_MM,0),1),""))&CLEAN(IFERROR(INDEX(MyanmarLetter_List,MATCH(MID(tblTQ_Jul[[#This Row],[TS Symbol]],2,1),MyanmarLetter_MM,0),1),""))&CLEAN(IFERROR(INDEX(MyanmarLetter_List,MATCH(RIGHT(tblTQ_Jul[[#This Row],[TS Symbol]],1),MyanmarLetter_MM,0),1),"")) | I45: =CLEAN(IFERROR(INDEX(NRCType_List,MATCH(tblTQ_Jul[[#This Row],[ID Type]],NRCType_Code,0),1),"")) | K45: =tblTQ_Jul[[#This Row],[State ID]] & "/" & tblTQ_Jul[[#This Row],[TS Symbol]] &CLEAN(IFERROR( " (" & INDEX(NRCType_List,MATCH($H45,NRCType_Code,0),4)& ") ","")) & tblTQ_Jul[[#This Row],[NRC/Passport No]] -> / | L45: =tblTQ_Jul[[#This Row],[State ID]]&tblTQ_Jul[[#This Row],[TS ID]]&tblTQ_Jul[[#This Row],[ID]]&tblTQ_Jul[[#This Row],[NRC/Passport No]] | Q45: =SUM($M45:$P45) -> 0 | R45: =SchoolOpenDays_Feb-tblTQ_Jul[[#This Row],[Total Leave]] -> 63
C46: =IFERROR(C45+1,1) -> 26 | E46: =CLEAN(IFERROR(INDEX(NRCState_List,MATCH(tblTQ_Jul[[#This Row],[State ID]],NRCState_ID,0),2),"")) | G46: =CLEAN(IFERROR(INDEX(MyanmarLetter_List,MATCH(LEFT(tblTQ_Jul[[#This Row],[TS Symbol]],1),MyanmarLetter_MM,0),1),""))&CLEAN(IFERROR(INDEX(MyanmarLetter_List,MATCH(MID(tblTQ_Jul[[#This Row],[TS Symbol]],2,1),MyanmarLetter_MM,0),1),""))&CLEAN(IFERROR(INDEX(MyanmarLetter_List,MATCH(RIGHT(tblTQ_Jul[[#This Row],[TS Symbol]],1),MyanmarLetter_MM,0),1),"")) | I46: =CLEAN(IFERROR(INDEX(NRCType_List,MATCH(tblTQ_Jul[[#This Row],[ID Type]],NRCType_Code,0),1),"")) | K46: =tblTQ_Jul[[#This Row],[State ID]] & "/" & tblTQ_Jul[[#This Row],[TS Symbol]] &CLEAN(IFERROR( " (" & INDEX(NRCType_List,MATCH($H46,NRCType_Code,0),4)& ") ","")) & tblTQ_Jul[[#This Row],[NRC/Passport No]] -> / | L46: =tblTQ_Jul[[#This Row],[State ID]]&tblTQ_Jul[[#This Row],[TS ID]]&tblTQ_Jul[[#This Row],[ID]]&tblTQ_Jul[[#This Row],[NRC/Passport No]] | Q46: =SUM($M46:$P46) -> 0 | R46: =SchoolOpenDays_Feb-tblTQ_Jul[[#This Row],[Total Leave]] -> 63
C47: =IFERROR(C46+1,1) -> 27 | E47: =CLEAN(IFERROR(INDEX(NRCState_List,MATCH(tblTQ_Jul[[#This Row],[State ID]],NRCState_ID,0),2),"")) | G47: =CLEAN(IFERROR(INDEX(MyanmarLetter_List,MATCH(LEFT(tblTQ_Jul[[#This Row],[TS Symbol]],1),MyanmarLetter_MM,0),1),""))&CLEAN(IFERROR(INDEX(MyanmarLetter_List,MATCH(MID(tblTQ_Jul[[#This Row],[TS Symbol]],2,1),MyanmarLetter_MM,0),1),""))&CLEAN(IFERROR(INDEX(MyanmarLetter_List,MATCH(RIGHT(tblTQ_Jul[[#This Row],[TS Symbol]],1),MyanmarLetter_MM,0),1),"")) | I47: =CLEAN(IFERROR(INDEX(NRCType_List,MATCH(tblTQ_Jul[[#This Row],[ID Type]],NRCType_Code,0),1),"")) | K47: =tblTQ_Jul[[#This Row],[State ID]] & "/" & tblTQ_Jul[[#This Row],[TS Symbol]] &CLEAN(IFERROR( " (" & INDEX(NRCType_List,MATCH($H47,NRCType_Code,0),4)& ") ","")) & tblTQ_Jul[[#This Row],[NRC/Passport No]] -> / | L47: =tblTQ_Jul[[#This Row],[State ID]]&tblTQ_Jul[[#This Row],[TS ID]]&tblTQ_Jul[[#This Row],[ID]]&tblTQ_Jul[[#This Row],[NRC/Passport No]] | Q47: =SUM($M47:$P47) -> 0 | R47: =SchoolOpenDays_Feb-tblTQ_Jul[[#This Row],[Total Leave]] -> 63
C48: =IFERROR(C47+1,1) -> 28 | E48: =CLEAN(IFERROR(INDEX(NRCState_List,MATCH(tblTQ_Jul[[#This Row],[State ID]],NRCState_ID,0),2),"")) | G48: =CLEAN(IFERROR(INDEX(MyanmarLetter_List,MATCH(LEFT(tblTQ_Jul[[#This Row],[TS Symbol]],1),MyanmarLetter_MM,0),1),""))&CLEAN(IFERROR(INDEX(MyanmarLetter_List,MATCH(MID(tblTQ_Jul[[#This Row],[TS Symbol]],2,1),MyanmarLetter_MM,0),1),""))&CLEAN(IFERROR(INDEX(MyanmarLetter_List,MATCH(RIGHT(tblTQ_Jul[[#This Row],[TS Symbol]],1),MyanmarLetter_MM,0),1),"")) | I48: =CLEAN(IFERROR(INDEX(NRCType_List,MATCH(tblTQ_Jul[[#This Row],[ID Type]],NRCType_Code,0),1),"")) | K48: =tblTQ_Jul[[#This Row],[State ID]] & "/" & tblTQ_Jul[[#This Row],[TS Symbol]] &CLEAN(IFERROR( " (" & INDEX(NRCType_List,MATCH($H48,NRCType_Code,0),4)& ") ","")) & tblTQ_Jul[[#This Row],[NRC/Passport No]] -> / | L48: =tblTQ_Jul[[#This Row],[State ID]]&tblTQ_Jul[[#This Row],[TS ID]]&tblTQ_Jul[[#This Row],[ID]]&tblTQ_Jul[[#This Row],[NRC/Passport No]] | Q48: =SUM($M48:$P48) -> 0 | R48: =SchoolOpenDays_Feb-tblTQ_Jul[[#This Row],[Total Leave]] -> 63
C49: =IFERROR(C48+1,1) -> 29 | E49: =CLEAN(IFERROR(INDEX(NRCState_List,MATCH(tblTQ_Jul[[#This Row],[State ID]],NRCState_ID,0),2),"")) | G49: =CLEAN(IFERROR(INDEX(MyanmarLetter_List,MATCH(LEFT(tblTQ_Jul[[#This Row],[TS Symbol]],1),MyanmarLetter_MM,0),1),""))&CLEAN(IFERROR(INDEX(MyanmarLetter_List,MATCH(MID(tblTQ_Jul[[#This Row],[TS Symbol]],2,1),MyanmarLetter_MM,0),1),""))&CLEAN(IFERROR(INDEX(MyanmarLetter_List,MATCH(RIGHT(tblTQ_Jul[[#This Row],[TS Symbol]],1),MyanmarLetter_MM,0),1),"")) | I49: =CLEAN(IFERROR(INDEX(NRCType_List,MATCH(tblTQ_Jul[[#This Row],[ID Type]],NRCType_Code,0),1),"")) | K49: =tblTQ_Jul[[#This Row],[State ID]] & "/" & tblTQ_Jul[[#This Row],[TS Symbol]] &CLEAN(IFERROR( " (" & INDEX(NRCType_List,MATCH($H49,NRCType_Code,0),4)& ") ","")) & tblTQ_Jul[[#This Row],[NRC/Passport No]] -> / | L49: =tblTQ_Jul[[#This Row],[State ID]]&tblTQ_Jul[[#This Row],[TS ID]]&tblTQ_Jul[[#This Row],[ID]]&tblTQ_Jul[[#This Row],[NRC/Passport No]] | Q49: =SUM($M49:$P49) -> 0 | R49: =SchoolOpenDays_Feb-tblTQ_Jul[[#This Row],[Total Leave]] -> 63
C50: =IFERROR(C49+1,1) -> 30 | E50: =CLEAN(IFERROR(INDEX(NRCState_List,MATCH(tblTQ_Jul[[#This Row],[State ID]],NRCState_ID,0),2),"")) | G50: =CLEAN(IFERROR(INDEX(MyanmarLetter_List,MATCH(LEFT(tblTQ_Jul[[#This Row],[TS Symbol]],1),MyanmarLetter_MM,0),1),""))&CLEAN(IFERROR(INDEX(MyanmarLetter_List,MATCH(MID(tblTQ_Jul[[#This Row],[TS Symbol]],2,1),MyanmarLetter_MM,0),1),""))&CLEAN(IFERROR(INDEX(MyanmarLetter_List,MATCH(RIGHT(tblTQ_Jul[[#This Row],[TS Symbol]],1),MyanmarLetter_MM,0),1),"")) | I50: =CLEAN(IFERROR(INDEX(NRCType_List,MATCH(tblTQ_Jul[[#This Row],[ID Type]],NRCType_Code,0),1),"")) | K50: =tblTQ_Jul[[#This Row],[State ID]] & "/" & tblTQ_Jul[[#This Row],[TS Symbol]] &CLEAN(IFERROR( " (" & INDEX(NRCType_List,MATCH($H50,NRCType_Code,0),4)& ") ","")) & tblTQ_Jul[[#This Row],[NRC/Passport No]] -> / | L50: =tblTQ_Jul[[#This Row],[State ID]]&tblTQ_Jul[[#This Row],[TS ID]]&tblTQ_Jul[[#This Row],[ID]]&tblTQ_Jul[[#This Row],[NRC/Passport No]] | Q50: =SUM($M50:$P50) -> 0 | R50: =SchoolOpenDays_Feb-tblTQ_Jul[[#This Row],[Total Leave]] -> 63
C51: =IFERROR(C50+1,1) -> 31 | E51: =CLEAN(IFERROR(INDEX(NRCState_List,MATCH(tblTQ_Jul[[#This Row],[State ID]],NRCState_ID,0),2),"")) | G51: =CLEAN(IFERROR(INDEX(MyanmarLetter_List,MATCH(LEFT(tblTQ_Jul[[#This Row],[TS Symbol]],1),MyanmarLetter_MM,0),1),""))&CLEAN(IFERROR(INDEX(MyanmarLetter_List,MATCH(MID(tblTQ_Jul[[#This Row],[TS Symbol]],2,1),MyanmarLetter_MM,0),1),""))&CLEAN(IFERROR(INDEX(MyanmarLetter_List,MATCH(RIGHT(tblTQ_Jul[[#This Row],[TS Symbol]],1),MyanmarLetter_MM,0),1),"")) | I51: =CLEAN(IFERROR(INDEX(NRCType_List,MATCH(tblTQ_Jul[[#This Row],[ID Type]],NRCType_Code,0),1),"")) | K51: =tblTQ_Jul[[#This Row],[State ID]] & "/" & tblTQ_Jul[[#This Row],[TS Symbol]] &CLEAN(IFERROR( " (" & INDEX(NRCType_List,MATCH($H51,NRCType_Code,0),4)& ") ","")) & tblTQ_Jul[[#This Row],[NRC/Passport No]] -> / | L51: =tblTQ_Jul[[#This Row],[State ID]]&tblTQ_Jul[[#This Row],[TS ID]]&tblTQ_Jul[[#This Row],[ID]]&tblTQ_Jul[[#This Row],[NRC/Passport No]] | Q51: =SUM($M51:$P51) -> 0 | R51: =SchoolOpenDays_Feb-tblTQ_Jul[[#This Row],[Total Leave]] -> 63
C52: =IFERROR(C51+1,1) -> 32 | E52: =CLEAN(IFERROR(INDEX(NRCState_List,MATCH(tblTQ_Jul[[#This Row],[State ID]],NRCState_ID,0),2),"")) | G52: =CLEAN(IFERROR(INDEX(MyanmarLetter_List,MATCH(LEFT(tblTQ_Jul[[#This Row],[TS Symbol]],1),MyanmarLetter_MM,0),1),""))&CLEAN(IFERROR(INDEX(MyanmarLetter_List,MATCH(MID(tblTQ_Jul[[#This Row],[TS Symbol]],2,1),MyanmarLetter_MM,0),1),""))&CLEAN(IFERROR(INDEX(MyanmarLetter_List,MATCH(RIGHT(tblTQ_Jul[[#This Row],[TS Symbol]],1),MyanmarLetter_MM,0),1),"")) | I52: =CLEAN(IFERROR(INDEX(NRCType_List,MATCH(tblTQ_Jul[[#This Row],[ID Type]],NRCType_Code,0),1),"")) | K52: =tblTQ_Jul[[#This Row],[State ID]] & "/" & tblTQ_Jul[[#This Row],[TS Symbol]] &CLEAN(IFERROR( " (" & INDEX(NRCType_List,MATCH($H52,NRCType_Code,0),4)& ") ","")) & tblTQ_Jul[[#This Row],[NRC/Passport No]] -> / | L52: =tblTQ_Jul[[#This Row],[State ID]]&tblTQ_Jul[[#This Row],[TS ID]]&tblTQ_Jul[[#This Row],[ID]]&tblTQ_Jul[[#This Row],[NRC/Passport No]] | Q52: =SUM($M52:$P52) -> 0 | R52: =SchoolOpenDays_Feb-tblTQ_Jul[[#This Row],[Total Leave]] -> 63
C53: =IFERROR(C52+1,1) -> 33 | E53: =CLEAN(IFERROR(INDEX(NRCState_List,MATCH(tblTQ_Jul[[#This Row],[State ID]],NRCState_ID,0),2),"")) | G53: =CLEAN(IFERROR(INDEX(MyanmarLetter_List,MATCH(LEFT(tblTQ_Jul[[#This Row],[TS Symbol]],1),MyanmarLetter_MM,0),1),""))&CLEAN(IFERROR(INDEX(MyanmarLetter_List,MATCH(MID(tblTQ_Jul[[#This Row],[TS Symbol]],2,1),MyanmarLetter_MM,0),1),""))&CLEAN(IFERROR(INDEX(MyanmarLetter_List,MATCH(RIGHT(tblTQ_Jul[[#This Row],[TS Symbol]],1),MyanmarLetter_MM,0),1),"")) | I53: =CLEAN(IFERROR(INDEX(NRCType_List,MATCH(tblTQ_Jul[[#This Row],[ID Type]],NRCType_Code,0),1),"")) | K53: =tblTQ_Jul[[#This Row],[State ID]] & "/" & tblTQ_Jul[[#This Row],[TS Symbol]] &CLEAN(IFERROR( " (" & INDEX(NRCType_List,MATCH($H53,NRCType_Code,0),4)& ") ","")) & tblTQ_Jul[[#This Row],[NRC/Passport No]] -> / | L53: =tblTQ_Jul[[#This Row],[State ID]]&tblTQ_Jul[[#This Row],[TS ID]]&tblTQ_Jul[[#This Row],[ID]]&tblTQ_Jul[[#This Row],[NRC/Passport No]] | Q53: =SUM($M53:$P53) -> 0 | R53: =SchoolOpenDays_Feb-tblTQ_Jul[[#This Row],[Total Leave]] -> 63
C54: =IFERROR(C53+1,1) -> 34 | E54: =CLEAN(IFERROR(INDEX(NRCState_List,MATCH(tblTQ_Jul[[#This Row],[State ID]],NRCState_ID,0),2),"")) | G54: =CLEAN(IFERROR(INDEX(MyanmarLetter_List,MATCH(LEFT(tblTQ_Jul[[#This Row],[TS Symbol]],1),MyanmarLetter_MM,0),1),""))&CLEAN(IFERROR(INDEX(MyanmarLetter_List,MATCH(MID(tblTQ_Jul[[#This Row],[TS Symbol]],2,1),MyanmarLetter_MM,0),1),""))&CLEAN(IFERROR(INDEX(MyanmarLetter_List,MATCH(RIGHT(tblTQ_Jul[[#This Row],[TS Symbol]],1),MyanmarLetter_MM,0),1),"")) | I54: =CLEAN(IFERROR(INDEX(NRCType_List,MATCH(tblTQ_Jul[[#This Row],[ID Type]],NRCType_Code,0),1),"")) | K54: =tblTQ_Jul[[#This Row],[State ID]] & "/" & tblTQ_Jul[[#This Row],[TS Symbol]] &CLEAN(IFERROR( " (" & INDEX(NRCType_List,MATCH($H54,NRCType_Code,0),4)& ") ","")) & tblTQ_Jul[[#This Row],[NRC/Passport No]] -> / | L54: =tblTQ_Jul[[#This Row],[State ID]]&tblTQ_Jul[[#This Row],[TS ID]]&tblTQ_Jul[[#This Row],[ID]]&tblTQ_Jul[[#This Row],[NRC/Passport No]] | Q54: =SUM($M54:$P54) -> 0 | R54: =SchoolOpenDays_Feb-tblTQ_Jul[[#This Row],[Total Leave]] -> 63
C55: =IFERROR(C54+1,1) -> 35 | E55: =CLEAN(IFERROR(INDEX(NRCState_List,MATCH(tblTQ_Jul[[#This Row],[State ID]],NRCState_ID,0),2),"")) | G55: =CLEAN(IFERROR(INDEX(MyanmarLetter_List,MATCH(LEFT(tblTQ_Jul[[#This Row],[TS Symbol]],1),MyanmarLetter_MM,0),1),""))&CLEAN(IFERROR(INDEX(MyanmarLetter_List,MATCH(MID(tblTQ_Jul[[#This Row],[TS Symbol]],2,1),MyanmarLetter_MM,0),1),""))&CLEAN(IFERROR(INDEX(MyanmarLetter_List,MATCH(RIGHT(tblTQ_Jul[[#This Row],[TS Symbol]],1),MyanmarLetter_MM,0),1),"")) | I55: =CLEAN(IFERROR(INDEX(NRCType_List,MATCH(tblTQ_Jul[[#This Row],[ID Type]],NRCType_Code,0),1),"")) | K55: =tblTQ_Jul[[#This Row],[State ID]] & "/" & tblTQ_Jul[[#This Row],[TS Symbol]] &CLEAN(IFERROR( " (" & INDEX(NRCType_List,MATCH($H55,NRCType_Code,0),4)& ") ","")) & tblTQ_Jul[[#This Row],[NRC/Passport No]] -> / | L55: =tblTQ_Jul[[#This Row],[State ID]]&tblTQ_Jul[[#This Row],[TS ID]]&tblTQ_Jul[[#This Row],[ID]]&tblTQ_Jul[[#This Row],[NRC/Passport No]] | Q55: =SUM($M55:$P55) -> 0 | R55: =SchoolOpenDays_Feb-tblTQ_Jul[[#This Row],[Total Leave]] -> 63

Sheet TQ_Oct
C2: The Republic of the Union of Myanmar
C3: Ministry of Education
C4: Township Education Management Information System
C5: TEACHER ATTENDANCE (AUG) | U5: Paper Form Signed By
G7: Academic Year | H7: =AcademicYear_Name -> 2013-2014 | N7: Attendance Period | O7: ="Oct " & Academic_Start_Year -> Oct 2013 | U7: Name | V7: =FormSignedName_31 -> ငွေဝင်း
G9: Township | H9: =Township_Name_EN -> Paung | N9: State / Region | O9: =StateRegion_Name_EN -> Mon | U9: Office Post | V9: =FormDate_31 -> 41768
G10: TS_Myanmar | H10: =Township_Name_MM -> ပေါင် | N10: SR_Myanmar | O10: =StateRegion_Name_MM -> မွန်ပြည်နယ် | U10: Signed Date (DD/MM/YYYY) | V10: 41768
E12: School ID | F12: =CLEAN(Selected_School_ID) -> 11008018001 | K12: School Name | L12: =CLEAN(Selected_School_Name) -> အ.ထ.က ရင်ငြိမ်
C16: School open days for each period (June-Aug) | K16: 58
D18: Teacher ID | M18: Days of absence for teaching | R18: Total teacher attendance for each period
C19: Sr. | M19: 1 | N19: 2 | O19: 3 | P19: 4 | Q19: 5 | R19: 6
C20: Sr. | D20: State ID | E20: State Name | F20: TS Symbol | G20: TS ID | H20: ID Type | I20: ID | J20: NRC/Passport No | K20: Teacher NRC ID | L20: Teacher ID | M20: Other duty | N20: Certified leave | O20: Uncertified leave | P20: Without Pay | Q20: Total Leave | R20: (June-Aug/Sept-Nov/ Dec-Aug)
A21: =IF(AND(NOT($G21=""),COUNTIF(TearcherID_Aug,$G21)>1),TRUE,FALSE) | C21: 1 | D21: 10 | E21: Mon | F21: ပမန | G21: 222621 | H21: n | I21: 1 | J21: 030552 | K21: 10/ပမန (နိုင်) 030552 | L21: 102226211030552 | N21: 1 | Q21: 1 | R21: 57
A22: =AND(ISNUMBER(VALUE(F21)),COUNTIF($H$15:$H$30,F21)<=1) | C22: 2 | D22: 10 | E22: Mon | F22: ပမန | G22: 222621 | H22: n | I22: 1 | J22: 030979 | K22: 10/ပမန (နိုင်) 030979 | L22: 102226211030979 | N22: 2 | Q22: 2 | R22: 56
C23: 3 | D23: 10 | E23: Mon | F23: ပမန | G23: 222621 | H23: n | I23: 1 | J23: 135754 | K23: 10/ပမန (နိုင်) 135754 | L23: 102226211135754 | N23: 1 | Q23: 1 | R23: 57
A24: =IF(NOT(OR(ISBLANK(TQ_Aug!$E21),ISBLANK(TQ_Aug!$J21))),TQ_Aug!$E21&TQ_Aug!$J21,"") | C24: 4 | D24: 10 | E24: Mon | F24: ပမန | G24: 222621 | H24: n | I24: 1 | J24: 031075 | K24: 10/ပမန (နိုင်) 031075 | L24: 102226211031075 | N24: 3 | Q24: 3 | R24: 55
C25: 5 | D25: 10 | E25: Mon | F25: ပမန | G25: 222621 | H25: n | I25: 1 | J25: 031065 | K25: 10/ပမန (နိုင်) 031065 | L25: 102226211031065 | N25: 1 | Q25: 1 | R25: 57
C26: 6 | D26: 10 | E26: Mon | F26: ပမန | G26: 222621 | H26: n | I26: 1 | J26: 035362 | K26: 10/ပမန (နိုင်) 035362 | N26: 2 | Q26: 2 | R26: 56
C27: 7 | D27: 10 | E27: Mon | F27: ပမန | G27: 222621 | H27: n | I27: 1 | J27: 094980 | K27: 10/ပမန (နိုင်) 094980 | N27: 3 | Q27: 3 | R27: 55
C28: 8 | D28: 10 | E28: Mon | F28: ပမန | G28: 222621 | H28: n | I28: 1 | J28: 126133 | K28: 10/ပမန (နိုင်) 126133 | L28: 102226211126133 | N28: 2 | Q28: 2 | R28: 56
C29: 9 | D29: 7 | E29: Bago | F29: အတန | G29: 341721 | H29: n | I29: 1 | J29: 070487 | K29: 7/အတန (နိုင်) 070487 | N29: 1 | Q29: 1 | R29: 57
C30: 10 | D30: 10 | E30: Mon | F30: ပမန | G30: 222621 | H30: n | I30: 1 | J30: 133059 | K30: 10/ပမန (နိုင်) 133059 | L30: 102226211133059 | Q30: 0 | R30: 58
C31: 11 | D31: 10 | E31: Mon | F31: ပမန | G31: 222621 | H31: n | I31: 1 | J31: 001832 | K31: 10/ပမန (နိုင်) 001832 | L31: 102226211001832 | N31: 1 | Q31: 1 | R31: 57
C32: 12 | D32: 10 | E32: Mon | F32: ပမန | G32: 222621 | H32: n | I32: 1 | J32: 195067 | K32: 10/ပမန (နိုင်) 195067 | L32: 102226211195067 | N32: 1 | Q32: 1 | R32: 57
C33: 13 | D33: 10 | E33: Mon | F33: ပမန | G33: 222621 | H33: n | I33: 1 | J33: 003215 | K33: 10/ပမန (နိုင်) 003215 | L33: 102226211003215 | N33: 2 | Q33: 2 | R33: 56
C34: 14 | D34: 10 | E34: Mon | F34: ပမန | G34: 222621 | H34: n | I34: 1 | J34: 031273 | K34: 10/ပမန (နိုင်) 031273 | L34: 102226211031273 | Q34: 0 | R34: 58
C35: 15 | D35: 10 | E35: Mon | F35: ပမန | G35: 222621 | H35: n | I35: 1 | J35: 031274 | K35: 10/ပမန (နိုင်) 031274 | L35: 102226211031274 | N35: 3 | Q35: 3 | R35: 55
C36: 16 | D36: 10 | E36: Mon | F36: ပမန | G36: 222621 | H36: n | I36: 1 | J36: 030858 | K36: 10/ပမန (နိုင်) 030858 | L36: 102226211030858 | N36: 1 | Q36: 1 | R36: 57
C37: 17 | D37: 10 | E37: Mon | F37: ပမန | G37: 222621 | H37: n | I37: 1 | J37: 003334 | K37: 10/ပမန (နိုင်) 003334 | L37: 102226211003334 | N37: 2 | Q37: 2 | R37: 56
C38: 18 | D38: 10 | E38: Mon | F38: ပမန | G38: 222621 | H38: n | I38: 1 | J38: 013348 | K38: 10/ပမန (နိုင်) 013348 | L38: 102226211013348 | N38: 1 | Q38: 1 | R38: 57
C39: 19 | D39: 10 | E39: Mon | F39: ပမန | G39: 222621 | H39: n | I39: 1 | J39: 000938 | K39: 10/ပမန (နိုင်) 000938 | L39: 102226211000938 | N39: 1 | Q39: 1 | R39: 57
C40: 20 | D40: 10 | E40: Mon | F40: ပမန | G40: 222621 | H40: n | I40: 1 | J40: 198796 | K40: 10/ပမန (နိုင်) 198796 | L40: 102226211198796 | N40: 1 | Q40: 1 | R40: 57
C41: 21 | D41: 10 | E41: Mon | F41: ပမန | G41: 222621 | H41: n | I41: 1 | J41: 111061 | K41: 10/ပမန (နိုင်) 111061 | L41: 102226211111061 | N41: 1 | Q41: 1 | R41: 57
C42: 22 | D42: 10 | E42: Mon | F42: ပမန | G42: 222621 | H42: n | I42: 1 | J42: 006110 | K42: 10/ပမန (နိုင်) 006110 | L42: 102226211006110 | N42: 2 | Q42: 2 | R42: 56
C43: 23 | D43: 10 | E43: Mon | F43: ပမန | G43: 222621 | H43: n | I43: 1 | J43: 123699 | K43: 10/ပမန (နိုင်) 123699 | L43: 102226211123699 | N43: 1 | Q43: 1 | R43: 57
C44: 24 | K44: / | Q44: 0 | R44: 64
C45: 25 | K45: / | Q45: 0 | R45: 64
C46: 26 | K46: / | Q46: 0 | R46: 64
C47: 27 | K47: / | Q47: 0 | R47: 64
C48: 28 | K48: / | Q48: 0 | R48: 64
C49: 29 | K49: / | Q49: 0 | R49: 64
C50: 30 | K50: / | Q50: 0 | R50: 64
C51: 31 | K51: / | Q51: 0 | R51: 64
C52: 32 | K52: / | Q52: 0 | R52: 64
C53: 33 | K53: / | Q53: 0 | R53: 64
C54: 34 | K54: / | Q54: 0 | R54: 64
C55: 35 | K55: / | Q55: 0 | R55: 64

Sheet Clean_PM_03_Head
A1: PM_03_ID | B1: School_AY_Info_ID | C1: AcdemicMonth
A2: ="313" & C2 & AcademicYear_ID& "" & TSIndex_SchoolID -> 313032014180018001 | B2: =CLEAN(SchoolAY_Info_ID) -> 30201411008018001 | C2: 03
A5: =LEN($A$2) -> 18 | B5: =LEN($B$2) -> 17 | C5: =LEN($C$2) -> 2 | D5: =LEN($D$2) -> 0 | E5: =LEN($E$2) -> 0 | F5: =LEN($F$2) -> 0

Sheet TQ_Mar
C2: The Republic of the Union of Myanmar
C3: Ministry of Education
C4: Township Education Management Information System
C5: TEACHER ATTENDANCE (NOV) | U5: Paper Form Signed By
G7: Academic Year | H7: =AcademicYear_Name -> 2013-2014 | N7: Attendance Period | O7: ="Mar " & Academic_Start_Year -> Mar 2013 | U7: Name | V7: =FormSignedName_31 -> ငွေဝင်း
G9: Township | H9: =Township_Name_EN -> Paung | N9: State / Region | O9: =StateRegion_Name_EN -> Mon | U9: Office Post | V9: 7
G10: TS_Myanmar | H10: =Township_Name_MM -> ပေါင် | N10: SR_Myanmar | O10: =StateRegion_Name_MM -> မွန်ပြည်နယ် | U10: Signed Date (DD/MM/YYYY) | V10: 41768
E12: School ID | F12: =CLEAN(Selected_School_ID) -> 11008018001 | K12: School Name | L12: =CLEAN(Selected_School_Name) -> အ.ထ.က ရင်ငြိမ်
C16: School open days for each period (Sept-Nov) | K16: 58
H18: Teacher ID | M18: Days of absence for teaching | R18: Total teacher attendance for each period
C19: Sr. | M19: 1 | N19: 2 | O19: 3 | Q19: 4 | R19: 5
C20: Sr. | D20: State ID | E20: State Name | F20: TS Symbol | G20: TS ID | H20: ID Type | I20: ID | J20: NRC/Passport No | K20: Teacher NRC ID | L20: Teacher ID | M20: Other duty | N20: Certified leave | O20: Uncertified leave | P20: Without Pay | Q20: Total Leave | R20: (June-Aug/ Sept-Nov/Dec-Aug)
A21: =IF(AND(NOT($G21=""),COUNTIF(TearcherID_Nov,$G21)>1),TRUE,FALSE) | C21: 1 | D21: 10 | E21: Mon | F21: ပမန | G21: 222621 | H21: n | I21: 1 | J21: 030552 | K21: 10/ပမန (နိုင်) 030552 | L21: 102226211030552 | N21: 1 | Q21: 1 | R21: 58
C22: 2 | D22: 10 | E22: Mon | F22: ပမန | G22: 222621 | H22: n | I22: 1 | J22: 030979 | K22: 10/ပမန (နိုင်) 030979 | L22: 102226211030979 | N22: 4 | Q22: 4 | R22: 55
C23: 3 | D23: 10 | E23: Mon | F23: ပမန | G23: 222621 | H23: n | I23: 1 | J23: 135754 | K23: 10/ပမန (နိုင်) 135754 | L23: 102226211135754 | N23: 1 | Q23: 1 | R23: 58
C24: 4 | D24: 10 | E24: Mon | F24: ပမန | G24: 222621 | H24: n | I24: 1 | J24: 031075 | K24: 10/ပမန (နိုင်) 031075 | L24: 102226211031075 | N24: 3 | Q24: 3 | R24: 56
C25: 5 | D25: 10 | E25: Mon | F25: ပမန | G25: 222621 | H25: n | I25: 1 | J25: 031065 | K25: 10/ပမန (နိုင်) 031065 | L25: 102226211031065 | N25: 1 | Q25: 1 | R25: 58
C26: 6 | D26: 10 | E26: Mon | F26: ပမန | G26: 222621 | H26: n | I26: 1 | J26: 035362 | K26: 10/ပမန (နိုင်) 035362 | N26: 3 | Q26: 3 | R26: 56
C27: 7 | D27: 10 | E27: Mon | F27: ပမန | G27: 222621 | H27: n | I27: 1 | J27: 094980 | K27: 10/ပမန (နိုင်) 094980 | N27: 2 | Q27: 2 | R27: 57
C28: 8 | D28: 10 | E28: Mon | F28: ပမန | G28: 222621 | H28: n | I28: 1 | J28: 126133 | K28: 10/ပမန (နိုင်) 126133 | L28: 102226211126133 | N28: 2 | Q28: 2 | R28: 57
C29: 9 | D29: 7 | E29: Bago | F29: အတန | G29: 341721 | H29: n | I29: 1 | J29: 070487 | K29: 7/အတန (နိုင်) 070487 | N29: 1 | Q29: 1 | R29: 58
C30: 10 | D30: 10 | E30: Mon | F30: ပမန | G30: 222621 | H30: n | I30: 1 | J30: 133059 | K30: 10/ပမန (နိုင်) 133059 | L30: 102226211133059 | Q30: 0 | R30: 59
C31: 11 | D31: 10 | E31: Mon | F31: ပမန | G31: 222621 | H31: n | I31: 1 | J31: 001832 | K31: 10/ပမန (နိုင်) 001832 | L31: 102226211001832 | N31: 1 | Q31: 1 | R31: 58
C32: 12 | D32: 10 | E32: Mon | F32: ပမန | G32: 222621 | H32: n | I32: 1 | J32: 195067 | K32: 10/ပမန (နိုင်) 195067 | L32: 102226211195067 | Q32: 0 | R32: 59
C33: 13 | D33: 10 | E33: Mon | F33: ပမန | G33: 222621 | H33: n | I33: 1 | J33: 003215 | K33: 10/ပမန (နိုင်) 003215 | L33: 102226211003215 | N33: 1 | Q33: 1 | R33: 58
C34: 14 | D34: 10 | E34: Mon | F34: ပမန | G34: 222621 | H34: n | I34: 1 | J34: 031273 | K34: 10/ပမန (နိုင်) 031273 | L34: 102226211031273 | Q34: 0 | R34: 59
C35: 15 | D35: 10 | E35: Mon | F35: ပမန | G35: 222621 | H35: n | I35: 1 | J35: 031274 | K35: 10/ပမန (နိုင်) 031274 | L35: 102226211031274 | N35: 2 | Q35: 2 | R35: 57
C36: 16 | D36: 10 | E36: Mon | F36: ပမန | G36: 222621 | H36: n | I36: 1 | J36: 030858 | K36: 10/ပမန (နိုင်) 030858 | L36: 102226211030858 | N36: 1 | Q36: 1 | R36: 58
C37: 17 | D37: 10 | E37: Mon | F37: ပမန | G37: 222621 | H37: n | I37: 1 | J37: 003334 | K37: 10/ပမန (နိုင်) 003334 | L37: 102226211003334 | N37: 2 | Q37: 2 | R37: 57
C38: 18 | D38: 10 | E38: Mon | F38: ပမန | G38: 222621 | H38: n | I38: 1 | J38: 013348 | K38: 10/ပမန (နိုင်) 013348 | L38: 102226211013348 | N38: 2 | Q38: 2 | R38: 57
C39: 19 | D39: 10 | E39: Mon | F39: ပမန | G39: 222621 | H39: n | I39: 1 | J39: 000938 | K39: 10/ပမန (နိုင်) 000938 | L39: 102226211000938 | N39: 1 | Q39: 1 | R39: 58
C40: 20 | D40: 10 | E40: Mon | F40: ပမန | G40: 222621 | H40: n | I40: 1 | J40: 198796 | K40: 10/ပမန (နိုင်) 198796 | L40: 102226211198796 | N40: 1 | Q40: 1 | R40: 58
C41: 21 | D41: 10 | E41: Mon | F41: ပမန | G41: 222621 | H41: n | I41: 1 | J41: 111061 | K41: 10/ပမန (နိုင်) 111061 | L41: 102226211111061 | N41: 1 | Q41: 1 | R41: 58
C42: 22 | D42: 10 | E42: Mon | F42: ပမန | G42: 222621 | H42: n | I42: 1 | J42: 006110 | K42: 10/ပမန (နိုင်) 006110 | L42: 102226211006110 | N42: 1 | Q42: 1 | R42: 58
C43: 23 | D43: 10 | E43: Mon | F43: ပမန | G43: 222621 | H43: n | I43: 1 | J43: 123699 | K43: 10/ပမန (နိုင်) 123699 | L43: 102226211123699 | N43: 1 | Q43: 1 | R43: 58
C44: 24 | K44: / | Q44: 0 | R44: 64
C45: 25 | K45: / | Q45: 0 | R45: 64
C46: 26 | K46: / | Q46: 0 | R46: 64
C47: 27 | K47: / | Q47: 0 | R47: 64
C48: 28 | K48: / | Q48: 0 | R48: 64
C49: 29 | K49: / | Q49: 0 | R49: 64
C50: 30 | K50: / | Q50: 0 | R50: 64
C51: 31 | K51: / | Q51: 0 | R51: 64
C52: 32 | K52: / | Q52: 0 | R52: 64
C53: 33 | K53: / | Q53: 0 | R53: 64
C54: 34 | K54: / | Q54: 0 | R54: 64
C55: 35 | K55: / | Q55: 0 | R55: 64

Sheet Clean_SA-4_Aug_ Head
A1: SA_4_ID | B1: School_AY_Info_ID | C1: AcdemicMonth
A2: ="34" & C2 & AcademicYear_ID& "" & TSIndex_SchoolID -> 34082014180018001 | B2: =CLEAN(SchoolAY_Info_ID) -> 30201411008018001 | C2: 08
A5: =LEN($A$2) -> 17 | B5: =LEN($B$2) -> 17 | C5: =LEN($C$2) -> 2 | D5: =LEN($D$2) -> 0 | E5: =LEN($E$2) -> 0 | F5: =LEN($F$2) -> 0

Sheet Clean_SA-4_Income_Aug_Detail
A1: \ | B1: SA_4_IncomeID | C1: SA_4_ID | D1: IncomeTitle_ID | E1: Budgetd | F1: Received_Amt_Current
A2: 1 | B2: =SA_4_Aug_ID &A2 -> 340820141800180011 | C2: =SA_4_Aug_ID -> 34082014180018001 | D2: 1 | E2: =BQ!G18 -> 0 | F2: =BQ!H18 -> 748500
A3: 2 | B3: =SA_4_Aug_ID &A3 -> 340820141800180012 | C3: =SA_4_Aug_ID -> 34082014180018001 | D3: 2 | E3: =BQ!G19 -> 0 | F3: =BQ!H19 -> 1050701
A4: 3 | B4: =SA_4_Aug_ID &A4 -> 340820141800180013 | C4: =SA_4_Aug_ID -> 34082014180018001 | D4: 3 | E4: =BQ!G20 -> 0 | F4: =BQ!H20 -> 1799201
A5: 4 | B5: =SA_4_Aug_ID &A5 -> 340820141800180014 | C5: =SA_4_Aug_ID -> 34082014180018001 | D5: 4 | E5: =BQ!G21 -> 0 | F5: =BQ!H21 -> 0
A6: 5 | B6: =SA_4_Aug_ID &A6 -> 340820141800180015 | C6: =SA_4_Aug_ID -> 34082014180018001 | D6: 5 | E6: =BQ!G23 -> 0 | F6: =BQ!H23 -> 3598402
A7: 6 | B7: =SA_4_Aug_ID &A7 -> 340820141800180016 | C7: =SA_4_Aug_ID -> 34082014180018001 | D7: 6 | E7: =BQ!G24 -> 0 | F7: =BQ!H24 -> 0
A8: 7 | B8: =SA_4_Aug_ID &A8 -> 340820141800180017 | C8: =SA_4_Aug_ID -> 34082014180018001 | D8: 7 | E8: =BQ!G25 -> 0 | F8: =BQ!H25 -> 0
A9: 8 | B9: =SA_4_Aug_ID &A9 -> 340820141800180018 | C9: =SA_4_Aug_ID -> 34082014180018001 | D9: 8 | E9: =BQ!G26 -> 0 | F9: =BQ!H26 -> 0
A10: 9 | B10: =SA_4_Aug_ID &A10 -> 340820141800180019 | C10: =SA_4_Aug_ID -> 34082014180018001 | D10: 9 | E10: =BQ!G28 -> 0 | F10: =BQ!H28 -> 0
A11: 10 | B11: =SA_4_Aug_ID &A11 -> 3408201418001800110 | C11: =SA_4_Aug_ID -> 34082014180018001 | D11: 10 | E11: =BQ!G29 -> Budgeted Amount | F11: =BQ!H29 -> Expenditure Amount
A12: 11 | B12: =SA_4_Aug_ID &A12 -> 3408201418001800111 | C12: =SA_4_Aug_ID -> 34082014180018001 | D12: 11 | E12: =BQ!G30 -> 0 | F12: =BQ!H30 -> 0
A13: 12 | B13: =SA_4_Aug_ID &A13 -> 3408201418001800112 | C13: =SA_4_Aug_ID -> 34082014180018001 | D13: 12 | E13: =BQ!G31 -> 0 | F13: =BQ!H31 -> 0
A16: =LEN($A$2) -> 1 | B16: =LEN($B$2) -> 18 | C16: =LEN($C$2) -> 17 | D16: =LEN($D$2) -> 1 | E16: =LEN($E$2) -> 1 | F16: =LEN($F$2) -> 6

Sheet Clean_SA-4_Expend_Aug_Detail
A1: id | B1: SA_4_Expenditure_ID | C1: SA_4_ID | D1: ExpenseTitle_ID | E1: ExpenseSubTitle_ID | F1: ExpenseSubTitle_Name | G1: Budget_Amt_Current | H1: Expenditure_Amt_Current
A2: 40 | B2: =SA_4_Aug_ID&A2 -> 3408201418001800140 | C2: =SA_4_Aug_ID -> 34082014180018001 | D2: Ordinary | E2: =BQ!$E29 -> 0 | F2: =BQ!$F29 -> Item | G2: =BQ!$G29 -> Budgeted Amount | H2: =BQ!$H29 -> Expenditure Amount
A3: =$A2+1 -> 41 | B3: =SA_4_Aug_ID&A3 -> 3408201418001800141 | C3: =SA_4_Aug_ID -> 34082014180018001 | D3: Ordinary | E3: =BQ!$E30 -> 0101 | F3: =BQ!$F30 -> 0 | G3: =BQ!$G30 -> 0 | H3: =BQ!$H30 -> 0
A4: =$A3+1 -> 42 | B4: =SA_4_Aug_ID&A4 -> 3408201418001800142 | C4: =SA_4_Aug_ID -> 34082014180018001 | D4: Ordinary | E4: =BQ!$E31 -> 0102 | F4: =BQ!$F31 -> 0 | G4: =BQ!$G31 -> 0 | H4: =BQ!$H31 -> 0
A5: =$A4+1 -> 43 | B5: =SA_4_Aug_ID&A5 -> 3408201418001800143 | C5: =SA_4_Aug_ID -> 34082014180018001 | D5: Ordinary | E5: =BQ!$E32 -> 0103 | F5: =BQ!$F32 -> 0 | G5: =BQ!$G32 -> 0 | H5: =BQ!$H32 -> 0
A6: =$A5+1 -> 44 | B6: =SA_4_Aug_ID&A6 -> 3408201418001800144 | C6: =SA_4_Aug_ID -> 34082014180018001 | D6: Ordinary | E6: =BQ!$E33 -> 0104 | F6: =BQ!$F33 -> 0 | G6: =BQ!$G33 -> 0 | H6: =BQ!$H33 -> 0
A7: =$A6+1 -> 45 | B7: =SA_4_Aug_ID&A7 -> 3408201418001800145 | C7: =SA_4_Aug_ID -> 34082014180018001 | D7: Ordinary | E7: =BQ!$E34 -> Item 01 Total | F7: =BQ!$F34 -> 0 | G7: =BQ!$G34 -> 0 | H7: =BQ!$H34 -> 0
A8: =$A7+1 -> 46 | B8: =SA_4_Aug_ID&A8 -> 3408201418001800146 | C8: =SA_4_Aug_ID -> 34082014180018001 | D8: Ordinary | E8: =BQ!$E35 -> 0201 | F8: =BQ!$F35 -> 0 | G8: =BQ!$G35 -> 0 | H8: =BQ!$H35 -> 0
A9: =$A8+1 -> 47 | B9: =SA_4_Aug_ID&A9 -> 3408201418001800147 | C9: =SA_4_Aug_ID -> 34082014180018001 | D9: Ordinary | E9: =BQ!$E36 -> 0202 | F9: =BQ!$F36 -> 0 | G9: =BQ!$G36 -> 0 | H9: =BQ!$H36 -> 0
A10: =$A9+1 -> 48 | B10: =SA_4_Aug_ID&A10 -> 3408201418001800148 | C10: =SA_4_Aug_ID -> 34082014180018001 | D10: Ordinary | E10: =BQ!$E37 -> 0203 | F10: =BQ!$F37 -> 0 | G10: =BQ!$G37 -> 0 | H10: =BQ!$H37 -> 0
A11: =$A10+1 -> 49 | B11: =SA_4_Aug_ID&A11 -> 3408201418001800149 | C11: =SA_4_Aug_ID -> 34082014180018001 | D11: Ordinary | E11: =BQ!$E38 -> 0204 | F11: =BQ!$F38 -> 0 | G11: =BQ!$G38 -> 0 | H11: =BQ!$H38 -> 0
A12: =$A11+1 -> 50 | B12: =SA_4_Aug_ID&A12 -> 3408201418001800150 | C12: =SA_4_Aug_ID -> 34082014180018001 | D12: Ordinary | E12: =BQ!$E39 -> Item 02 Total | F12: =BQ!$F39 -> 0 | G12: =BQ!$G39 -> 0 | H12: =BQ!$H39 -> 0
A13: =$A12+1 -> 51 | B13: =SA_4_Aug_ID&A13 -> 3408201418001800151 | C13: =SA_4_Aug_ID -> 34082014180018001 | D13: Ordinary | E13: =BQ!$E40 -> 0301 | F13: =BQ!$F40 -> 0 | G13: =BQ!$G40 -> 0 | H13: =BQ!$H40 -> 260000
A14: =$A13+1 -> 52 | B14: =SA_4_Aug_ID&A14 -> 3408201418001800152 | C14: =SA_4_Aug_ID -> 34082014180018001 | D14: Ordinary | E14: =BQ!$E41 -> 0302 | F14: =BQ!$F41 -> 0 | G14: =BQ!$G41 -> 0 | H14: =BQ!$H41 -> 0
A15: =$A14+1 -> 53 | B15: =SA_4_Aug_ID&A15 -> 3408201418001800153 | C15: =SA_4_Aug_ID -> 34082014180018001 | D15: Ordinary | E15: =BQ!$E68 -> 0329 | F15: =BQ!$F68 -> 0 | G15: =BQ!$G68 -> 0 | H15: =BQ!$H68 -> 0
A16: =$A15+1 -> 54 | B16: =SA_4_Aug_ID&A16 -> 3408201418001800154 | C16: =SA_4_Aug_ID -> 34082014180018001 | D16: Ordinary | E16: =BQ!$E69 -> 0330 | F16: =BQ!$F69 -> 0 | G16: =BQ!$G69 -> 0 | H16: =BQ!$H69 -> 0
A17: =$A16+1 -> 55 | B17: =SA_4_Aug_ID&A17 -> 3408201418001800155 | C17: =SA_4_Aug_ID -> 34082014180018001 | D17: Ordinary | E17: =BQ!$E70 -> Item 03 Total | F17: =BQ!$F70 -> 0 | G17: =BQ!$G70 -> 0 | H17: =BQ!$H70 -> 1954075
A18: =$A17+1 -> 56 | B18: =SA_4_Aug_ID&A18 -> 3408201418001800156 | C18: =SA_4_Aug_ID -> 34082014180018001 | D18: LumpSum | E18: =BQ!$E106 -> 0 | F18: =BQ!$F106 -> 0 | G18: =BQ!$G106 -> 0 | H18: =BQ!$H106 -> 0
A19: =$A18+1 -> 57 | B19: =SA_4_Aug_ID&A19 -> 3408201418001800157 | C19: =SA_4_Aug_ID -> 34082014180018001 | D19: LumpSum | E19: =E18 -> 0 | F19: =BQ!$F108 -> (၄၀ X ၃၀)ပေ(၁)ထပ် | G19: =BQ!$H108 -> 0 | H19: =BQ!$J108 -> 0
A20: =$A19+1 -> 58 | B20: =SA_4_Aug_ID&A20 -> 3408201418001800158 | C20: =SA_4_Aug_ID -> 34082014180018001 | D20: LumpSum | E20: =E19 -> 0 | F20: =BQ!$F109 -> (၄၀ X ၃၀)ပေ(၂)ထပ် | G20: =BQ!$H109 -> 0 | H20: =BQ!$J109 -> 0
A21: =$A20+1 -> 59 | B21: =SA_4_Aug_ID&A21 -> 3408201418001800159 | C21: =SA_4_Aug_ID -> 34082014180018001 | D21: LumpSum | E21: =E20 -> 0 | F21: =BQ!$F110 -> (၆၀ X ၃၀)ပေ(၁)ထပ် | G21: =BQ!$H110 -> 0 | H21: =BQ!$J110 -> 0
A22: =$A21+1 -> 60 | B22: =SA_4_Aug_ID&A22 -> 3408201418001800160 | C22: =SA_4_Aug_ID -> 34082014180018001 | D22: LumpSum | E22: =E21 -> 0 | F22: =BQ!$F111 -> (၆၀ X ၃၀)ပေ(၂)ထပ် | G22: =BQ!$H111 -> 0 | H22: =BQ!$J111 -> 0
A23: =$A22+1 -> 61 | B23: =SA_4_Aug_ID&A23 -> 3408201418001800161 | C23: =SA_4_Aug_ID -> 34082014180018001 | D23: LumpSum | E23: =E22 -> 0 | F23: =BQ!$F112 -> (၈၀ X ၃၀)ပေ(၁)ထပ် | G23: =BQ!$H112 -> 0 | H23: =BQ!$J112 -> 0
A24: =$A23+1 -> 62 | B24: =SA_4_Aug_ID&A24 -> 3408201418001800162 | C24: =SA_4_Aug_ID -> 34082014180018001 | D24: LumpSum | E24: =E23 -> 0 | F24: =BQ!$F113 -> (၈၀ X ၃၀)ပေ(၂)ထပ် | G24: =BQ!$H113 -> 0 | H24: =BQ!$J113 -> 0
A25: =$A24+1 -> 63 | B25: =SA_4_Aug_ID&A25 -> 3408201418001800163 | C25: =SA_4_Aug_ID -> 34082014180018001 | D25: LumpSum | E25: =E24 -> 0 | F25: =BQ!$F114 -> (၉၀ X ၃၀)ပေ(၁)ထပ် | G25: =BQ!$H114 -> 0 | H25: =BQ!$J114 -> 0
A26: =$A25+1 -> 64 | B26: =SA_4_Aug_ID&A26 -> 3408201418001800164 | C26: =SA_4_Aug_ID -> 34082014180018001 | D26: LumpSum | E26: =E25 -> 0 | F26: =BQ!$F115 -> (၉၀ X ၃၀)ပေ(၂)ထပ် | G26: =BQ!$H115 -> 0 | H26: =BQ!$J115 -> 0
A27: =$A26+1 -> 65 | B27: =SA_4_Aug_ID&A27 -> 3408201418001800165 | C27: =SA_4_Aug_ID -> 34082014180018001 | D27: LumpSum | E27: =E26 -> 0 | F27: =BQ!#REF! -> #REF! | G27: =BQ!#REF! -> #REF! | H27: =BQ!#REF! -> #REF!
A28: =$A27+1 -> 66 | B28: =SA_4_Aug_ID&A28 -> 3408201418001800166 | C28: =SA_4_Aug_ID -> 34082014180018001 | D28: LumpSum | E28: =E27 -> 0 | F28: =BQ!$F116 -> (၁၀၀ X ၃၀)ပေ(၁)ထပ် | G28: =BQ!$H116 -> 0 | H28: =BQ!$J116 -> 0
A29: =$A28+1 -> 67 | B29: =SA_4_Aug_ID&A29 -> 3408201418001800167 | C29: =SA_4_Aug_ID -> 34082014180018001 | D29: LumpSum | E29: =E28 -> 0 | F29: =BQ!$F117 -> (၁၀၀ X ၃၀)ပေ(၂)ထပ် | G29: =BQ!$H117 -> 0 | H29: =BQ!$J117 -> 0
A30: =$A29+1 -> 68 | B30: =SA_4_Aug_ID&A30 -> 3408201418001800168 | C30: =SA_4_Aug_ID -> 34082014180018001 | D30: LumpSum | E30: =E29 -> 0 | F30: =BQ!#REF! -> #REF! | G30: =BQ!#REF! -> #REF! | H30: =BQ!#REF! -> #REF!
A31: =$A30+1 -> 69 | B31: =SA_4_Aug_ID&A31 -> 3408201418001800169 | C31: =SA_4_Aug_ID -> 34082014180018001 | D31: LumpSum | E31: =E30 -> 0 | F31: =BQ!#REF! -> #REF! | G31: =BQ!#REF! -> #REF! | H31: =BQ!#REF! -> #REF!
A32: =$A31+1 -> 70 | B32: =SA_4_Aug_ID&A32 -> 3408201418001800170 | C32: =SA_4_Aug_ID -> 34082014180018001 | D32: LumpSum | E32: =E31 -> 0 | F32: =BQ!$F119 -> (၁၂၀ X ၃၀)ပေ(၂)ထပ် | G32: =BQ!$H119 -> 0 | H32: =BQ!$J119 -> 0
A33: =$A32+1 -> 71 | B33: =SA_4_Aug_ID&A33 -> 3408201418001800171 | C33: =SA_4_Aug_ID -> 34082014180018001 | D33: LumpSum | E33: =E32 -> 0 | F33: =BQ!$F122 -> 0 | G33: =BQ!$H122 -> 0 | H33: =BQ!$J122 -> 0
A34: =$A33+1 -> 72 | B34: =SA_4_Aug_ID&A34 -> 3408201418001800172 | C34: =SA_4_Aug_ID -> 34082014180018001 | D34: LumpSum | E34: =E33 -> 0 | F34: =BQ!$F123 -> (၁)ယောက်ထိုင်ခုံ | G34: =BQ!$H123 -> 0 | H34: =BQ!$J123 -> 0
A35: =$A34+1 -> 73 | B35: =SA_4_Aug_ID&A35 -> 3408201418001800173 | C35: =SA_4_Aug_ID -> 34082014180018001 | D35: LumpSum | E35: =E34 -> 0 | F35: =BQ!$F130 -> (၄)ယောက်စာရေးခုံ | G35: =BQ!$H130 -> 0 | H35: =BQ!$J130 -> 0
A36: =$A35+1 -> 74 | B36: =SA_4_Aug_ID&A36 -> 3408201418001800174 | C36: =SA_4_Aug_ID -> 34082014180018001 | D36: LumpSum | E36: =E35 -> 0 | F36: =BQ!$F131 -> 0 | G36: =BQ!$H131 -> 0 | H36: =BQ!$J131 -> 0
A37: =$A36+1 -> 75 | B37: =SA_4_Aug_ID&A37 -> 3408201418001800175 | C37: =SA_4_Aug_ID -> 34082014180018001 | D37: LumpSum | E37: =E36 -> 0 | F37: =BQ!$F133 -> 0 | G37: =BQ!$H133 -> 0 | H37: =BQ!$J133 -> 0
A38: =$A37+1 -> 76 | B38: =SA_4_Aug_ID&A38 -> 3408201418001800176 | C38: =SA_4_Aug_ID -> 34082014180018001 | D38: LumpSum | E38: =E37 -> 0 | F38: =BQ!$F134 -> 0 | G38: =BQ!$H134 -> 0 | H38: =BQ!$J134 -> 0
A39: =$A38+1 -> 77 | B39: =SA_4_Aug_ID&A39 -> 3408201418001800177 | C39: =SA_4_Aug_ID -> 34082014180018001 | D39: LumpSum | E39: =E38 -> 0 | F39: =BQ!$F135 -> 0 | G39: =BQ!$H135 -> 0 | H39: =BQ!$J135 -> 0
A40: =$A39+1 -> 78 | B40: =SA_4_Aug_ID&A40 -> 3408201418001800178 | C40: =SA_4_Aug_ID -> 34082014180018001 | D40: LumpSum | E40: =E39 -> 0 | F40: =BQ!$F136 -> 0 | G40: =BQ!$H136 -> 0 | H40: =BQ!$J136 -> 0
A41: =$A40+1 -> 79 | B41: =SA_4_Aug_ID&A41 -> 3408201418001800179 | C41: =SA_4_Aug_ID -> 34082014180018001 | D41: LumpSum | E41: =E40 -> 0 | F41: =BQ!#REF! -> #REF! | G41: =BQ!#REF! -> #REF! | H41: =BQ!#REF! -> #REF!
A42: =$A41+1 -> 80 | B42: =SA_4_Aug_ID&A42 -> 3408201418001800180 | C42: =SA_4_Aug_ID -> 34082014180018001 | D42: LumpSum | E42: =E41 -> 0 | F42: =BQ!$F138 -> 0 | G42: =BQ!$H138 -> 0 | H42: =BQ!$J138 -> 0
A43: =$A42+1 -> 81 | B43: =SA_4_Aug_ID&A43 -> 3408201418001800181 | C43: =SA_4_Aug_ID -> 34082014180018001 | D43: LumpSum | E43: =E42 -> 0 | F43: =BQ!$F139 -> 0 | G43: =BQ!$H139 -> 0 | H43: =BQ!$J139 -> 0
A44: =$A43+1 -> 82 | B44: =SA_4_Aug_ID&A44 -> 3408201418001800182 | C44: =SA_4_Aug_ID -> 34082014180018001 | D44: LumpSum | E44: =E43 -> 0 | F44: =BQ!$F140 -> 0 | G44: =BQ!$H140 -> 0 | H44: =BQ!$J140 -> 0
A45: =$A44+1 -> 83 | B45: =SA_4_Aug_ID&A45 -> 3408201418001800183 | C45: =SA_4_Aug_ID -> 34082014180018001 | D45: LumpSum | E45: =E44 -> 0 | F45: =BQ!$F141 -> 0 | G45: =BQ!$H141 -> 0 | H45: =BQ!$J141 -> 0
A46: =$A45+1 -> 84 | B46: =SA_4_Aug_ID&A46 -> 3408201418001800184 | C46: =SA_4_Aug_ID -> 34082014180018001 | D46: LumpSum | E46: =E45 -> 0 | F46: =BQ!$F142 -> 0 | G46: =BQ!$H142 -> 0 | H46: =BQ!$J142 -> 0
A47: =$A46+1 -> 85 | B47: =SA_4_Aug_ID&A47 -> 3408201418001800185 | C47: =SA_4_Aug_ID -> 34082014180018001 | D47: LumpSum | E47: =E46 -> 0 | F47: =BQ!$F143 -> 0 | G47: =BQ!$H143 -> 0 | H47: =BQ!$J143 -> 0
A48: =$A47+1 -> 86 | B48: =SA_4_Aug_ID&A48 -> 3408201418001800186 | C48: =SA_4_Aug_ID -> 34082014180018001 | D48: LumpSum | E48: =E47 -> 0 | F48: =BQ!$F144 -> 0 | G48: =BQ!$H144 -> 0 | H48: =BQ!$J144 -> 0
A49: =$A48+1 -> 87 | B49: =SA_4_Aug_ID&A49 -> 3408201418001800187 | C49: =SA_4_Aug_ID -> 34082014180018001 | D49: LumpSum | E49: =E48 -> 0 | F49: =BQ!$F145 -> 0 | G49: =BQ!$H145 -> 0 | H49: =BQ!$J145 -> 0
A50: =$A49+1 -> 88 | B50: =SA_4_Aug_ID&A50 -> 3408201418001800188 | C50: =SA_4_Aug_ID -> 34082014180018001 | D50: LumpSum | E50: =E49 -> 0 | F50: =BQ!$F146 -> 0 | G50: =BQ!$G146 -> 0 | H50: =BQ!$J146 -> 0
A51: =$A50+1 -> 89 | B51: =SA_4_Aug_ID&A51 -> 3408201418001800189 | C51: =SA_4_Aug_ID -> 34082014180018001 | D51: LumpSum | E51: =E50 -> 0 | F51: =BQ!$F147 -> 0 | G51: =BQ!$G147 -> 0 | H51: =BQ!$J147 -> 2019075
A52: =$A51+1 -> 90 | B52: =SA_4_Aug_ID&A52 -> 3408201418001800190 | C52: =SA_4_Aug_ID -> 34082014180018001 | D52: LumpSum | E52: =E51 -> 0 | F52: =BQ!$F148 -> 0 | G52: =BQ!$G148 -> 0 | H52: =BQ!$H148 -> 0
A53: =$A52+1 -> 91 | B53: =SA_4_Aug_ID&A53 -> 3408201418001800191 | C53: =SA_4_Aug_ID -> 34082014180018001 | D53: LumpSum | E53: =E52 -> 0 | F53: =BQ!$F149 -> 0 | G53: =BQ!$G149 -> 0 | H53: =BQ!$H149 -> 0
A54: =$A53+1 -> 92 | B54: =SA_4_Aug_ID&A54 -> 3408201418001800192 | C54: =SA_4_Aug_ID -> 34082014180018001 | D54: LumpSum | E54: =E53 -> 0 | F54: =BQ!$F150 -> 0 | G54: =BQ!$G150 -> 0 | H54: =BQ!#REF! -> #REF!
A55: =$A54+1 -> 93 | B55: =SA_4_Aug_ID&A55 -> 3408201418001800193 | C55: =SA_4_Aug_ID -> 34082014180018001 | D55: LumpSum | E55: =E54 -> 0 | F55: =BQ!$F151 -> 0 | G55: =BQ!$G151 -> 0 | H55: =BQ!$M5 -> Paper Form Signed By
A56: =$A55+1 -> 94 | B56: =SA_4_Aug_ID&A56 -> 3408201418001800194 | C56: =SA_4_Aug_ID -> 34082014180018001 | D56: LumpSum | E56: =E55 -> 0 | F56: =BQ!$F152 -> 0 | G56: =BQ!$G152 -> 0 | H56: =BQ!$M7 -> Name
A57: =$A56+1 -> 95 | B57: =SA_4_Aug_ID&A57 -> 3408201418001800195 | C57: =SA_4_Aug_ID -> 34082014180018001 | D57: LumpSum | E57: =E56 -> 0 | F57: =BQ!$F153 -> 0 | G57: =BQ!$G153 -> 0 | H57: =BQ!$M9 -> Office Post
A58: =$A57+1 -> 96 | B58: =SA_4_Aug_ID&A58 -> 3408201418001800196 | C58: =SA_4_Aug_ID -> 34082014180018001 | D58: LumpSum | E58: =E57 -> 0 | F58: =BQ!$F154 -> 0 | G58: =BQ!$G154 -> 0 | H58: =BQ!$M10 -> Signed Date (DD/MM/YYYY)
A62: =LEN($A$2) -> 2 | B62: =LEN($B$2) -> 19 | C62: =LEN($C$2) -> 17 | D62: =LEN($D$2) -> 8 | E62: =LEN($E$2) -> 1 | F62: =LEN($F$2) -> 4

Sheet Clean_SA-4_Aug_Signed
A1: SA_4_ID | B1: SignedName_31 | C1: SignedPost_31 | D1: SignedDate_31
A2: =SA_4_Aug_ID -> 34082014180018001 | B2: =CLEAN(BQ!N7) -> ငွေဝင်း | C2: =FormPost_34_Aug -> 7 | D2: =BQ!N10 -> 41768
A5: =LEN($A$2) -> 17 | B5: =LEN($B$2) -> 7 | C5: =LEN($C$2) -> 1 | D5: =LEN($D$2) -> 5 | E5: =LEN($E$2) -> 0 | F5: =LEN($F$2) -> 0

Sheet Clean_SA-4_Nov_ Head
A1: SA_4_ID | B1: School_AY_Info_ID | C1: AcdemicMonth
A2: ="34" & C2 & AcademicYear_ID& "" & TSIndex_SchoolID -> 34112014180018001 | B2: =CLEAN(SchoolAY_Info_ID) -> 30201411008018001 | C2: 11
A5: =LEN($A$2) -> 17 | B5: =LEN($B$2) -> 17 | C5: =LEN($C$2) -> 2 | D5: =LEN($D$2) -> 0 | E5: =LEN($E$2) -> 0 | F5: =LEN($F$2) -> 0

Sheet Clean_SA-4_Income_Nov_Detail
B1: SA_4_IncomeID | C1: SA_4_ID | D1: IncomeTitle_ID | E1: Budgetd | F1: Received_Amt_Current
A2: 1 | B2: =SA_4_Nov_ID &A2 -> 341120141800180011 | C2: =SA_4_Nov_ID -> 34112014180018001 | D2: 1 | E2: =#REF! -> #REF! | F2: =#REF! -> #REF!
A3: 2 | B3: =SA_4_Nov_ID &A3 -> 341120141800180012 | C3: =SA_4_Nov_ID -> 34112014180018001 | D3: 2 | E3: =#REF! -> #REF! | F3: =#REF! -> #REF!
A4: 3 | B4: =SA_4_Nov_ID &A4 -> 341120141800180013 | C4: =SA_4_Nov_ID -> 34112014180018001 | D4: 3 | E4: =#REF! -> #REF! | F4: =#REF! -> #REF!
A5: 4 | B5: =SA_4_Nov_ID &A5 -> 341120141800180014 | C5: =SA_4_Nov_ID -> 34112014180018001 | D5: 4 | E5: =#REF! -> #REF! | F5: =#REF! -> #REF!
A6: 5 | B6: =SA_4_Nov_ID &A6 -> 341120141800180015 | C6: =SA_4_Nov_ID -> 34112014180018001 | D6: 5 | E6: =#REF! -> #REF! | F6: =#REF! -> #REF!
A7: 6 | B7: =SA_4_Nov_ID &A7 -> 341120141800180016 | C7: =SA_4_Nov_ID -> 34112014180018001 | D7: 6 | E7: =#REF! -> #REF! | F7: =#REF! -> #REF!
A8: 7 | B8: =SA_4_Nov_ID &A8 -> 341120141800180017 | C8: =SA_4_Nov_ID -> 34112014180018001 | D8: 7 | E8: =#REF! -> #REF! | F8: =#REF! -> #REF!
A9: 8 | B9: =SA_4_Nov_ID &A9 -> 341120141800180018 | C9: =SA_4_Nov_ID -> 34112014180018001 | D9: 8 | E9: =#REF! -> #REF! | F9: =#REF! -> #REF!
A10: 9 | B10: =SA_4_Nov_ID &A10 -> 341120141800180019 | C10: =SA_4_Nov_ID -> 34112014180018001 | D10: 9 | E10: =#REF! -> #REF! | F10: =#REF! -> #REF!
A11: 10 | B11: =SA_4_Nov_ID &A11 -> 3411201418001800110 | C11: =SA_4_Nov_ID -> 34112014180018001 | D11: 10 | E11: =#REF! -> #REF! | F11: =#REF! -> #REF!
A12: 11 | B12: =SA_4_Nov_ID &A12 -> 3411201418001800111 | C12: =SA_4_Nov_ID -> 34112014180018001 | D12: 11 | E12: =#REF! -> #REF! | F12: =#REF! -> #REF!
A13: 12 | B13: =SA_4_Nov_ID &A13 -> 3411201418001800112 | C13: =SA_4_Nov_ID -> 34112014180018001 | D13: 12 | E13: =#REF! -> #REF! | F13: =#REF! -> #REF!
A16: =LEN($A$2) -> 1 | B16: =LEN($B$2) -> 18 | C16: =LEN($C$2) -> 17 | D16: =LEN($D$2) -> 1 | E16: =LEN($E$2) -> #REF! | F16: =LEN($F$2) -> #REF!

Sheet Clean_SA-4_Expend_Nov_Detail
A1: id | B1: SA_4_Expenditure_ID | C1: SA_4_ID | D1: ExpenseTitle_ID | E1: ExpenseSubTitle_ID | F1: ExpenseSubTitle_Name | G1: Budget_Amt_Current | H1: Expenditure_Amt_Current
A2: 40 | B2: =SA_4_Nov_ID&A2 -> 3411201418001800140 | C2: =SA_4_Nov_ID -> 34112014180018001 | D2: Ordinary | E2: =#REF! -> #REF! | F2: =#REF! -> #REF! | G2: =#REF! -> #REF! | H2: =#REF! -> #REF!
A3: =$A2+1 -> 41 | B3: =SA_4_Nov_ID&A3 -> 3411201418001800141 | C3: =SA_4_Nov_ID -> 34112014180018001 | D3: Ordinary | E3: =#REF! -> #REF! | F3: =#REF! -> #REF! | G3: =#REF! -> #REF! | H3: =#REF! -> #REF!
A4: =$A3+1 -> 42 | B4: =SA_4_Nov_ID&A4 -> 3411201418001800142 | C4: =SA_4_Nov_ID -> 34112014180018001 | D4: Ordinary | E4: =#REF! -> #REF! | F4: =#REF! -> #REF! | G4: =#REF! -> #REF! | H4: =#REF! -> #REF!
A5: =$A4+1 -> 43 | B5: =SA_4_Nov_ID&A5 -> 3411201418001800143 | C5: =SA_4_Nov_ID -> 34112014180018001 | D5: Ordinary | E5: =#REF! -> #REF! | F5: =#REF! -> #REF! | G5: =#REF! -> #REF! | H5: =#REF! -> #REF!
A6: =$A5+1 -> 44 | B6: =SA_4_Nov_ID&A6 -> 3411201418001800144 | C6: =SA_4_Nov_ID -> 34112014180018001 | D6: Ordinary | E6: =#REF! -> #REF! | F6: =#REF! -> #REF! | G6: =#REF! -> #REF! | H6: =#REF! -> #REF!
A7: =$A6+1 -> 45 | B7: =SA_4_Nov_ID&A7 -> 3411201418001800145 | C7: =SA_4_Nov_ID -> 34112014180018001 | D7: Ordinary | E7: =#REF! -> #REF! | F7: =#REF! -> #REF! | G7: =#REF! -> #REF! | H7: =#REF! -> #REF!
A8: =$A7+1 -> 46 | B8: =SA_4_Nov_ID&A8 -> 3411201418001800146 | C8: =SA_4_Nov_ID -> 34112014180018001 | D8: Ordinary | E8: =#REF! -> #REF! | F8: =#REF! -> #REF! | G8: =#REF! -> #REF! | H8: =#REF! -> #REF!
A9: =$A8+1 -> 47 | B9: =SA_4_Nov_ID&A9 -> 3411201418001800147 | C9: =SA_4_Nov_ID -> 34112014180018001 | D9: Ordinary | E9: =#REF! -> #REF! | F9: =#REF! -> #REF! | G9: =#REF! -> #REF! | H9: =#REF! -> #REF!
A10: =$A9+1 -> 48 | B10: =SA_4_Nov_ID&A10 -> 3411201418001800148 | C10: =SA_4_Nov_ID -> 34112014180018001 | D10: Ordinary | E10: =#REF! -> #REF! | F10: =#REF! -> #REF! | G10: =#REF! -> #REF! | H10: =#REF! -> #REF!
A11: =$A10+1 -> 49 | B11: =SA_4_Nov_ID&A11 -> 3411201418001800149 | C11: =SA_4_Nov_ID -> 34112014180018001 | D11: Ordinary | E11: =#REF! -> #REF! | F11: =#REF! -> #REF! | G11: =#REF! -> #REF! | H11: =#REF! -> #REF!
A12: =$A11+1 -> 50 | B12: =SA_4_Nov_ID&A12 -> 3411201418001800150 | C12: =SA_4_Nov_ID -> 34112014180018001 | D12: Ordinary | E12: =#REF! -> #REF! | F12: =#REF! -> #REF! | G12: =#REF! -> #REF! | H12: =#REF! -> #REF!
A13: =$A12+1 -> 51 | B13: =SA_4_Nov_ID&A13 -> 3411201418001800151 | C13: =SA_4_Nov_ID -> 34112014180018001 | D13: Ordinary | E13: =#REF! -> #REF! | F13: =#REF! -> #REF! | G13: =#REF! -> #REF! | H13: =#REF! -> #REF!
A14: =$A13+1 -> 52 | B14: =SA_4_Nov_ID&A14 -> 3411201418001800152 | C14: =SA_4_Nov_ID -> 34112014180018001 | D14: Ordinary | E14: =#REF! -> #REF! | F14: =#REF! -> #REF! | G14: =#REF! -> #REF! | H14: =#REF! -> #REF!
... A18: =$A17+1 -> 56 | B18: =SA_4_Nov_ID&A18 -> 3411201418001800156 | C18: =SA_4_Nov_ID -> 34112014180018001 | D18: LumpSum | E18: =#REF! -> #REF! | F18: =#REF! -> #REF! | G18: =#REF! -> #REF! | H18: =#REF! -> #REF!
A19: =$A18+1 -> 57 | B19: =SA_4_Nov_ID&A19 -> 3411201418001800157 | C19: =SA_4_Nov_ID -> 34112014180018001 | D19: LumpSum | E19: =E18 -> #REF! | F19: =#REF! -> #REF! | G19: =#REF! -> #REF! | H19: =#REF! -> #REF!
A20: =$A19+1 -> 58 | B20: =SA_4_Nov_ID&A20 -> 3411201418001800158 | C20: =SA_4_Nov_ID -> 34112014180018001 | D20: LumpSum | E20: =E19 -> #REF! | F20: =#REF! -> #REF! | G20: =#REF! -> #REF! | H20: =#REF! -> #REF!
A21: =$A20+1 -> 59 | B21: =SA_4_Nov_ID&A21 -> 3411201418001800159 | C21: =SA_4_Nov_ID -> 34112014180018001 | D21: LumpSum | E21: =E20 -> #REF! | F21: =#REF! -> #REF! | G21: =#REF! -> #REF! | H21: =#REF! -> #REF!
A22: =$A21+1 -> 60 | B22: =SA_4_Nov_ID&A22 -> 3411201418001800160 | C22: =SA_4_Nov_ID -> 34112014180018001 | D22: LumpSum | E22: =E21 -> #REF! | F22: =#REF! -> #REF! | G22: =#REF! -> #REF! | H22: =#REF! -> #REF!
A23: =$A22+1 -> 61 | B23: =SA_4_Nov_ID&A23 -> 3411201418001800161 | C23: =SA_4_Nov_ID -> 34112014180018001 | D23: LumpSum | E23: =E22 -> #REF! | F23: =#REF! -> #REF! | G23: =#REF! -> #REF! | H23: =#REF! -> #REF!
A24: =$A23+1 -> 62 | B24: =SA_4_Nov_ID&A24 -> 3411201418001800162 | C24: =SA_4_Nov_ID -> 34112014180018001 | D24: LumpSum | E24: =E23 -> #REF! | F24: =#REF! -> #REF! | G24: =#REF! -> #REF! | H24: =#REF! -> #REF!
A25: =$A24+1 -> 63 | B25: =SA_4_Nov_ID&A25 -> 3411201418001800163 | C25: =SA_4_Nov_ID -> 34112014180018001 | D25: LumpSum | E25: =E24 -> #REF! | F25: =#REF! -> #REF! | G25: =#REF! -> #REF! | H25: =#REF! -> #REF!
A26: =$A25+1 -> 64 | B26: =SA_4_Nov_ID&A26 -> 3411201418001800164 | C26: =SA_4_Nov_ID -> 34112014180018001 | D26: LumpSum | E26: =E25 -> #REF! | F26: =#REF! -> #REF! | G26: =#REF! -> #REF! | H26: =#REF! -> #REF!
A27: =$A26+1 -> 65 | B27: =SA_4_Nov_ID&A27 -> 3411201418001800165 | C27: =SA_4_Nov_ID -> 34112014180018001 | D27: LumpSum | E27: =E26 -> #REF! | F27: =#REF! -> #REF! | G27: =#REF! -> #REF! | H27: =#REF! -> #REF!
A28: =$A27+1 -> 66 | B28: =SA_4_Nov_ID&A28 -> 3411201418001800166 | C28: =SA_4_Nov_ID -> 34112014180018001 | D28: LumpSum | E28: =E27 -> #REF! | F28: =#REF! -> #REF! | G28: =#REF! -> #REF! | H28: =#REF! -> #REF!
A29: =$A28+1 -> 67 | B29: =SA_4_Nov_ID&A29 -> 3411201418001800167 | C29: =SA_4_Nov_ID -> 34112014180018001 | D29: LumpSum | E29: =E28 -> #REF! | F29: =#REF! -> #REF! | G29: =#REF! -> #REF! | H29: =#REF! -> #REF!
A30: =$A29+1 -> 68 | B30: =SA_4_Nov_ID&A30 -> 3411201418001800168 | C30: =SA_4_Nov_ID -> 34112014180018001 | D30: LumpSum | E30: =E29 -> #REF! | F30: =#REF! -> #REF! | G30: =#REF! -> #REF! | H30: =#REF! -> #REF!
... A58: =$A57+1 -> 96 | B58: =SA_4_Nov_ID&A58 -> 3411201418001800196 | C58: =SA_4_Nov_ID -> 34112014180018001 | D58: LumpSum | E58: =E57 -> #REF! | F58: =#REF! -> #REF! | G58: =#REF! -> #REF! | H58: =#REF! -> #REF!
A62: =LEN($A$2) -> 2 | B62: =LEN($B$2) -> 19 | C62: =LEN($C$2) -> 17 | D62: =LEN($D$2) -> 8 | E62: =LEN($E$2) -> #REF! | F62: =LEN($F$2) -> #REF!

Sheet Clean_SA-4_Nov_Signed
A1: SA_4_ID | B1: SignedName_31 | C1: SignedPost_31 | D1: SignedDate_31
A2: =SA_4_Nov_ID -> 34112014180018001 | B2: =CLEAN(#REF!) -> #REF! | C2: =FormPost_34_Nov -> #REF! | D2: =#REF! -> #REF!
A5: =LEN($A$2) -> 17 | B5: =LEN($B$2) -> #REF! | C5: =LEN($C$2) -> #REF! | D5: =LEN($D$2) -> #REF! | E5: =LEN($E$2) -> 0 | F5: =LEN($F$2) -> 0

Sheet Clean_SA-4_Feb_ Head
A1: SA_4_ID | B1: School_AY_Info_ID | C1: AcdemicMonth
A2: ="34" & C2 & AcademicYear_ID& "" & TSIndex_SchoolID -> 34022014180018001 | B2: =CLEAN(SchoolAY_Info_ID) -> 30201411008018001 | C2: 02
A5: =LEN($A$2) -> 17 | B5: =LEN($B$2) -> 17 | C5: =LEN($C$2) -> 2 | D5: =LEN($D$2) -> 0 | E5: =LEN($E$2) -> 0 | F5: =LEN($F$2) -> 0

Sheet Clean_SA-4_Income_Feb_Detail
B1: SA_4_IncomeID | C1: SA_4_ID | D1: IncomeTitle_ID | E1: Budgetd | F1: Received_Amt_Current
A2: 1 | B2: =SA_4_Feb_ID &A2 -> 340220141800180011 | C2: =SA_4_Feb_ID -> 34022014180018001 | D2: 1 | E2: =#REF! -> #REF! | F2: =#REF! -> #REF!
A3: 2 | B3: =SA_4_Feb_ID &A3 -> 340220141800180012 | C3: =SA_4_Feb_ID -> 34022014180018001 | D3: 2 | E3: =#REF! -> #REF! | F3: =#REF! -> #REF!
A4: 3 | B4: =SA_4_Feb_ID &A4 -> 340220141800180013 | C4: =SA_4_Feb_ID -> 34022014180018001 | D4: 3 | E4: =#REF! -> #REF! | F4: =#REF! -> #REF!
A5: 4 | B5: =SA_4_Feb_ID &A5 -> 340220141800180014 | C5: =SA_4_Feb_ID -> 34022014180018001 | D5: 4 | E5: =#REF! -> #REF! | F5: =#REF! -> #REF!
A6: 5 | B6: =SA_4_Feb_ID &A6 -> 340220141800180015 | C6: =SA_4_Feb_ID -> 34022014180018001 | D6: 5 | E6: =#REF! -> #REF! | F6: =#REF! -> #REF!
A7: 6 | B7: =SA_4_Feb_ID &A7 -> 340220141800180016 | C7: =SA_4_Feb_ID -> 34022014180018001 | D7: 6 | E7: =#REF! -> #REF! | F7: =#REF! -> #REF!
A8: 7 | B8: =SA_4_Feb_ID &A8 -> 340220141800180017 | C8: =SA_4_Feb_ID -> 34022014180018001 | D8: 7 | E8: =#REF! -> #REF! | F8: =#REF! -> #REF!
A9: 8 | B9: =SA_4_Feb_ID &A9 -> 340220141800180018 | C9: =SA_4_Feb_ID -> 34022014180018001 | D9: 8 | E9: =#REF! -> #REF! | F9: =#REF! -> #REF!
A10: 9 | B10: =SA_4_Feb_ID &A10 -> 340220141800180019 | C10: =SA_4_Feb_ID -> 34022014180018001 | D10: 9 | E10: =#REF! -> #REF! | F10: =#REF! -> #REF!
A11: 10 | B11: =SA_4_Feb_ID &A11 -> 3402201418001800110 | C11: =SA_4_Feb_ID -> 34022014180018001 | D11: 10 | E11: =#REF! -> #REF! | F11: =#REF! -> #REF!
A12: 11 | B12: =SA_4_Feb_ID &A12 -> 3402201418001800111 | C12: =SA_4_Feb_ID -> 34022014180018001 | D12: 11 | E12: =#REF! -> #REF! | F12: =#REF! -> #REF!
A13: 12 | B13: =SA_4_Feb_ID &A13 -> 3402201418001800112 | C13: =SA_4_Feb_ID -> 34022014180018001 | D13: 12 | E13: =#REF! -> #REF! | F13: =#REF! -> #REF!
A16: =LEN($A$2) -> 1 | B16: =LEN($B$2) -> 18 | C16: =LEN($C$2) -> 17 | D16: =LEN($D$2) -> 1 | E16: =LEN($E$2) -> #REF! | F16: =LEN($F$2) -> #REF!

Sheet Clean_SA-4_Expend_Feb_Detail
A1: id | B1: SA_4_Expenditure_ID | C1: SA_4_ID | D1: ExpenseTitle_ID | E1: ExpenseSubTitle_ID | F1: ExpenseSubTitle_Name | G1: Budget_Amt_Current | H1: Expenditure_Amt_Current
A2: 40 | B2: =SA_4_Feb_ID&A2 -> 3402201418001800140 | C2: =SA_4_Feb_ID -> 34022014180018001 | D2: Ordinary | E2: =#REF! -> #REF! | F2: =#REF! -> #REF! | G2: =#REF! -> #REF! | H2: =#REF! -> #REF!
A3: =$A2+1 -> 41 | B3: =SA_4_Feb_ID&A3 -> 3402201418001800141 | C3: =SA_4_Feb_ID -> 34022014180018001 | D3: Ordinary | E3: =#REF! -> #REF! | F3: =#REF! -> #REF! | G3: =#REF! -> #REF! | H3: =#REF! -> #REF!
A4: =$A3+1 -> 42 | B4: =SA_4_Feb_ID&A4 -> 3402201418001800142 | C4: =SA_4_Feb_ID -> 34022014180018001 | D4: Ordinary | E4: =#REF! -> #REF! | F4: =#REF! -> #REF! | G4: =#REF! -> #REF! | H4: =#REF! -> #REF!
A5: =$A4+1 -> 43 | B5: =SA_4_Feb_ID&A5 -> 3402201418001800143 | C5: =SA_4_Feb_ID -> 34022014180018001 | D5: Ordinary | E5: =#REF! -> #REF! | F5: =#REF! -> #REF! | G5: =#REF! -> #REF! | H5: =#REF! -> #REF!
A6: =$A5+1 -> 44 | B6: =SA_4_Feb_ID&A6 -> 3402201418001800144 | C6: =SA_4_Feb_ID -> 34022014180018001 | D6: Ordinary | E6: =#REF! -> #REF! | F6: =#REF! -> #REF! | G6: =#REF! -> #REF! | H6: =#REF! -> #REF!
A7: =$A6+1 -> 45 | B7: =SA_4_Feb_ID&A7 -> 3402201418001800145 | C7: =SA_4_Feb_ID -> 34022014180018001 | D7: Ordinary | E7: =#REF! -> #REF! | F7: =#REF! -> #REF! | G7: =#REF! -> #REF! | H7: =#REF! -> #REF!
A8: =$A7+1 -> 46 | B8: =SA_4_Feb_ID&A8 -> 3402201418001800146 | C8: =SA_4_Feb_ID -> 34022014180018001 | D8: Ordinary | E8: =#REF! -> #REF! | F8: =#REF! -> #REF! | G8: =#REF! -> #REF! | H8: =#REF! -> #REF!
A9: =$A8+1 -> 47 | B9: =SA_4_Feb_ID&A9 -> 3402201418001800147 | C9: =SA_4_Feb_ID -> 34022014180018001 | D9: Ordinary | E9: =#REF! -> #REF! | F9: =#REF! -> #REF! | G9: =#REF! -> #REF! | H9: =#REF! -> #REF!
